Workbook

Sheet Sessions
A1: SPEAKERS INFORMATION | AT1: SPEAKERS PREFERENCES | BI1: FOLLOW-UP | BM1: Travel information - confirmed | CF1: APPROVALS
A2: Date | B2: Slot | C2: Estimated arrival date | D2: Estimated departure date | E2: Index unique | F2: Title | G2: Thematic clusters | H2: Format | I2: Merged sessions | J2: Merged lead? | K2: Lead partner organisation name | L2: Lead partner organisation country of origin | M2: Associated partners | N2: Coordinator | O2: Email address | P2: Company name | Q2: Job title | R2: Speakers | S2: Answered | T2: Form sent to speakers/reminder to SC | U2: Do any of your speakers require travel coverage? | V2: Number of speakers needed for Travel | W2: Travel - Speaker 1 - Name | X2: Travel - Speaker 1 - Name + last name | Y2: Travel - Speaker 1 - Email address | Z2: Travel - Speaker 2 - Name | AA2: Travel - Speaker 2 - Name + last name | AB2: Travel - Speaker 2 - Email address | AC2: Travel - Speaker 3 - Name | AD2: Travel - Speaker 3 - Name + last name | AE2: Travel - Speaker 3 - Email address | AF2: Do any of your speakers require accommodation coverage? | AG2: Number of speakers needed for Accommodation | AH2: Accomodation - Speaker 1 - Name | AI2: Accomodation - Speaker 1 - Last name | AJ2: Accomodation - Speaker 1 - Email address | AK2: Accomodation - Speaker 2 - Name | AL2: Accomodation - Speaker 2 - Last name | AM2: Accomodation - Speaker 2 - Email address | AN2: Accomodation - Speaker 3 - Name | AO2: Accomodation - Speaker 3 - Last name | AP2: Accomodation - Speaker 3 - Email address | AQ2: Additional comments | AR2: Email follow up - Responses | AS2: Comments VO | AT2: First Name | AU2: Last name | AV2: Email address | AW2: Phone number | AX2: Date and time of your speaking slot | AY2: Travel needed | AZ2: Preferred mode of transport | BA2: City of departure | BB2: Date of departure | BC2: Time of departure | BD2: Return city | BE2: Preferred date of return | BF2: Preferred time of return | BG2: Accommodation needed | BH2: Additional comments | BI2: Agency sent proposal | BJ2: Guest confirmed proposal | BK2: Travel booked | BL2: Travel tickets sent to guest | BM2: Origin City (to Brussels) | BN2: Flight/Train | BO2: Date of departure | BP2: Flight/Train time | BQ2: Flight number/Train | BR2: Return City (from Brussels) | BS2: Date of return | BT2: Flight/Train time | BU2: Flight number/Train | BV2: Flight/Train cost | BW2: 45943 | BX2: 45944 | BY2: 45945 | BZ2: Check-in date | CA2: Check out date | CB2: Hotel name | CC2: Hotel nights | CD2: Hotel cost, €, excl. VAT | CE2: Total cost, € | CF2: Client's approval needed | CG2: Client's approval received | CH2: Approval reason
A3: 45944 | B3: 11:30 - 13:00 | C3: 45943 | D3: 45945 | E3: 1965 | F3: Enabled by Design: Building Risk Communication for People with Disabilities | G3: Cities building tomorrow | H3: Interactive session | J3: No | K3: Climate KIC International Foundation | L3: Netherlands | N3: Michelle Zheng ; Cristobal Reveco | O3: michelle.zheng@climate-kic.org; cristobal.reveco@hereon.de | P3: EIT Climate-KIC | Q3: Officer | R3: Zdeněk HŘIB - - - - ; Štěpán Vizina - - - - ; Georgia KALOUSI - - - - | S3: Yes | T3: YES | U3: No | V3: 0 | AF3: No | AG3: 0 | AQ3: No comment | AY3: No | BG3: No
A4: 45944 | B4: 09:30 - 10:30 | C4: 45943 | D4: 45945 | E4: 1969 | F4: Cities leveraging data for impact – showcasing real-life success stories | G4: Cities building tomorrow | H4: Workshop | I4: 19692590 | J4: Yes | K4: Publications Office of the European Union | L4: Luxembourg | N4: Cecilia Charlier ; Dominika Uhrikova | O4: Cecilia.CHARLIER@publications.europa.eu ; Dominika.UHRIKOVA@ec.europa.eu | P4: Publications Office of the European Union | Q4: Assistant | R4: Mani Dhingra - Dublin City Council - Programme Manager - - ; Carlos MARTINS FERREIRA - Publications Office of the European Union - Assistant - - | S4: yes | T4: YES | U4: Yes | V4: 2 | W4: Mani | X4: Dhingra | Y4: mani@smartd8.ie | Z4: Olaf | AA4: Osica | AB4: olaf.osica@gmail.com | AF4: Yes | AG4: 2 | AH4: Mani | AI4: Dhingra | AJ4: mani@smartd8.ie | AK4: Olaf | AL4: Osica | AM4: olaf.osica@gmail.com | AQ4: We have only 2 speakers to reimburse. As the system didn't allow to submit the form without filling in the 3rd line in each table, I put "n/a" in the third line of each table to say that line is not applicable. | AR4: positive | AS4: They will need t&a for their speaker | AT4: Mani | AU4: Dhingra | AV4: mani@smartd8.ie | AW4: 353892541846 | AX4: 14th Oct 9.30 to 10.30 am | AY4: Yes | AZ4: I prefer to travel by plane | BA4: Dublin | BB4: 45943 | BC4: Between 1 and 4 pm | BD4: Dublin | BE4: 45945 | BF4: Between 12 and 4 pm | BG4: Yes | BH4: Because of strike i would like to come a day early and leave a day later ti avoid 14th October travel day. | BI4: YES | BJ4: YES | BK4: YES | BL4: YES | BM4: Dublin | BN4: Flight | BO4: 45943 | BP4: 0.64236111 | BQ4: fr1452 | BR4: Dublin | BS4: 45945 | BT4: 0.88888889 | BU4: ei639 | BV4: 259.71 | BW4: 1 | BX4: 1 | BZ4: 45943 | CA4: 45945 | CC4: =BW4+BX4+BY4 -> 2
AT5: Olaf | AU5: Osica | AV5: olaf.osica@gmail.com | AW5: 48784939432 | AX5: 14 Oct 09.30 AM | AY5: Yes | AZ5: I prefer to travel by plane | BA5: Warsaw | BB5: 45943 | BC5: 1000 | BD5: Warsaw | BE5: 45945 | BF5: 1500 | BG5: Yes | BH5: Since a national strike has been announced for the 14th of Oct I need to stay one more night after my panel. | BI5: YES | BJ5: YES | BK5: YES | BL5: YES | BM5: Warsaw | BN5: Flight | BO5: 45943 | BP5: 0.43402778 | BQ5: LO237 | BR5: Warsaw | BS5: 45945 | BT5: 0.63888889 | BU5: SN2555 | BV5: 512.02 | BW5: 1 | BX5: 1 | BZ5: 45943 | CA5: 45945 | CC5: =BW5+BX5+BY5 -> 2
A6: 45945 | B6: 11:30 - 13:00 | C6: 45943 | D6: 45945 | E6: 2026 | F6: The European Innovation Experience: A dynamic co-creative dialogue on how regional innovation boosts the Union of Skills and the twin transition | G6: Cohesion and Growth for the Future | H6: Interactive session | J6: No | K6: Hanze University of Applied Sciences | L6: Netherlands | N6: Albert Haan ; Elanna Veldkamp | O6: a.w.haan@pl.hanze.nl ; e.s.veldkamp@pl.hanze.nl | P6: Hanze University of Applied Sciences | Q6: Project Manager | R6: Svenja Tams - Hochschule Bremen - Professor - - ; Rix Groenboom - Hanze University of Applied Sciences - Professor - - ; Amir Haj-Bolouri - University West - Professor - - | S6: Yes | T6: YES | U6: Yes | V6: 3 | W6: Rix | X6: Groenboom | Y6: h.m.groenboom@pl.hanze.nl | Z6: Svenja | AA6: Tams | AB6: Svenja.Tams@hs-bremen.de | AC6: Dorina | AD6: Gjipali | AE6: dorinagjipali@uamd.edu.al | AF6: Yes | AG6: 3 | AH6: Rix | AI6: Groenboom | AJ6: h.m.groenboom@pl.hanze.nl | AK6: Svenja | AL6: Tams | AM6: Svenja.Tams@hs-bremen.de | AN6: Dorina | AO6: Gjipali | AP6: dorinagjipali@uamd.edu.al | AQ6: No comment | AS6: Groningen | AT6: Rix | AU6: Groenboom | AV6: h.m.groenboom@pl.hanze.nl | AY6: No | BB6: 45943 | BE6: 45945 | BG6: Yes | BI6: YES | BJ6: YES | BK6: YES | BL6: YES | BW6: 1 | BX6: 1 | BZ6: 45943 | CA6: 45945
AT7: Svenja | AU7: Tams | AV7: Svenja.Tams@hs-bremen.de | AW7: +49 1516 5151 748 | AX7: Wed, 15/10/2025, 11:30-13:00 CET | AY7: Yes | AZ7: I prefer to travel by train | BA7: Bremen | BB7: 45943 | BC7: 09:00 | BD7: Bremen | BE7: 45945 | BF7: 15:00 | BG7: Yes | BH7: Please book one additional night from Monday, 13.10.2025 - Tuesday, 14.10.2025. | BI7: YES | BJ7: YES | BK7: YES | BL7: YES | BM7: Bremen | BN7: train | BO7: 45943 | BP7: 0.36944444 | BR7: Bremen | BS7: 45945 | BT7: 0.68194444 | BV7: 392.59 | BW7: 1 | BX7: 1 | BZ7: 45943 | CA7: 45945 | CC7: =BW7+BX7+BY7 -> 2
AT8: Dorina | AU8: Gjipali | AV8: dorinagjipali@uamd.edu.al | AW8: 355689022333 | AX8: Wednesday, 15 October 2025 11:30 - 13:00 CET | AY8: Yes | AZ8: I prefer to travel by plane | BA8: Tirana | BB8: 45943 | BC8: Daily | BD8: Tirana | BE8: 45945 | BF8: Daily | BG8: Yes | BI8: YES | BJ8: YES | BK8: YES | BL8: YES | BM8: Tirana | BN8: Flight | BO8: 45943 | BP8: 0.39583333 | BQ8: tb2952 | BR8: Tirana | BS8: 45945 | BT8: 0.72916667 | BU8: lh5577-1453 | BV8: 487.82 | BW8: 1 | BX8: 1 | BZ8: 45943 | CA8: 45945 | CC8: =BW8+BX8+BY8 -> 2
A9: 45944 | B9: 15:30 - 16:30 | C9: 45943 | D9: 45945 | E9: 2027 | F9: Power of Territorial Cooperation: Co-creating a common and sustainable Baltic Sea Region by Macro-Regional Strategy, Interreg, Youth and Communities | G9: The Right to Stay: unlocking the potential of every territory | H9: Workshop | I9: 20272512 | J9: Yes | K9: Interreg Baltic Sea Region | L9: Germany | N9: Elena Kolosova ; Anna Galyga | O9: elena.kolosova@interreg-baltic.eu; Anna.Galyga@interreg-baltic.eu | P9: baltic.eu | Q9: Interreg Baltic Sea Region - Representative | R9: Esa Kokkonen - The Baltic Institute of Finland - Director - - ; Martin Noorkõiv - Foundation for Science and Liberal Arts Domus Dorpatensis - Director - - ; Silva Laure - The Council of the Baltic Sea States Secretariat - Officer - - | S9: After deadline-via email - request approved | T9: YES | U9: Yes | V9: 1 | W9: Silva | X9: Laure | Y9: silva.laure@gmail.com | AG9: 1 | AH9: Silva | AI9: Laure | AJ9: silva.laure@gmail.com | AT9: Silva | AU9: Laure | AV9: silva.laure@gmail.com | AW9: +371 29215900 | AX9: 14th of October, 15:30 to 16:30 | AY9: Yes | AZ9: I prefer to travel by plane | BA9: Riga | BB9: 45943 | BC9: evening | BD9: Riga | BE9: 45945 | BG9: Yes | BI9: YES | BJ9: YES | BK9: YES | BL9: YES | BM9: Riga | BN9: Flight | BO9: 45943 | BP9: 0.70486111 | BQ9: BT603 | BR9: Riga | BS9: 45945 | BT9: 0.40625 | BU9: BT602 | BV9: 251.82 | BW9: 1 | BX9: 1 | BZ9: 45943 | CA9: 45945 | CC9: =BW9+BX9+BY9 -> 2
A10: 45945 | B10: 11:30 - 12:30 | C10: 45943 | D10: 45945 | E10: 2046 | F10: Connected to stay: Investing in digital connectivity for Europe’s remote, rural and outermost regions | G10: The Right to Stay: unlocking the potential of every territory | H10: Workshop | J10: No | K10: European Broadband Competence Offices Network Support Facility | L10: Belgium | N10: Dimitra Vasilia ; Angelo Cerqueti | O10: dimitra.vasilia@broadbandeurope.eu ; angelo.cerqueti@ec.europa.eu | P10: European Commission | Q10: DG AGRI - Representative | R10: Maria-Christina MAKRANDREOU - European Commission - DG AGRI - - - ; Herve DUPUY - Health and Digital Executive Agency (HaDEA) - Head of Unit - - ; João Vaz - National Authority for Communications - ANACOM - Director - - | S10: yes | T10: YES | U10: Yes | V10: 2 | W10: Joao | X10: Vaz | Y10: joao.beleza@anacom.pt | Z10: Ashya | AA10: Lane Spollen MODERATOR | AB10: ashya@broadbandeurope.eu | AE10: Yes | AG10: 2 | AH10: Joao | AI10: Vaz | AJ10: joao.beleza@anacom.pt | AK10: Ashya | AL10: Lane Spollen MODERATOR | AM10: ashya@broadbandeurope.eu | AQ10: answered on the first of july | AS10: Deadline to complete the form: 31 July. - REMINDER SENT 08-08 + 14/08 | AT10: Joao | AU10: Vaz | AV10: joao.beleza@anacom.pt | AW10: 351919291238 | AX10: October 15 11:30 to 12:30 CET | AY10: Yes | AZ10: I prefer to travel by plane | BA10: Ponta Delgada | BB10: 45943 | BC10: 0.375 | BD10: Ponta Delgada | BE10: 45945 | BF10: 0.70833333 | BG10: Yes | BH10: Travelling to and from Ponta Delgada (Azores) may involve a stopover in Lisbon. If there is no flight connection on the same day, I would like to request accommodation in Lisbon. | BI10: YES | CC10: =BW10+BX10+BY10 -> 0
AT11: Ashya | AU11: Lane Spollen MODERATOR | AV11: ashya@broadbandeurope.eu | AY11: No | BG11: No | BW11: 0 | BX11: 0
A12: 45945 | B12: 14:00 - 15:30 | C12: 45945 | D12: 45946 | E12: 2110 | F12: Advancing and monitoring circular economy lifestyles and policies in cities and regions. | G12: Cities building tomorrow | H12: Interactive session | I12: 21102359 | J12: Yes | K12: German Environment Agency | L12: Germany | N12: Jan Gimkiewicz; Mariann Szabo | O12: Jan.Gimkiewicz@uba.de; szabo.mariann@gtk.bme.hu | P12: German Environment Agency | Q12: Project Manager | S12: yes | T12: YES | U12: Yes | V12: 3 | W12: Jan | X12: Gimkiewicz | Y12: jan.gimkiewicz@uba.de | Z12: Mariann | AA12: Szabo | AB12: szabo.mariann@gtk.bme.hu | AC12: Iris | AD12: Kriikkula | AE12: iris.kriikkula@turku.fi | AF12: Yes | AG12: 3 | AH12: Jan | AI12: Gimkiewicz | AJ12: jan.gimkiewicz@uba.de | AK12: Mariann | AL12: Szabo | AM12: szabo.mariann@gtk.bme.hu | AN12: Iris | AO12: Kriikkula | AP12: iris.kriikkula@turku.fi | AQ12: We will try to confirm Speakers in July. | AT12: Jan | AU12: Gimkiewicz | AV12: jan.gimkiewicz@uba.de | AW12: +49 (0)340 2103 3305 | AX12: Wed 15/10/2025, 14:00 - 15:30 CET | AY12: Yes | AZ12: I prefer to travel by train | BA12: Leipzig | BB12: 45945 | BC12: early morning - session at 2pm | BD12: Leipzig | BE12: 45946 | BG12: Yes | BH12: My session is on 15 October afternoon, but I would like to travel to Brussels already on 14 October, as the journey is quite long and there is no adequate option to travel on 15 October and get to Brussels in time. However, I wish to extend my stay to attend other sessions as a participant. And I would like to avoid the strike on 14 October. Therefore, I would be grateful if I could travel already on 13 October. | BW12: 1 | CF12: Please confirm whether we can book the flight on the 13th (instead of 15th in the morning) and whether we could cover those extra nights or not The speaker coming from Leipzig (session 2110), for whom we agreed the following: "while the train is cheaper, it seems disproportionate to cover 3 nights for him when there is a flight option, in particular since the journey is above 400 km. Please offer the flight ticket with one night accommodation." is insisting that he wants to arrive on 13 October instead of the morning of the 15th. He says: "This would ensure a timely arrival without complications and it would give me the opportunity to attend other sessions as well." The travel agency has confirmed that the train on 13 October is cheaper than on the 15th. Can we therefore offer him travel from 13 to 15 October, informing him that he would need to cover both nights of accommodation in that case? | CG12: TRAVEX comment: Current prices show that train tickets 13-15 Oct. are 256€ cheaper than flying 15-16 Oct Shadi decision: while the train is cheaper it seems disproportionate to cover 3 nights for him when there is a flight option, in particular since the journey is above 400 km. Please offer the flight ticket with one night accommodation. Caroline: If it is possible to make the round trip by plane on the same day for his session, then the train would not have been our recommended option. That said, we can offer a round trip by train since it is cheaper. We could even consider covering one overnight stay, provided that the price difference between the plane and the train is enough to cover the cost of one night. Any additional night, however, would remain at his own expense.
AT13: Iris | AU13: Kriikkula | AV13: iris.kriikkula@turku.fi | AW13: 358405899485 | AX13: 15.10.2025, 14.00-15.30 | AY13: Yes | AZ13: I prefer to travel by plane | BA13: Turku | BB13: 45943 | BC13: 14-16 | BD13: Turku | BE13: 45946 | BF13: 10am-18 | BG13: Yes | BM13: Turku | BN13: Flight | BR13: Turku | CF13: 13-15 is possible but it makes a landing in Turku at 02.00am…which is not really suitable -> PRICE: 701.10 euro 13-16 is more suitable - PRICE: 673.10 -> if this option is selected, please confirm whether we should cover all the nights from13 to 16th. | CG13: Regarding the accommodation, we can agree to cover from the 13 to the 15 (given the particular case as no feasible flights are available on 15 AM and due to strike on 14 October)
AT14: Mariann | AU14: Szabo | AV14: szabo.mariann@gtk.bme.hu | AW14: +36706012632 | AX14: 15/10/2025 from 14:00 to 15:30 | AY14: Yes | AZ14: I prefer to travel by plane | BA14: Budapest | BB14: 45945 | BC14: 6:30 | BD14: Budapest | BE14: 45945 | BF14: 21:30 | BG14: Yes | BI14: YES | BJ14: YES | BK14: YES | BL14: YES | BM14: Budapest | BN14: Flight | BO14: 45943 | BP14: 0.75 | BQ14: SN2826 | BR14: Budapest | BS14: 45945 | BT14: 0.89583333 | BU14: FR4264 | BV14: 406.27 | BW14: 1 | BX14: 1 | BY14: 0 | BZ14: 45943 | CA14: 45945 | CC14: =BW14+BX14+BY14 -> 2
A15: 45944 | B15: 14:00 - 15:00 | C15: 45943 | D15: 45945 | E15: 2112 | F15: Let’s build the future in cities together — accelerating the climate transition through impactful, U!REKA European university collaboration | G15: Cities building tomorrow | H15: Workshop | J15: No | K15: Metropolia University of Applied Sciences | L15: Finland | N15: Mikael Vainio ; Liesbet Cosyn | O15: mikael.vainio@metropolia.fi ; liesbet.cosyn@hogent.be | P15: Metropolia University of Applied Sciences | Q15: Representative | R15: Iina Oilinki - City of Helsinki - Director - - ; Filip van de Velde - City of Ghent - Expert - - ; Geleyn Meijer - Amsterdam University of Applied Sciences - President - - | S15: yes | T15: YES | U15: Yes | V15: 1 | W15: Iina | X15: Oilinki | Y15: iina.oilinki@hel.fi | Z15: - | AA15: - | AB15: - | AC15: - | AD15: - | AE15: - | AF15: Yes | AG15: 1 | AH15: Iina | AI15: Oilinki | AJ15: iina.oilinki@hel.fi | AK15: - | AL15: - | AM15: - | AN15: - | AO15: - | AP15: - | AQ15: Our speaker from the City of Helsinki, Iina Oilinki, would prefer a direct flight connection from Helsinki to Brussels. | AR15: positive | AS15: they would like t&a from the 13th to the 15th | AT15: Iina | AU15: Oilinki | AV15: iina.oilinki@hel.fi | AW15: 358-50-3461216 | AX15: 14.10.2025 14.00-15-00 | AY15: Yes | AZ15: I prefer to travel by plane | BA15: Helsinki | BB15: 45943 | BC15: afternoon (for example the Finnair at 16.40) | BD15: Helsinki | BE15: 45945 | BF15: mid morning (not before 8 am) for example the Finnair at 11.40 | BG15: Yes | BI15: YES | BJ15: YES | BK15: YES | BL15: YES | BM15: Helsinki | BN15: Flight | BO15: 45943 | BP15: 0.69444444 | BQ15: AY1545 | BR15: Helsinki | BS15: 45945 | BT15: 0.48611111 | BU15: AY1542 | BV15: 653.1 | BW15: 1 | BX15: 1 | BZ15: 45943 | CA15: 45945 | CC15: =BW15+BX15+BY15 -> 2 | CF15: 673,10€ - over budget | CG15: Shadi: ok | CH15: Approval received via email on 8 August
A16: 45945 | B16: 14:00 - 15:00 | C16: 45945 | D16: 45946 | E16: 2113 | F16: Cooperation for a Safer Tomorrow: Strengthening Security and Resilience Across Europe | G16: Cohesion and Growth for the Future | H16: Workshop | J16: No | K16: Interact Managing Authority | L16: Slovakia | N16: Jelena Stojovic ; Zaneta Chylova | O16: jelena.stojovic@interact.eu ; zaneta.chylova@interact.eu | P16: Interact | Q16: Representative | R16: Erwin SIWERIS - Interreg Europe - Programme Manager - - ; Wiktor Szydarowski - ESPON EGTC - Director - - ; Margit Tuennemann - URBACT Secretariat - Policy Officer - -
A17: 45945 | B17: 14:00 - 15:00 | C17: 45945 | D17: 45946 | E17: 2117 | F17: YOUTH 4 OUTERMOST REGIONS Final Event | G17: The Right to Stay: unlocking the potential of every territory | H17: Workshop | J17: No | K17: Startup Europe Regions Network | L17: Belgium | N17: Ana Catarino ; Luisa Marchionni | O17: ana.catarino@startupregions.eu ; luisa.marchionni@startupregions.eu; info@youth4outermostregions.eu | P17: Startup Europe Regions Network | Q17: Project Manager | R17: Daniel ALBUQUERQUE - European Commission - Expert - - ; German ESTEBAN - European Commission - Deputy Head of Unit - - ; Luisa Marchionni - Startup Europe Regions Network - Project Manager - - | S17: yes | T17: YES | U17: Yes | V17: 2 | W17: Soraia | X17: Rodrigues | Y17: Soraia.Rodrigues00@hotmail.com | Z17: Laurine | AA17: Marié | AB17: o.laurinemarie@gmail.com | AF17: Yes | AG17: 3 | AH17: Soraia | AI17: Rodrigues | AJ17: Soraia.Rodrigues00@hotmail.com | AK17: Laurine | AL17: Marié | AM17: o.laurinemarie@gmail.com | AN17: Noelia del Pino | AO17: Rodriguez Dominguez | AP17: noeliarodriguez1900@gmail.com; hola@b4c.es | AQ17: The speakers will be travelling from EU's outermost regions. | AS17: Email sent to confirm city/location | AT17: Soraia | AU17: Rodrigues | AV17: Soraia.Rodrigues00@hotmail.com | AW17: +351 912000151 | AX17: 15 october at 2 pm | AY17: Yes | AZ17: I prefer to travel by plane | BA17: Funchal, Madeira | BB17: 45943 | BD17: Funchal, Madeira | BE17: 45946 | BG17: Yes | BH17: Considering the national strike is planned for 14 October, I would prefer to travel on the 13th or 12 th of October. I only wish to stay for the time strictly necessary for the event (or a little bit more to know the city) . If possible, I would appreciate it if you could arrange a direct flight from Madeira to Brussels. I’m not sure what dates to request at this stage, as the event is still a bit far off. I would also be grateful if you could contact me or share the available flight options closer to the date, when travel arrangements are being prepared. If possible, I would appreciate it if you could contact me or share the available flight options closer to the date, or when travel arrangements are being prepared. Thank You so much | BI17: YES | BJ17: YES | BK17: YES | BL17: YES | BM17: Funchal (Madeira) | BN17: Flight | BO17: 45943 | BP17: 0.52430556 | BQ17: TP1688 | BR17: Funchal (Madeira) | BS17: 45946 | BT17: 0.49305556 | BU17: TP641-TP1691 | BW17: 1 | BX17: 1 | BY17: 1 | CF17: Please confirm whether we can book the flight on the 13th (instead of 15th in the morning) and whether we could cover the extra nights on 13 and 14 October | CG17: Shadi: Given the length of the journey we confirm we can cover the accommodation and travel from 13 to 16 AugustFInalis
AT18: Laurine | AU18: Marié | AV18: o.laurinemarie@gmail.com | AW18: 33685516610 | AX18: 15 october at 2 pm | AY18: Yes | AZ18: I prefer to travel by plane | BA18: Toulon (France) | BB18: 45945 | BC18: In the morning | BD18: Toulon | BE18: 45945 | BF18: In the morning | BG18: Yes | BH18: Considering the national strike is planned for 14 October, I would prefer to travel on the 13th of October | BY18: 0 | CF18: Please confirm whether we can book the flight on the 13th (instead of 15th in the morning) and whether we could cover the extra nights on 13 and 14 October Laurine is the speaker coming from Toulon. In her form, she indicated that she wanted to travel on 13 October instead of 15 October. However, after checking with Shadi, we agreed to offer her a round-trip on 15 October (since her session is at 2:00 pm that day and this option was feasible). SN3604 15OCT MRS 1 BRU 06:40 - 0825 SN3603 15OCT BRU MRS 1 21:10 – 22: 55 However, when the travel agency sent her the travel proposal, she replied saying that she insists on traveling on 13 October. We informed her that: "As your session is on 15 October at 2 pm, the strike does not affect your case. In addition, since there is an option to return on the same day after your session, no nights can be offered to you (we would only offer the night of 15 October if no return flight were available that same evening). Therefore, if you wish to arrive on 13 October (provided there is a flight at the same or lower cost than on 15 October), you would need to cover both the night of 13 and the night of 14 October yourself. Moreover, we would not arrange the booking for you and you would need to take care of it directly." Now the session organiser (Ana Caterino) has contacted us and said the following: "We were previously informed by the EU Regions Week Secretariat team of the possibility of traveling on 13 October, with an extra night secured for this purpose. As DG REGIO.A1 colleagues are already making arrangements for 14 October, I would like to kindly request that Laurine arrives on 13 October in order to join her colleagues and participate in the programme on 14 October." I still understand that, since she has the option to travel to Brussels and back on 15 October, we should not cover the extra nights and that we could only offer travel on 13 October if the flight on that day is equal to or cheaper than the flight on 15 October. Could you please confirm how we should proceed? | CG18: Shadi: Please offer a return travel for the same day 15 August SN3604 15OCT MRS 1 BRU 0640 0825 SN3603 15OCT BRU MRS 1 2110 2255 Price : 660€ Caroline: If a same-day return by plane is possible for her session, we would not have suggested the outbound travel on 13 October. However, we can offer it. We could cover one overnight stay if the fare difference between 13–15 October and a same-day return on 15 October is enough to cover the cost of one night. Any extra nights would remain at her expense.
AT19: Noelia del Pino | AU19: Rodriguez Dominguez | AV19: noeliarodriguez1900@gmail.com; hola@b4c.es | AW19: 34662431372 | AX19: 15 october at 2 pm | AY19: Yes | AZ19: I prefer to travel by plane | BA19: Las Palmas de Gran Canaria | BB19: 45943 | BC19: 0.33333333 | BD19: Las Palmas de Gran Canaria | BE19: 45945 | BF19: 0.75 | BG19: Yes | BH19: "Considerando que el paro nacional está previsto para el 14 de octubre, preferiría viajar el 13 de octubre". | BI19: YES | BJ19: YES | BK19: YES | BL19: YES | BM19: Las Palmas de Gran Canaria | BN19: Flight | BO19: 45943 | BP19: 10:25 | BQ19: VY 3005 | BR19: Las Palmas de Gran Canaria | BS19: 45945 | BT19: 18:05 | BU19: VY 8983 | BV19: €759.84 (TBC) | BW19: 1 | BX19: 1 | BY19: 0 | CF19: no flight available on the morning of the 15th that would allow her to arrive in time for her session. Therefore, she would need to arrive on the 13th and could return on the 15th after her session. The price of this flight is €759.84. Could you please confirm whether we can book this flight, and if so, whether we should cover the nights of October 13 and 14 (and “release” the night of the 15 we had initially planned for her)? | CG19: Agreed, thank you
A20: 45944 | B20: 14:00 - 15:00 | C20: 45943 | D20: 45945 | E20: 2124 | F20: Unlocking Regional Potential through European University Alliances: The Cases of BAUHAUS4EU and SUNRISE | G20: The Right to Stay: unlocking the potential of every territory | H20: Workshop | J20: No | K20: Hauts-de-France Regional Council | L20: France | N20: Romain Nivelle ; Annaelie Zapfe | O20: romain.nivelle@hautsdefrance.fr ; Annelie.Zapfe@tsk.thueringen.de | P20: Hauts-de-France Region | Q20: Director | R20: Thomas MIROW - TU Ilmenau - Head of Unit - - ; Joanna Daaboul - UTC - Head of Unit - - ; Andreas ZEINERT - UPJV - Project Manager - -
A21: 45945 | B21: 14:00 - 15:00 | C21: 45945 | D21: 45946 | E21: 2127 | F21: Women breaking barriers: gender-responsive twin transformation across regions | G21: Cohesion and Growth for the Future | H21: Workshop | I21: 21272163 | J21: Yes | K21: United Nations Development Programme | L21: Türkiye | N21: İrem Uzun ; Sedef Zağlıkılıç | O21: irem.uzun@undp.org ; sedef.zaglikilic@undp.org | P21: United Nations Development Programme | Q21: Representative | R21: Turkish Confederation of Employer Associations TİSK - Turkish Conferedation of Employer Associations - Director - - ; Hande Bayrak - MEXT Technology Center (MEXT) - Director - - ; Kısmet Deniz Çiftçi - United Nations Development Programme - Director - - | S21: yes | T21: YES | U21: Yes | V21: 3 | W21: İrem | X21: Uzun | Y21: irem.uzun@undp.org | Z21: Pelin | AA21: Öztürk Yudu | AB21: pozturk@tisk.org.tr | AC21: Mustafa Akan | AD21: Fazlıoğlu | AE21: mustafa.fazlioglu@eeas.europa.eu | AF21: Yes | AG21: 3 | AH21: İrem | AI21: Uzun | AJ21: irem.uzun@undp.org | AK21: Pelin | AL21: Öztürk Yudu | AM21: pozturk@tisk.org.tr | AN21: Mustafa Akan | AO21: Fazlıoğlu | AP21: mustafa.fazlioglu@eeas.europa.eu | AQ21: We had previously sent an email to clarify whether the T&A arrangement covers the moderator and coordinator, but since we haven’t received a response yet, we filled out the form in order not to miss the deadline. If this is not the case, we would appreciate it if you could kindly let us know. | AT21: İrem | AU21: Uzun | AV21: irem.uzun@undp.org | AW21: +90 535 971 7794 | AX21: 15/10/2025 14:00-15:00 | AY21: Yes | AZ21: I prefer to travel by plane | BA21: Ankara, Türkiye | BB21: 45943 | BC21: early morning on 15th of October if possible. If not departure date is 13th October | BD21: Ankara, Türkiye | BE21: 45946 | BF21: 15:00 | BG21: Yes | BH21: Although our session is scheduled for the afternoon of October 15, since we will be travelling from Ankara and there are no direct flights between Ankara and Brussels, we would prefer to travel on October 14— if it is also convenient for you. In addition, since we would like to attend the events taking place after our session on 15 October and plan to hold meetings with potential partners, would it be possible to arrange our return tickets for 16 October? In this case, we agree to cover the accommodation expenses for the extra night in Brussels on 15 October. | BY21: 0 | CC21: =BW21+BX21+BY21 -> 0 | CF21: no flight on the 15th morning - they should travel on the 13th | CG21: We confirm that we can cover accommodation for the extra nights for the two speakers (nights covered from 13 to 16)
AT22: Pelin | AU22: Öztürk Yudu | AV22: pozturk@tisk.org.tr | AW22: +90 530 312 48 84 | AX22: 15/10/2025 14:00-15:00 | AY22: Yes | AZ22: I prefer to travel by plane | BA22: Ankara, Türkiye | BB22: 45943 | BC22: 09:00 | BD22: Ankara, Türkiye | BE22: 45946 | BF22: 15:00 | BG22: Yes | BH22: Although our session is scheduled for the afternoon of October 15, since we will be travelling from Ankara and_x000D_ there are no direct flights between Ankara and Brussels, we would prefer to travel on October 14— if it is also_x000D_ convenient for you. In addition, since we would like to attend the events taking place after our session on 15_x000D_ October and plan to hold meetings with potential partners, would it be possible to arrange our return tickets for_x000D_ 16 October? In this case, we agree to cover the accommodation expenses for the extra night in Brussels on 15_x000D_ October. | BY22: 0 | CC22: =BW22+BX22+BY22 -> 0 | CF22: no flight on the 15th morning - they should travel on the 13th | CG22: We confirm that we can cover accommodation for the extra nights for the two speakers (nights covered from 13 to 16)
AT23: Deniz | AU23: Ciftci | AV23: deniz.ciftci@undp.org | AW23: 36706339119 | AX23: 2025. October 15. / 11:30 | AY23: Yes | AZ23: I prefer to travel by plane | BA23: Ankara, Türkiye | BB23: 45943 | BC23: 0.33333333 | BD23: Ankara, Türkiye | BE23: 45946 | BF23: 0.58333333 | BG23: NO - IMPORTANT - ACCOMMODATION NOT COVERED | BH23: Within the scope of the event, the ticket options for our other team members (İrem Hüda Uzun and Pelin Öztürk Yudu) were proposed as departure on 13 October and return on 16 October. In this regard, I kindly request that the same ticket options be proposed for me as well. | BY23: 0 | CC23: =BW23+BX23+BY23 -> 0 | CF23: Since the EEAS speaker was initially indicated but could not be covered as this did not align with the event’s guidelines, and given that the replacement has been proposed after the deadline, we are unfortunately unable to guarantee full coverage at this stage. What we can do is cover the travel ticket for the replacement, Ms. Deniz Ciftci. However, please note that the accommodation arrangements would need to be made and covered directly by you.
A24: 45945 | B24: 09:30 - 11:00 | C24: 45943 | D24: 45945 | E24: 2151 | F24: EU NEB Local Chapters: Shaping the Future of the New European Bauhaus at Local Level together – Participatory lab | G24: Cities building tomorrow | H24: Interactive session | J24: No | K24: EuroVértice | L24: Spain | N24: Nuria Prior Arce ; Alessandro Rancati | O24: nuria.prior@eurovertice.eu ; starglide@livepods.eu | P24: EuroVértice | Q24: Director-General | R24: Borut CINK - European Commission - JRC - Brussels - Representative - - ; Marcos ROS SEMPERE - European Parliament - - - - ; Paola VALANDRO - ART-ER Attrattività Ricerca Territorio - - - | S24: yes | T24: YES | U24: Yes | V24: 3 | W24: Maria | X24: Huertas Rubio | Y24: maria.huertas@eurovertice.eu | Z24: Paola | AA24: Valandro | AB24: paola.valandro@art-er.it | AC24: Patrik | AD24: Karlsson | AE24: patrik.karlsson.ryberg@ri.se | AF24: Yes | AG24: 3 | AH24: María | AI24: Huertas Rubio | AJ24: maria.huertas@eurovertice.eu | AK24: Paola | AL24: Valandro | AM24: paola.valandro@art-er.it | AN24: Patrik | AO24: Karlsson | AP24: patrik.karlsson.ryberg@ri.se | AQ24: no comment | AR24: positive | AS24: they would like to stay more and change their flight date | AT24: Maria | AU24: Huertas Rubio | AV24: maria.huertas@eurovertice.eu | AW24: 34636244484 | AX24: Wed 15/10/2025, 09:30 - 11:00 CET | AY24: Yes | AZ24: I prefer to travel by plane | BA24: Alicante | BB24: 45943 | BC24: 17.3 | BD24: Alicante | BE24: 45946 | BF24: 21.15 | BG24: Yes | BH24: I wish to extend my stay to attend other sessions as a participant if possible. Additional nights on 13th and 15th will be covered on my own. | BI24: YES | BM24: Alicante | BN24: Flight | BR24: Alicante | CF24: Please confirm whether we can book the return flight on the 16 (instead of 15th). He says he would cover the extra night on the 15th
AT25: Paola | AU25: Valandro | AV25: paola.valandro@art-er.it | AW25: 393382219275 | AX25: 15/10/2025 - 9:30 - 11:00 | AY25: Yes | AZ25: I prefer to travel by plane | BA25: Bologna (Italy) | BB25: 45943 | BC25: 0.60416667 | BD25: Brussels | BE25: 45945 | BF25: 0.66666667 | BG25: Yes | BH25: To avoid issues with the national strike planned for 14 October in Belgium I will travel the 13th, so I need additional night in Brussels. Thanks | BI25: YES | BJ25: YES | BK25: YES | BL25: YES | BM25: Bologna (Italy) | BN25: Flight | BO25: 45943 | BP25: 0.77083333 | BQ25: az7636 | BR25: Bologna (Italy) | BS25: 45945 | BT25: 0.66666667 | BU25: az7637 | BV25: 398.2 | BW25: 1 | BX25: 1 | BZ25: 45943 | CA25: 45945 | CC25: =BW25+BX25+BY25 -> 2
AT26: Patrik | AU26: Karlsson Ryberg | AV26: patrik.karlsson.ryberg@ri.se | AW26: 46730452338 | AX26: the 15th October, 9:30-11:00 | AY26: Yes | AZ26: I prefer to travel by plane | BA26: Stockholm | BB26: 45943 | BC26: 0.5 | BD26: Stockholm | BE26: 45945 | BF26: 0.75 | BG26: Yes | BI26: YES | BJ26: YES | BK26: YES | BL26: YES | BM26: Stockholm | BN26: Flight | BO26: 45943 | BP26: 0.53472222 | BQ26: SN2292 | BR26: Stockholm | BS26: 45945 | BT26: 0.82986111 | BU26: SK1590 | BV26: 388.93 | BW26: 1 | BX26: 1 | BZ26: 45943 | CA26: 45945 | CC26: =BW26+BX26+BY26 -> 2
A27: 45944 | B27: 14:00 - 15:00 | C27: 45943 | D27: 45945 | E27: 2155 | F27: Choosing Europe and its regions: Addressing brain drain of scientific minds in Europe & attracting talents from oversees | G27: The Right to Stay: unlocking the potential of every territory | H27: Workshop | J27: No | K27: European Commission - DG RTD | L27: Belgium | N27: Chiara Aprea ; Eszter Wirth | O27: Chiara.APREA@ec.europa.eu; Eszter.Wirth@cor.europa.eu | P27: European Commission | Q27: DG RTD - Representative | R27: Magda DE CARLI - European Commission - DG RTD - Deputy Director - - ; Emil Boc - Cluj-Napoca City - Mayor - - | S27: yes | T27: YES | U27: Yes | V27: 1 | W27: Gabriele | X27: Marzano | Y27: gabriele.marzano@regione.emilia-romagna.it | AF27: Yes | AG27: 1 | AH27: Gabriele | AI27: Marzano | AJ27: gabriele.marzano@regione.emilia-romagna.it | AQ27: Only 1 speaker may need travel and accommodation coverage. The name of the speaker is yet to be confirmed. | AT27: Gabriele | AU27: Marzano | AV27: gabriele.marzano@regione.emilia-romagna.it | AW27: 00393358285087 | AX27: Tue 14/10/2025, 14:00 - 15:00 CET | AY27: Yes | AZ27: I prefer to travel by plane | BA27: Bologna (IT) | BB27: 45943 | BC27: h. 18.30 | BD27: Bologna | BE27: 45945 | BG27: Yes | BH27: In order to prevent the risk of delaying my presence to the session due at 14.00h on the 14th of October, because of national strikes, I would prefer 1) to reach Brussels the day before (i.e. Brussels Airlines from Bologna to Brussels (h. 18.30 - 20.15); 2) stay the night btw 13th and 14th Oct; 3) be already in the morning at the events; 4) leaving in the evening by airplane (i.e. BRU h. 18.55 - FCO - BLQ h. 22.45). I motivate this request for prevening any risk of facing impediments for strikes in the morning of the 14th October. Thanks. Gabriele Marzano | BI27: YES | BJ27: YES | BK27: YES | BL27: YES | BM27: Bologna (IT) | BN27: Flight | BO27: 45943 | BP27: 0.77083333 | BQ27: az7636 | BR27: Bologna (IT) | BT27: 0.78819444 | BU27: az165-1321 | BV27: 412.96 | BW27: 1 | BX27: 1 | BZ27: 45943 | CA27: 45945 | CC27: =BW27+BX27+BY27 -> 2
A28: 45944 | B28: 09:30 - 10:30 | C28: 45943 | D28: 45945 | E28: 2158 | F28: Territorial truths: What the data say about Europe's cohesion and competitiveness | G28: Cohesion and Growth for the Future | H28: Workshop | J28: No | K28: European Commission - Eurostat | L28: Luxembourg | N28: Reka Fodor ; Mate Farkas | O28: Reka.FODOR@ec.europa.eu ; Mate.FARKAS@ec.europa.eu | P28: European Commission | Q28: Eurostat - Assistant | R28: Lewis DIJKSTRA - European Commission - DG JRC - Representative - - ; Teodora BRANDMUELLER - Eurostat - Deputy Head of Unit - - ; Rudiger Ahrend - Organisation for Economic Co-operation and Development - Representative - - | S28: yes | T28: YES | V28: 1 | W28: Rudiger | X28: Ahrend | Y28: Rudiger.Ahrend@oecd.org | AF28: Yes | AG28: 1 | AH28: Rudiger | AI28: Ahrend | AJ28: Rudiger.Ahrend@oecd.org | AS28: Deadline to complete the form: 5 August - REMINDER SENT 08-08 | AT28: Rudiger | AU28: Ahrend | AV28: Rudiger.Ahrend@oecd.org | AW28: 685483996 | AX28: 14 October, 9.30 | AY28: Yes | AZ28: I prefer to travel by train | BA28: Paris | BB28: 45943 | BC28: 9.12 am | BD28: Paris | BE28: 45945 | BF28: 17.16 | BH28: I would like to stay beyond the 14th to participate in other sessions. I understand that the second night may not be covered. | BI28: YES | BM28: Paris | BN28: Train | BR28: Paris
A29: 45945 | B29: 14:00 - 15:30 | C29: 45945 | D29: 45946 | E29: 2192 | F29: Hackathon: Shaping a smart and sustainable tourism strategy in the Mediterranean together | G29: Cohesion and Growth for the Future | H29: Interactive session | I29: 219224972658 | J29: Yes | K29: Interreg Italy - France Maritime | L29: Italy | N29: Filippo Giabbani ; Maura Isetto ; Franceesca D'Angelo | O29: marittimo1420@regione.toscana.it ; mauraisetto11@gmail.com; francesca.dangelo@regione.toscana.it | P29: Interreg Italy | Q29: France Maritime - Programme Manager | R29: Filippo Giabbani - Interreg Italy - France Maritime - Programme Manager - - ; Joseph Park - NECSTouR - Representative - - ; ROSA ESCAMILLA - Interact - - - - | S29: yes | T29: YES | U29: Yes | V29: 2 | W29: ALEJANDRO | X29: LA FARGA MARTINEZ | Y29: lafarga_ale@gva.es | Z29: SILVIA | AA29: COMIATI | AB29: silvia.comiati@regione.veneto.it | AF29: Yes | AG29: 2 | AH29: ALEJANDRO | AI29: LA FARGA MARTINEZ | AJ29: lafarga_ale@gva.es | AK29: SILVIA | AL29: COMIATI | AM29: silvia.comiati@regione.veneto.it | AQ29: no comment | AS29: Deadline to complete the form: 30 July - REMINDER SENT 08-08 | AT29: ALEJANDRO | AU29: LA FARGA MARTINEZ | AV29: lafarga_ale@gva.es | AW29: +34659557133 | AX29: 15/10/2025 14:00 | AY29: Yes | AZ29: I prefer to travel by plane | BA29: Valencia, Spain | BB29: 45943 | BC29: morning | BD29: Valencia, Spain | BE29: 45946 | BF29: afternoon | BG29: Yes | BH29: I am also part of the organising team of the stand 251960: transnational cooperation: building solidarity, driving synergies and delivering change; and my Programme (Interreg NEXT MED) is funding the NAWAMED project, which is finalist at the Regiostars Awards. We expect to attend the REGIOSTARS ceremony. Given all this. I need to travel to Brussels the 13th to be at the stand and come back the 16th to attend the ceremony. Thanks | BI29: YES | BM29: Valencia, Spain | BN29: Flight | BR29: Valencia, Spain | CF29: He is also part of a stand. Please confirm whether we can book his flights from the 13th to the 16th instead of 15 to 16th. PLease also confirm whether we will cover the extra nights or not | CG29: Approved from 13 to 16th - nights covered
AT30: SILVIA | AU30: COMIATI | AV30: silvia.comiati@regione.veneto.it | AW30: +39 338 496 3190 | AX30: 15/10/2025 at 14.00 | AY30: Yes | AZ30: I prefer to travel by plane | BA30: Venice | BB30: 45943 | BC30: 6.55 | BD30: Venice | BE30: 45945 | BF30: 21.2 | BG30: Yes | BH30: The cost of the flight on Monday 13/10 and Tuesday 14/10 is the same and I will take care of covering the hotel night for 13/10 | BI30: YES | BJ30: YES | BK30: YES | BL30: YES | BM30: Venice | BN30: Flight | BO30: 45943 | BP30: 0.28819444 | BQ30: sn3208 | BR30: Venice | BS30: 45945 | BT30: 0.88888889 | BU30: sn3207 | BV30: 383.13 | BY30: 0 | CC30: =BW30+BX30+BY30 -> 0 | CF30: Check if there is a flight on the 15th. IF YES -> If the fllight on the 13th has the same price or below she can travel. Accommodation at her own exp on 13 and 14 IF THERE IS NO FLIGHT ON 15TH early morning, please inform us
A31: 45945 | B31: 11:30 - 13:00 | C31: 45943 | D31: 45945 | E31: 2243 | F31: Participatory Lab: empowering communities through inclusive renovation and regional sustainability | G31: The Right to Stay: unlocking the potential of every territory | H31: Interactive session | I31: 22432635 | J31: Yes | K31: Steinbeis Europa Zentrum | L31: Germany | N31: Pia Burkhardt ; Siora Keller | O31: Ramojus.REIMERIS@ec.europa.eu ; Solange.MIFSUD@ec.europa.eu | P31: Steinbeis Europa Zentrum | Q31: Representative | R31: Mara Oprea - Institute for European Energy and Climate Policy - Expert - - ; Bernardo Xavier - Just a Change - Expert - - ; David Ferge - Th!nk Europe - Expert - - | S31: yes | T31: YES | U31: Yes | V31: 2 | W31: Clara | X31: Tripodi | Y31: clara.tripodi@justachange.pt | Z31: David | AA31: Ferge | AB31: david.ferge@fdm-ius.eu | AF31: Yes | AG31: 2 | AH31: Clara | AI31: Tripodi | AJ31: clara.tripodi@justachange.pt | AK31: David | AL31: Ferge | AM31: david.ferge@fdm-ius.eu | AP31: geral@mediotejo21.net | AQ31: Can we adapt in case the speaker changes? | AS31: BUDAPEST | AT31: Clara | AU31: Tripodi | AV31: clara.tripodi@justachange.pt | AW31: 351920403739 | AX31: 15th Oct at 11:30 CEST | AY31: Yes | AZ31: I prefer to travel by plane | BA31: Lisbon | BB31: 45943 | BC31: no preferences | BD31: Lisbon | BE31: 45945 | BF31: Later afternoon/Evening | BG31: Yes | BI31: YES | BJ31: YES | BK31: YES | BL31: YES | BM31: Lisbon | BN31: Flight | BO31: 45943 | BP31: 0.47222222 | BQ31: TP642 | BR31: Lisbon | BS31: 45945 | BT31: 0.87152778 | BU31: TP645 | BV31: 341.32 | BW31: 1 | BX31: 1 | BZ31: 45943 | CA31: 45945 | CC31: =BW31+BX31+BY31 -> 2
AT32: David | AU32: Ferge | AV32: david.ferge@fdm-ius.eu | AW32: 36706339119 | AX32: 13 - 15 Oct 11:30 CEST.N/A | AY32: Yes | AZ32: I prefer to travel by plane | BA32: Budapest | BB32: 45943 | BC32: Early morning or early afternoon | BD32: Budapest | BE32: 45945 | BF32: Afternoon or evening | BG32: Yes | BI32: YES | BJ32: YES | BK32: YES | BL32: YES | BW32: 1 | BX32: 1 | BZ32: 45943 | CA32: 45945
A33: 45944 | B33: 14:00 - 15:30 | C33: 45943 | D33: 45945 | E33: 2244 | F33: Regulatory Sandboxes in Action: Empowering Regions for Smarter Innovation | G33: Cohesion and Growth for the Future | H33: Interactive session | J33: No | K33: Joint Research Centre | L33: Italy | N33: Ramojus Reimeris ; Solange Mifsud | O33: Ramojus.REIMERIS@ec.europa.eu ; Solange.MIFSUD@ec.europa.eu | P33: European Commission | Q33: DG JRC - Representative | R33: Tatiana Fernández Sirera - Government of Catalonia - Head of Unit - - ; Johanna Dahl - Regional Council of Ostrobothnia - Expert - - | S33: yes | T33: YES | U33: Yes | V33: 3 | W33: Tatiana | X33: Fernández Sirera | Y33: t.fernandez@gencat.cat | Z33: Johanna | AA33: Dahl | AB33: Johanna.Dahl@obotnia.fi | AC33: Rosvaldas | AD33: Krušna | AE33: RKrusna@lb.lt | AF33: Yes | AG33: 3 | AH33: Tatiana | AI33: Fernández Sirera | AJ33: t.fernandez@gencat.cat | AK33: Johanna | AL33: Dahl | AM33: Johanna.Dahl@obotnia.fi | AN33: Rosvaldas | AO33: Krušna | AP33: RKrusna@lb.lt | AQ33: answered on the first of july | AS33: Deadline to complete the form: 30 July REMINDER SENT 08-08 Johanna has been replaced by Mats Brandt on13 August - approved by the client - form sent and deadline on Friday 15 August | AT33: Tatiana | AU33: Fernández Sirera | AV33: t.fernandez@gencat.cat | AW33: 34687494773 | AX33: 14/10/2025 14h - 15.30 h | AY33: Yes | AZ33: I prefer to travel by plane | BA33: Barcelona | BB33: 45943 | BC33: Afternoon | BD33: Barcelona | BE33: 45945 | BG33: Yes | BI33: YES | BJ33: YES | BK33: YES | BL33: YES | BM33: Barcelona | BN33: Flight | BO33: 45943 | BP33: 0.63194444 | BQ33: sn3707 | BR33: Barcelona | BS33: 45945 | BT33: 0.39930556 | BU33: sn3697 | BV33: 377.9 | BW33: 1 | BX33: 1 | BZ33: 45943 | CA33: 45945 | CC33: =BW33+BX33+BY33 -> 2
AT34: Mats | AU34: Brandt | AV34: mats.brandt@obotnia.fi | AW34: +358444934576 | AX34: 14.10.2025 14:00-15:30 | AY34: Yes | AZ34: I prefer to travel by plane | BA34: Vaasa | BB34: 13.10.2025 | BC34: 0.73263889 | BD34: Vaasa | BE34: 15.10.2025 | BF34: 0.79513889 | BG34: Yes | CF34: Mats Brandt – He is a speaker coming from Vaasa, and the travel agency has informed us that his Vaasa – Helsinki – Brussels round-trip ticket is over budget: €698.56. Could you please confirm if we can book it? | CG34: 20/08 : confirmed by Caroline | CH34: difference in price is only 50€
AT35: Rosvaldas | AU35: Krušna | AV35: RKrusna@lb.lt | AW35: 37069117792 | AX35: Tue 14/10/2025, 14:00 - 15:30 CET | AY35: Yes | AZ35: I prefer to travel by plane | BA35: Vilnius | BB35: 45943 | BC35: No preference | BD35: Vilnius | BE35: 45945 | BF35: No preference | BG35: Yes | BI35: YES | BJ35: YES | BK35: YES | BL35: YES | BM35: Vilnius | BN35: Flight | BO35: 45943 | BP35: 0.77777778 | BQ35: BT5371 | BR35: Vilnius | BS35: 45945 | BT35: 0.40625 | BU35: BT602 | BV35: 397.53 | BW35: 1 | BX35: 1 | BZ35: 45943 | CA35: 45945 | CC35: =BW35+BX35+BY35 -> 2
A36: 45945 | B36: 11:30 - 12:30 | C36: 45943 | D36: 45945 | E36: 2291 | F36: Safer Cities and Neighbourhoods through Public Space Design - Interactive Workshop for Future Cooperation and Expansion of Safer Cities Across Europe | G36: Cities building tomorrow | H36: Workshop | J36: No | K36: Innoarch, Innovation in architecture and Urban Planning | L36: Norway | N36: Isabel Ruiz Lopez ; Mads Bruun Høy | O36: isabel@grape.no ; mads@era.as | P36: Innoarch, Innovation in architecture and Urban Planning | Q36: Secretary - General | R36: Christina Thomassen Rooth - Oslo Police - Officer - - ; Marie Herping Abrahamsen - City of Copenhagen - Project Manager - - ; Magnus Lindgren - Safer Sweden Foundation - Secretary-General - - | S36: Yes | T36: YES | U36: Yes | V36: 3 | W36: Isabel | X36: Ruiz López | Y36: isabel@grape.no | Z36: Mads | AA36: Bruun Høy | AB36: mads@era.as | AC36: Christina | AD36: Thomassen Rooth | AE36: christina.thomassen.rooth@politiet.no | AF36: Yes | AG36: 3 | AH36: Isabel | AI36: Ruiz López | AJ36: isabel@grape.no | AK36: Mads | AL36: Bruun Høy | AM36: mads@era.as | AN36: Christina | AO36: Thomassen Rooth | AP36: christina.thomassen.rooth@politiet.no | AQ36: No comment | AT36: Isabel | AU36: Ruiz López | AV36: isabel@grape.no | AW36: 4796826316 | AX36: 13.10/14.10/15.10 | AY36: Yes | AZ36: I prefer to travel by plane | BA36: Oslo | BB36: 45943 | BC36: Early in the morning (Or 12.10.25 at the evening) | BD36: Alicante | BE36: 45945 | BF36: Late in the evening | BG36: Yes | BH36: I am also coordinating a parallel event organized by the Oslo Region Office on 13 October 2025 at 17:00. In addition, I will be participating as an external contributor at an event on 15 October 2025 at 09:30. I kindly ask you to take these events into consideration as well. Looking forward! | BI36: YES | BJ36: YES | BK36: YES | BL36: YES | BM36: Oslo | BN36: Flight | BO36: 45943 | BP36: 0.28125 | BQ36: sn2288 | BR36: Alicante | BS36: 45945 | BT36: 0.86111111 | BU36: vy1335 | BV36: 353.12 | BW36: 1 | BX36: 1 | BZ36: 45943 | CA36: 45945 | CC36: =BW36+BX36+BY36 -> 2
AT37: Mads | AU37: Bruun Høy | AV37: mads@era.as | AW37: 4792823204 | AX37: 15-10-2025 1130-1230 | AY37: Yes | AZ37: I prefer to travel by plane | BA37: Oslo | BB37: 45943 | BC37: Early in the morning | BD37: Oslo | BE37: 45945 | BF37: Late in the evening | BG37: Yes | BH37: nut allergy | BI37: YES | BJ37: YES | BK37: YES | BL37: YES | BM37: Oslo | BN37: Flight | BO37: 45943 | BP37: 0.28125 | BQ37: sn2288 | BR37: Oslo | BS37: 45945 | BT37: 0.87152778 | BU37: sn2287 | BV37: 356.12 | BW37: 1 | BX37: 1 | BZ37: 45943 | CA37: 45945 | CC37: =BW37+BX37+BY37 -> 2
AT38: Christina | AU38: Thomassen Rooth | AV38: christina.thomassen.rooth@politiet.no | AW38: 004740434545 | AX38: 14.10.25 | AY38: Yes | AZ38: I prefer to travel by plane | BA38: Oslo airport | BB38: 45943 | BC38: late evening | BD38: oslo airport | BE38: 45945 | BF38: evening | BG38: Yes | BI38: YES | BJ38: YES | BK38: YES | BL38: YES | BM38: Oslo | BN38: Flight | BO38: 45943 | BP38: 0.34722222 | BQ38: SK4743 | BR38: Oslo | BS38: 45945 | BT38: 0.87152778 | BU38: SN2287 | BV38: 320.96 | BW38: 1 | BX38: 1 | BZ38: 45943 | CA38: 45945 | CC38: =BW38+BX38+BY38 -> 2
A39: 45945 | B39: 09:30 - 11:00 | C39: 45943 | D39: 45945 | E39: 2304 | F39: How to make urban resilience work? City case studies and the role of research & innovation from DUT Partnership and URBACT | G39: Cities building tomorrow | H39: Interactive session | I39: Fegtc | J39: No | K39: AustriaTech GmbH | L39: Austria | N39: Maximilian Jäger ; Kristijan Radojcic | O39: maximilian.jaeger@austriatech.at ; k.radojcic@urbact.eu | P39: AustriaTech GmbH | Q39: Expert | R39: Mickaëlle Vergnaud - Bordeaux Metropolis - Head of Unit - - ; Merlin Pitz - - - - | S39: yes | T39: DO NOT NEED COVERAGE | U39: No, my speakers do not need coverage | AF39: No, my speakers do not need accommodation coverage | AQ39: no comment
A40: 45944 | B40: 11:30 - 13:00 | C40: 45943 | D40: 45945 | E40: 2314 | F40: Leveraging reconstruction and EU accession for regional development in Ukraine | G40: Cohesion and Growth for the Future | H40: Interactive session | I40: 205523142647 | J40: Yes | K40: EasyBusiness | L40: Ukraine | N40: Yaroslav Zhydyk ; Ljubica Kosheliuk | O40: yaroslav.zhydyk@easybusiness.in.ua ; ljubica.kosheliuk@giz.de | P40: EasyBusiness | Q40: Head of Unit | R40: Ambre Maucorps - The Vienna Institute for International Economic Studies - - - ; Yaroslav Zhydyk - EasyBusiness - Head of Unit - - ; Ljubica Kosheliuk - Deutsche Gesellschaft für Internationale Zusammenarbeit (GIZ) - Project Manager - - | S40: yes | T40: YES | U40: Yes | V40: 2 | W40: Dmytro | X40: Lyvch | Y40: dlyvch@easybusiness.in.ua | Z40: Iryna | AA40: Mykulych | AB40: mykulych@ard-ukraine.org | AF40: Yes | AG40: 2 | AH40: Dmytro | AI40: Lyvch | AJ40: dlyvch@easybusiness.in.ua | AK40: Iryna | AL40: Mykulych | AM40: mykulych@ard-ukraine.org | AQ40: no comment | AR40: positive | AS40: Deadline to complete the form: 30 July - REMINDER SENT 08-08 | AT40: Dmytro | AU40: Lyvch | AV40: dlyvch@easybusiness.in.ua | AY40: Yes | BG40: Yes | BW40: 0 | BX40: 0
AT41: Iryna | AU41: Mykulych | AV41: mykulych@ard-ukraine.org | AW41: 380669944247 | AX41: 15th of November, 16:30 | AY41: Yes | AZ41: I have no preference regarding the mode of transport – please make a suggestion | BA41: Paris | BB41: 45943 | BC41: Noon | BD41: Lviv | BE41: 45946 | BF41: First part of the day | BG41: Yes | BH41: Please be aware that my trip from and to Ukraine usually takes no less than 17 hours | BW41: 0 | BX41: 0 | CF41: She wants to depart on the 16th to Lvyv | CG41: If the ticket price is the same or lower we can cover return on 16, but we do not cover for the extra accommodation. Please share with me the price difference of a return to paris and a return to Lvyv and share it with me. We will get back to you on our decision then
A42: 45944 | B42: 11:30 - 12:30 | C42: 45943 | D42: 45945 | E42: 2315 | F42: Bankable Public Green Infrastructure & Services: A Practical Approach | G42: Cities building tomorrow | H42: Workshop | J42: No | K42: ICLEI European Secretariat | L42: Germany | N42: Priscila Franco Steier ; Haris Biskos | O42: priscila.steier@gmail.com; Haris.Biskos@urban-initiative.eu | P42: steier@iclei.org | R42: Heather Matson - Bankers without Boundaries - Director - - ; Etienne Aulotte - Bruxelles Environnement - Project Manager - - ; Ana-Maria MITROI-CIOBICA - European Investment Bank Group - Expert - -
A43: 45944 | B43: 11:30 - 13:00 | C43: 45943 | D43: 45945 | E43: 2322 | F43: How is policy contributing to cohesion and growth? Have a peek into the latest evaluation findings | G43: Cohesion and Growth for the Future | H43: Interactive session | J43: No | K43: European Commission - DG REGIO | L43: Belgium | N43: Carlo Amati ; Enrico Pesaresi | O43: Carlo.AMATI@ec.europa.eu ; enrico.pesaresi@ec.europa.eu | P43: European Commission | Q43: DG REGIO - Policy Officer
A44: 45945 | B44: 11:30 - 12:30 | C44: 45943 | D44: 45945 | E44: 2348 | F44: How Much Nature Do We Need in our Cities? Turning Data Into Urban Greening Action | G44: Cities building tomorrow | H44: Workshop | J44: No | K44: Urban Agenda for the EU Greening Cities Partnership | L44: France | N44: Haris Biskos ; Nadia Siokou | O44: Haris.Biskos@urban-initiative.eu ; nadia.siokou@urban-initiative.eu | P44: European Urban Initiative | Q44: Representative | R44: Carolina Cantergiani - TECNALIA - Researcher - - ; Philipp Walter - ICLEI Europe - Head of Sector - - | S44: Yes | T44: YES | U44: Yes | V44: 3 | W44: Yoan | X44: Clouet | Y44: clouet@institute-urbanex.org | Z44: Philipp | AA44: Walter | AB44: philipp.walter@iclei.org | AC44: Marino | AD44: Cavallo | AE44: marino.cavallo@cittametropolitana.bo.it | AF44: Yes | AG44: 3 | AH44: Yoan | AI44: Clouet | AJ44: clouet@institute-urbanex.org | AK44: Philipp | AL44: Walter | AM44: philipp.walter@iclei.org | AN44: Marino | AO44: Cavallo | AP44: marino.cavallo@cittametropolitana.bo.it | AQ44: no comment | AR44: positive: we confirm that we will need accommodation support for an additional night (13 to 15 October) for our speakers to ensure their participation and avoid the travel disruption. We fully understand the budget constraints and the possible shift to 3-star hotel arrangements, which is absolutely fine. | AS44: Deadline to complete the form: 8 August Reminder on 14-08 | AT44: Yoann | AU44: Clouet | AV44: clouet@institute-urbanex.org | AW44: 31653176168 | AX44: 15/10/2025 at 11.30 | AY44: Yes | AZ44: I prefer to travel by train | BA44: Den Haag | BB44: 45943 | BC44: late afternoon | BD44: Den Haag | BE44: 45945 | BF44: afternoon | BG44: Yes | BI44: YES | BJ44: YES | BK44: YES | BL44: YES | BM44: Den Haag | BN44: Train | BO44: 45945 | BP44: 0.30486111 | BR44: Den Haag | BS44: 45945 | BT44: 0.74513889 | BV44: 270.4 | BW44: 0 | BX44: 0 | CC44: =BW44+BX44+BY44 -> 0
AT45: Marino | AU45: Cavallo | AV45: marino.cavallo@cittametropolitana.bo.it | AW45: +393491657277 | AX45: 15th of October at 11:30 AM | AY45: Yes | AZ45: I prefer to travel by plane | BA45: Bologna | BB45: 45943 | BC45: after 10 am | BD45: Bologna | BE45: 45945 | BF45: after 14 pm | BG45: Yes | BI45: YES | BJ45: YES | BK45: YES | BL45: YES | BM45: Bologna | BN45: Flight | BO45: 45943 | BP45: 0.77083333 | BQ45: AZ7636 | BR45: Bologna | BS45: 45945 | BT45: 0.66666667 | BU45: AZ7637 | BV45: 398.12 | BW45: 1 | BX45: 1 | BZ45: 45943 | CA45: 45945 | CC45: =BW45+BX45+BY45 -> 2
AT46: Philipp | AU46: Walter | AV46: philipp.walter@iclei.org | AY46: Yes | BG46: Yes
A47: 45944 | B47: 15:30 - 16:30 | C47: 45943 | D47: 45945 | E47: 2365 | F47: Strengthening the competitiveness of European regions through STEP | G47: Cohesion and Growth for the Future | H47: Workshop | J47: No | K47: European Commission - DG BUDG | L47: Belgium | N47: Irati Icardo Isasa ; Theodora Flikas | O47: Irati.ICARDO-ISASA@ec.europa.eu; Theodora.FLIKAS1@ec.europa.eu | P47: European Commission | Q47: DG BUDG- Policy Officer | S47: yes | T47: YES. | U47: Yes | V47: 3 | W47: Federica | X47: Busillo | Y47: f.busillo@governo.it | Z47: Kirsten | AA47: Kötter | AB47: Kirsten.Koetter@mwike.nrw.de | AC47: Marta | AD47: Kolimaga | AE47: marta.kolimaga@crido.pl | AF47: Yes | AG47: 3 | AH47: Federica | AI47: Busillo | AJ47: f.busillo@governo.it | AK47: Kirsten | AL47: Kötter | AM47: Kirsten.Koetter@mwike.nrw.de | AN47: Marta | AO47: Kolimaga | AP47: marta.kolimaga@crido.pl | AS47: Deadline to complete the form: 7 August REMINDER SENT 08-08 | AT47: Federica | AU47: Busillo | AV47: f.busillo@governo.it | AW47: 393397093707 | AX47: 14 October 15:30-16:30 | AY47: Yes | AZ47: I prefer to travel by plane | BA47: Rome | BB47: 45943 | BC47: 0.5 | BD47: Rome | BE47: 45945 | BF47: 0.75 | BG47: Yes | BI47: YES | BM47: Rome | BN47: Flight | BR47: Rome | CC47: =BW47+BX47+BY47 -> 0
AT48: Kirsten | AU48: Kötter | AV48: Kirsten.Koetter@mwike.nrw.de | AW48: 491741512511 | AX48: 14.10.2025, 15.30 - 16.30 h | AY48: Yes | AZ48: I prefer to travel by train | BA48: Düsseldorf | BB48: 45943 | BC48: 9 | BD48: Warsaw | BE48: 45945 | BF48: 17.25 | BG48: No | BH48: Düsseldorf-Brüssel: On 14th Octobeer: 7.40 - 10.35; Brüssel-Düsseldorf: 17.25-19.57
AT49: Marta | AU49: Kolimaga | AV49: marta.kolimaga@crido.pl | AW49: +48 660 627 137 | AX49: 14 October 2025, 15h30-16h30 | AY49: Yes | AZ49: I prefer to travel by plane | BA49: Warsaw | BB49: 45943 | BC49: 9 | BD49: Warsaw | BE49: 45945 | BF49: 13 | BG49: Yes | BI49: YES | BJ49: YES | BK49: YES | BL49: YES | BM49: Warsaw | BN49: Flight | BO49: 45943 | BP49: 0.70486111 | BQ49: lo233 | BR49: Warsaw | BS49: 45945 | BT49: 0.55902778 | BU49: lo238 | BV49: 457.7 | BW49: 1 | BX49: 1 | BZ49: 45943 | CA49: 45945 | CC49: =BW49+BX49+BY49 -> 2
A50: 45944 | B50: 14:00 - 15:00 | C50: 45943 | D50: 45945 | E50: 2376 | F50: Integrated territorial development for a stronger future for European rural communities | G50: Cohesion and Growth for the Future | H50: Workshop | I50: 23722376 | J50: Yes | K50: Rurality-Environment-Development | L50: Belgium | N50: Eric Martial Taguem ; Johanna Tirinelli | O50: eric.taguem@ruraleurope.org ; johanna.tirinelli@ruraleurope.org | R50: Gerard PELTRE - Rurality-Environment-Development - President - - ; Michael RESTIER - - Director - - | S50: yes | T50: Reminder sent - 24/07 | U50: Yes | V50: 3 | W50: TBC | X50: TBC | Y50: TBC | Z50: TBC | AA50: TBC | AB50: TBC | AC50: TBC | AD50: TBC | AE50: TBC | AF50: Yes | AG50: 3 | AH50: TBC | AI50: TBC | AJ50: TBC | AK50: TBC | AL50: TBC | AM50: TBC | AN50: TBC | AO50: TBC | AP50: TBC | AQ50: no comment | AR50: positive | AS50: they will need t&a | AT50: TBC | AU50: TBC | AV50: TBC | AY50: Yes | BG50: Yes
AT51: TBC | AU51: TBC | AV51: TBC | AY51: Yes | BG51: Yes
AT52: TBC | AU52: TBC | AV52: TBC | AY52: Yes | BG52: Yes
A53: 45945 | B53: 11:30 - 13:00 | C53: 45943 | D53: 45945 | E53: 2392 | F53: A Bridge for the EU - a new tool to better integrate border regions | G53: The Right to Stay: unlocking the potential of every territory | H53: Interactive session | J53: No | K53: European Commission - DG REGIO | L53: Belgium | N53: Eva Lieber ; Benjamino Brunati | O53: Eva.LIEBER@ec.europa.eu ; Beniamino.BRUNATI@ec.europa.eu | P53: European Commission | Q53: DG REGIO - Programme Manager | R53: Ricardo FERREIRA - European Commission - DG REGIO - Representative - -
A54: 45945 | B54: 09:30 - 11:00 | C54: 45943 | D54: 45945 | E54: 2397 | F54: Digital lifelines for left-behind regions: reviving rural potential through smart tools | G54: The Right to Stay: unlocking the potential of every territory | H54: Interactive session | I54: 23862397 | J54: Yes | K54: Hanze University of Applied Sciences Groningen | L54: Netherlands | N54: Peter Meister Broekema ; Anne Katrine Ebbesen | O54: p.meister-broekema@pl.hanze.nl ; anne-katrine.ebbesen@nordregio.org | P54: Hanze University of Applied Sciences Groningen - | Q54: Representative | R54: Leo VAN WISSEN - Netherlands Interdisciplinary Demographic Institute NIDI, Royal Academy of Sciences, The Netherlands - Researcher - - ; Patricia MARTINEZ - European Association for Innovation in Local Development - Project Manager - - ; KAIRE LUHT - - - - | S54: yes | T54: YES | U54: Yes | V54: 3 | W54: Emilija | X54: Stojmenova Duh | Y54: emilija.stojmenova@ltfe.org | Z54: Peter | AA54: Meister-Broekema | AB54: p.meister-broekema@pl.hanze.nl | AC54: Pavel | AD54: Chmielinski | AE54: pchmielinski@irwirpan.waw.pl | AF54: Yes | AG54: 3 | AH54: Emilija | AI54: Stojmenova Duh | AJ54: emilija.stojmenova@ltfe.org | AK54: Peter | AL54: Meister-Broekema | AM54: p.meister-broekema@pl.hanze.nl | AN54: Pavel | AO54: Chmielinski | AP54: pchmielinski@irwirpan.waw.pl | AQ54: Could we also cover the accomodation of the coordinator (Anne Katrine Ebbesen) and the Moderator (Clive Peckham)? | AR54: positive: the speakers and all are willing to come on the 13th and stay till the 15th! | AS54: Deadline to complete the form: 31 July - REMINDER SENT 08-08 + 14/08 | AT54: Emilija | AU54: Stojmenova Duh | AV54: emilija.stojmenova@ltfe.org | AW54: 38651662730 | AX54: 15.10.2024; 9:30 | AY54: Yes | AZ54: I prefer to travel by plane | BA54: Zagreb | BB54: 45943 | BC54: 0.28472222 | BD54: Zagreb | BE54: 45947 | BF54: 0.85416667 | BG54: Yes | BH54: I wish to stay an additional night, on Thursday. I will cover the cost for the additional night. The price of the flight ticket is the same if travelling back on Thursday or Wednesday. | BI54: YES | BM54: Zagreb | BN54: Flight | BR54: Zagreb | CF54: Can we book his flight on the 17th of October? Informing him that he needs to cover the nights of the 15th and 16th of October | CG54: If the ticket price is the same or lower we can cover return on 17, but we do not cover for the extra accommodation
AT55: Peter | AU55: Meister-Broekema | AV55: p.meister-broekema@pl.hanze.nl | AW55: 31611182909 | AX55: 15/10 at 930 | AY55: Yes | AZ55: I prefer to travel by train | BA55: Groningen | BB55: 45943 | BC55: 2000 | BD55: Groningen | BE55: 45945 | BF55: 1600 | BG55: Yes | BI55: YES | BJ55: YES | BK55: YES | BL55: YES | BM55: Groningen | BN55: Train | BO55: 45943 | BP55: 0.78333333 | BR55: Groningen | BS55: 45945 | BT55: 0.70069444 | BV55: 201.4 | BW55: 1 | BX55: 1 | BZ55: 45943 | CA55: 45945 | CC55: =BW55+BX55+BY55 -> 2
AT56: Pawel | AU56: Chmielinski | AV56: pchmielinski@irwirpan.waw.pl | AW56: 48504854669 | AX56: 15.10 9.30-11.00 | AY56: Yes | AZ56: I prefer to travel by plane | BA56: Warszawa | BB56: 45943 | BC56: 5 Dep.10:25 Arr. 12:35 LO237 | BD56: Warszawa | BE56: 45946 | BF56: LO236 - dep. 10:15 OR: LO238 - dep.16:50 | BG56: No | BH56: I will book and pay my accommodation, I will stay longer than 'speaking slot' day. | BI56: YES | BJ56: YES | BK56: YES | BL56: YES | BM56: Warszawa | BN56: FLight | BO56: 45943 | BP56: 0.43402778 | BQ56: LO237 | BR56: Warszawa | BS56: 45946 | BT56: 0.42708333 | BU56: LO236 | BV56: 546.55 | BW56: 0 | BX56: 0 | CF56: Please confirm whether we can book the return flight on the 16th, informing him that we will not cover the extra night (15)
A57: 45945 | B57: 09:30 - 10:30 | C57: 45943 | D57: 45945 | E57: 2402 | F57: Unlocking the Potential of EU Border Regions: Data-Driven Decision Making to enhance cross-border public services | G57: The Right to Stay: unlocking the potential of every territory | H57: Workshop | I57: 24022480 | J57: Yes | K57: European Commission - DG REGIO | L57: Belgium | N57: Matteo Berzi; Peter Ulrich | O57: Matteo.BERZI@ec.europa.eu; peter.ulrich@uni-potsdam.de | P57: European Commission | Q57: JRC - Ispra - Expert | R57: Romina Kocina - European Grouping of Territorial Cooperation Territory of municipalities: Municipality of Gorizia, Municipality of Nova Gorica and municipality of Šempeter-Vrtojba - CEO - - ; Claire Duvernet - German Federal Ministry for Housing, Urban Development and Building - Project Manager - - ; Matteo BERZI - European Commission - JRC - Ispra - Expert - - | S57: yes | T57: Reminder sent - 24/07 | U57: Yes | V57: 2 | W57: TBC | X57: TBC | Y57: TBC | Z57: TBC | AA57: TBC | AB57: TBC | AC57: / | AD57: / | AE57: / | AF57: Yes | AG57: 2 | AH57: TBC | AI57: TBC | AJ57: TBC | AK57: TBC | AL57: TBC | AM57: TBC | AQ57: no comment | AT57: TBC | AU57: TBC | AV57: TBC | AY57: Yes | BG57: Yes
AT58: TBC | AU58: TBC | AV58: TBC | AY58: Yes | BG58: Yes
A59: 45945 | B59: 09:30 - 10:30 | C59: 45943 | D59: 45945 | E59: 2405 | F59: Cities building tomorrow: Working together on National Building Renovation Plans | G59: Cities building tomorrow | H59: Workshop | J59: No | K59: Buildings Performance Institute Europe | L59: Belgium | N59: Volodymyr Vladyka ; Clare Taylor | O59: volodymyr.vladyka@bpie.eu ; clareannetaylor@gmail.com | P59: BUILDINGS PERFORMANCE INSTITUTE EUROPE | Q59: Policy Officer | R59: Oliver RAPF - Buildings Performance Institute Europe - Director - - ; Julien Tami - European Commission - DG ENER - Policy Officer - - ; Adrian Hiel - Energy Cities - Representative - - | S59: yes | T59: YES | U59: Yes | V59: 1 | W59: Wies | X59: Ettema | Y59: wies.ettema@denhaag.nl | Z59: - | AA59: - | AB59: - | AC59: - | AD59: - | AE59: - | AF59: Yes | AG59: 1 | AH59: Weis | AI59: Ettema | AJ59: weis.ettema@denhaag.nl | AQ59: no comment | AR59: positive: I would like to confirm that one speaker will still be travelling for our session, with new conditions for travel and accommodation support. | AT59: Wieteke Mylène | AU59: Ettema | AV59: weis.ettema@denhaag.nl | AW59: 31640248255 | AX59: 15 October, 09.30 AM | AY59: Yes | AZ59: I prefer to travel by train | BA59: Amsterdam, NL | BB59: 45945 | BC59: Around 07.00 AM | BD59: Amsterdam, NL | BE59: 45945 | BF59: After the session | BG59: No | BI59: YES | BJ59: YES | BM59: Amsterdam, NL | BN59: Train | BO59: 45945 | BP59: 0.29861111 | BQ59: EST 9316 | BR59: Amsterdam, NL | BS59: 45945 | BT59: 15:53 | BU59: EST 9351 | BW59: 0 | BX59: 0 | CF59: Please confirm if the speaker can arrive on the 15th by train | CG59: OK to arrive and leave on the same day since this person arrives from Amsterdam.
A60: 45944 | B60: 14:00 - 15:30 | C60: 45943 | D60: 45945 | E60: 2426 | F60: Empowering Implementation: a strategic approach to administrative capacity building and supporting beneficiaries | G60: Cohesion and Growth for the Future | H60: Interactive session | J60: No | K60: European Commission - DG REGIO | L60: Belgium | N60: Vaida Zydelyte ; Maria-Varinia Michalun | O60: Vaida.ZYDELYTE@ec.europa.eu ; mariavarinia.michalun@oecd.org | P60: European Commission | Q60: DG REGIO - Policy Officer | R60: Irina Pintilescu - North-East Romania Regional Development Agency - Director - - ; Lorenzo Palego - t33 srl - Policy Expert - - | S60: yes | T60: YES | U60: Yes | V60: 2 | W60: Maria Varinia | X60: Michalun | Y60: MariaVarinia.MICHALUN@oecd.org | Z60: Lorenzo | AA60: Palego | AB60: l.palego@t33.it | AF60: Yes | AG60: 1 | AH60: Lorenzo | AI60: Palego | AJ60: l.palego@t33.it | AQ60: no comment | AT60: Maria Varinia | AU60: Michalun | AV60: MariaVarinia.MICHALUN@oecd.org | AW60: +33.6.34.67.43.14 | AX60: 14 October; 14h00 | AY60: Yes | AZ60: I prefer to travel by train | BA60: Paris, France | BB60: 45943 | BC60: 8h30 | BD60: Paris, France | BE60: 45945 | BF60: 20h30 | BG60: Yes | BH60: If it is at all possible to have a modifiable ticket, I would be very grateful, as it may become necessary to do so but is still uncertain and I did not want to miss your deadline. | BI60: YES | BJ60: YES | BK60: YES | BL60: YES | BM60: Paris, France | BN60: Train | BO60: 45943 | BP60: 0.59583333 | BQ60: EUR9351 | BR60: Paris, France | BS60: 45945 | BT60: 0.63611111 | BU60: EUR9352 | BV60: 318 | BW60: 1 | BX60: 1 | BZ60: 45943 | CA60: 45945 | CC60: =BW60+BX60+BY60 -> 2
AT61: Lorenzo | AU61: Palego | AV61: l.palego@t33.it | AW61: +39.3383636478 | AX61: 14 October 2025, 14-15.30 | AY61: Yes | AZ61: I prefer to travel by train | BA61: Ancona or Bologna | BB61: 45943 | BC61: after 5 am and before 3 pm | BD61: Bologna | BE61: 45945 | BF61: after 2 pm | BG61: Yes | BH61: I would prefer to travel BY TRAIN from Ancona to Brussels, during daytime, with a journey Ancona-Milan-Paris-Brussels, with departure around 5 or 6 am, and arrival around 10 or 11 pm,. And then to travel BY PLANE to come back to Italy (Zaventem-Bologna, and then I will pay a train to Ancona). If this is not doable for any reason, there is absolutely no problem and I would kindly ask you to simply book inbound and outbound flights Bologna-Zaventem. I am also requiring to stay 2 NIGHTS so that I can attend other workshops at the EU Regions week. I am ok to personally cover the cost of the second night (14 October): so please, if possible, book 2 nights in the same hotel (no more than 220-240 € per night, if possible, please) and I will cover the cost of the second night. If not possible, I will book the second night on my own. Thank you for your patience, and kind regards. | BI61: YES | BJ61: YES | BK61: YES | BL61: YES | BM61: Milan | BN61: Train and flight | BO61: 45943 | BP61: 0.86458333 | BQ61: EUR9389 | BR61: Bologna | BS61: 45945 | BT61: 0.66666667 | BU61: AZ7637 | BV61: 549.18 | BW61: 1 | BX61: 1 | BZ61: 45943 | CA61: 45945 | CC61: =BW61+BX61+BY61 -> 2
A62: 45944 | B62: 09:30 - 11:00 | C62: 45943 | D62: 45945 | E62: 2429 | F62: From insight to impact: Leveraging data-driven approaches for smarter regional policy | G62: The Right to Stay: unlocking the potential of every territory | H62: Interactive session | I62: 24292651 | J62: Yes | K62: White Research SRL | L62: Belgium | N62: Giulia Zendron ; Anastasia Panori | O62: g.zendron@white-research.eu; apanori@plandevel.auth.gr | P62: White Research SRL | Q62: Project Manager | R62: Anastasia Panori - Aristotle University of Thessaloniki - - - ; Jennifer MCGARRIGLE - Institute of Geography and Spatial Planning - University of Lisbon - Professor - - ; Peter MEISTER BROEKEMA - Hanze University of Applied Sciences Groningen - Representative - - | S62: yes | T62: YES | U62: Yes | V62: 1 | W62: Seamus | X62: McGuinness | Y62: seamus.mcguinness@esri.ie | Z62: / | AA62: / | AB62: / | AC62: / | AD62: / | AE62: / | AF62: Yes | AG62: 1 | AH62: Seamus | AI62: McGuinness | AJ62: seamus.mcguinness@esri.ie | AQ62: no comment | AT62: Seamus | AU62: McGuinness | AV62: seamus.mcguinness@esri.ie | AW62: 447955739681 | AX62: 14/10/25 at 9.30am | AY62: Yes | AZ62: I prefer to travel by plane | BA62: Dublin | BB62: 45943 | BC62: 1pm | BD62: dublin | BE62: 45945 | BG62: Yes | BI62: YES | BJ62: YES | BK62: YES | BL62: YES | BM62: Dublin | BN62: Flight | BO62: 45943 | BP62: 0.74652778 | BQ62: ei638 | BR62: Dublin | BS62: 45945 | BT62: 0.43055556 | BU62: ei631 | BV62: 280.1 | BW62: 1 | BX62: 1 | BZ62: 45943 | CA62: 45945 | CC62: =BW62+BX62+BY62 -> 2
A63: 45944 | B63: 17:00 - 18:00 | C63: 45943 | D63: 45945 | E63: 2435 | F63: Peer-to-peer learning on replicating and upscaling nature-based solutions for climate adaptation | G63: Cohesion and Growth for the Future | H63: Workshop | I63: 21462435 | J63: Yes | K63: TU Dortmund University | L63: Germany | N63: Stefan Greiving ; Natascha Ng | O63: stefan.greiving@tu-dortmund.de; natascha.ng@sei.org | P63: TU Dortmund University | Q63: Professor | R63: Mindert de Vries - Deltares - - - ; Jaroslav Mysiak - Euro-Mediterranean Centre for Climate Change - - - ; Stefan Greiving - TU Dortmund University - - - | S63: yes | T63: DO NOT NEED COVERAGE | U63: No, my speakers do not need coverage | AF63: No, my speakers do not need accommodation coverage | AQ63: no comment
A64: 45944 | B64: 17:00 - 18:00 | C64: 45943 | D64: 45945 | E64: 2449 | F64: Co-Creating Resilient Cities: Citizens, Data and Participatory Action | G64: Cities building tomorrow | H64: Workshop | I64: 24492578 | J64: Yes | K64: NILU | L64: Norway | N64: Nuria Castell ; Masha Smimova | O64: ncb@nilu.no ; Masha.smirnova@eurocities.eu | P64: NILU | Q64: Researcher | R64: Nuria CASTELL - NILU - Researcher - - ; Celia Santos - Barcelona Institute for Global Health - Researcher - - ; Hester Volten - - - - | S64: yes | T64: YES | U64: Yes | V64: 3 | W64: Nuria | X64: Castell | Y64: ncb@nilu.no | Z64: Sonia | AA64: Matera | AB64: sonia.matera@dblue.it | AC64: Pablo | AD64: Garcia Arcos | AE64: pablo.garcia@gencat.cat | AF64: Yes | AG64: 3 | AH64: Nuria | AI64: Castell | AJ64: ncb@nilu.no | AK64: Sonia | AL64: Matera | AM64: sonia.matera@dblue.it | AN64: Pablo | AO64: Garcia Arcos | AP64: pablo.garcia@gencat.cat | AQ64: no comment | AT64: Nuria | AU64: Castell | AV64: ncb@nilu.no | AW64: +47 92523352 | AX64: Tue 14/10/2025, 17:00 - 18:00 CET | AY64: Yes | AZ64: I prefer to travel by plane | BA64: Oslo | BB64: 45943 | BC64: 10am | BD64: Oslo | BE64: 45945 | BF64: 21pm (I prefer to go back the same day if possible) | BG64: Yes | BH64: I am a single mum, and I would prefer to fly back the same day. | BI64: YES | BM64: Oslo | BR64: Oslo | CC64: =BW64+BX64+BY64 -> 0
AT65: Sonia | AU65: Matera | AV65: sonia.matera@dblue.it | AW65: +393274765249 | AX65: 14/10/2025, 17:00 - 18:00 CET | AY65: Yes | AZ65: I have no preference regarding the mode of transport – please make a suggestion | BA65: Paris | BB65: 45943 | BC65: 15:55 | BD65: Rome | BE65: 45945 | BF65: 18:30 | BG65: Yes | BH65: I am currently based in Rome but will be in Paris on 13 October. To avoid potential disruptions due to the national strike, I am considering traveling from Paris to Brussels by train on 13 October and returning to Rome by plane on 15 October. Could you kindly confirm whether the additional night’s accommodation could be covered, given the circumstances? If the additional night cannot be covered, I will instead plan to travel from Rome on the morning of 14 October and return in the evening of 15 October. This would allow me to attend additional conference sessions, I’ve checked the travel costs, and they do not exceed those of the standard itinerary. | BI65: YES | BJ65: YES | BK65: YES | BL65: YES | BM65: Paris, France | BN65: Train and flight | BO65: 45943 | BP65: 0.66319444 | BQ65: EUR9359 | BR65: Rome | BS65: 45945 | BT65: 0.78819444 | BU65: AZ165 | BV65: 240.22 | BW65: 1 | BX65: 1 | BZ65: 45943 | CA65: 45945 | CC65: =BW65+BX65+BY65 -> 2
AT66: Pablo | AU66: García Arcos | AV66: pablo.garcia@gencat.cat | AW66: +34 686097117 | AX66: 14 October 2025 from 17:00 to 18:00 CET in Brussels | AY66: Yes | AZ66: I prefer to travel by plane | BA66: Barcelona | BB66: 45943 | BC66: Afternoon | BD66: Barcelona | BE66: 45946 | BF66: Afternoon | BG66: Yes | BH66: Due to the planned national strike in Belgium, I would prefer to travel to Brussels the day before. Therefore, I would need accommodation for one night. Additionally, I would like to return later on the 16th, if the cost does not exceed that of the minimum necessary stay, as I will also be attending the Democracy R&D annual meeting that same week.. | BI66: YES | BM66: Barcelona | BN66: Flight | BR66: Barcelona | CF66: Please confirm if the speaker can leave one day later on the 16th as he attends the Democracy R&D annual meeting | CG66: If the ticket price is the same or lower we can cover return on 16, but we do not cover for the extra accommodation
A67: 45944 | B67: 17:00 - 18:00 | C67: 45943 | D67: 45945 | E67: 2450 | F67: Empowering Regional Innovation Ecosystems: Tools for SME Resilience, Funding and Global Integration | G67: Cohesion and Growth for the Future | H67: Workshop | I67: 243924502487 | J67: Yes | K67: AIM Centre | L67: Ireland | N67: Elena Bezborodova ; Julie Dowling; Michela Gaifami | O67: elenabezborodova@aimcentre.ie ; juliedowling@aimcentre.ie; michela.gaifami@interreg-npa.eu | P67: AIM Centre | Q67: Programme Manager | R67: Julie Dowling - AIM Centre - CEO - - ; David Bermingham - AIM Centre - Director - - | S67: yes | T67: yes | U67: Yes | V67: 2 | W67: Julie | X67: Dowling | Y67: juliedowling@aimcentre.ie | Z67: Alexander | AA67: Lembcke | AB67: Alexander.LEMBCKE@oecd.org | AF67: Yes | AG67: 2 | AH67: Julie | AI67: Dowling | AJ67: juliedowling@aimcentre.ie | AK67: Alexander | AL67: Lembcke | AM67: Alexander.LEMBCKE@oecd.org | AQ67: answered on the first of july | AS67: Deadline to complete the form: 31 July - REMINDER SENT 08-08 | AT67: Julie | AU67: Dowling | AV67: juliedowling@aimcentre.ie | AW67: 353870987200 | AX67: Tue 14/10/2025, 17:00 - 18:00 CET | AY67: Yes | AZ67: I prefer to travel by plane | BA67: Dublin | BB67: 45943 | BC67: 7am - 10am | BD67: Dublin | BE67: 45945 | BF67: around 9am | BG67: Yes | BI67: YES | BM67: Dublin | BN67: Flight | BR67: Dublin
AT68: Alexander | AU68: Lembcke | AV68: Alexander.LEMBCKE@oecd.org | AW68: +33651819491 | AX68: Tue 14/10/2025, 11:30 - 12:30 CET and Tue 14/10/2025, 17:00 - 18:00 CET | AY68: Yes | AZ68: I prefer to travel by train | BA68: Paris | BB68: 45943 | BC68: 16:00 | BD68: Paris | BE68: 45945 | BF68: 20:00 | BG68: Yes | BI68: YES | BJ68: YES | BK68: YES | BL68: YES | BM68: Paris, France | BN68: Train | BO68: 45943 | BP68: 0.66319444 | BQ68: EUR9359 | BR68: Paris, France | BS68: 45945 | BT68: 0.61319444 | BU68: EUR9350 | BV68: 190 | BW68: 1 | BX68: 1 | BZ68: 45943 | CA68: 45945 | CC68: =BW68+BX68+BY68 -> 2
A69: 45945 | B69: 09:30 - 10:30 | C69: 45943 | D69: 45945 | E69: 2468 | F69: Driving Change: bridging sustainable mobility and urban planning | G69: Cities building tomorrow | H69: Workshop | J69: No | K69: POLIS | L69: Belgium | N69: Pedro Gomes ; Ivo Cré | O69: pgomes@polisnetwork.eu ; icre@polisnetwork.eu | P69: POLIS | Q69: Project Manager | R69: Nele Sergeant - Bruxelles Environnement - - - ; Bram Seeuws - Way To Go - - - ; Clara Mafé - Housing Europe - Representative - -
A70: 45945 | B70: 14:00 - 15:00 | C70: 45945 | D70: 45946 | E70: 2476 | F70: Housing affordability crisis in European cities and regions: from data to policy insights and financial instruments | G70: Cities building tomorrow | H70: Workshop | I70: 24332476 | J70: Yes | K70: European Commission - DG ENER | L70: Belgium | N70: Orsola Mautone ; Elisa Bazzani | O70: Orsola.MAUTONE@ec.europa.eu ; Elisa.BAZZANI@ec.europa.eu | P70: European Commission | Q70: Policy Officer | R70: Rudiger Ahrend - Organisation for Economic Co-operation and Development - Representative - - ; Martin GAUK - ESPON EGTC - Expert - - ; Filipe Batista i Silva - European Commission - JRC - Ispra - - - | S70: Yes | T70: yes | U70: Yes | V70: 1 | W70: Martin | X70: Gauk | Y70: martin.gauk@espon.eu | AF70: Yes | AG70: 1 | AH70: Martin | AI70: Gauk | AJ70: martin.gauk@espon.eu | AQ70: although we are asked how many speakers need travel/accommodation, when chosing less than 3, we need anyway to fill in the cells for all 3 speakers | AT70: Martin | AU70: Gauk | AV70: martin.gauk@espon.eu | AW70: +352 20 600 280 | AX70: Wed 15/10/2025, 14:00 - 15:00 CET | AY70: Yes | AZ70: I prefer to travel by train | BA70: Luxembourg | BB70: 45943 | BC70: 10h | BD70: Luxembourg | BE70: 45946 | BF70: 16h | BG70: Yes | BI70: YES | BM70: Luxembourg | BN70: train | BR70: Luxembourg | BY70: 0 | CF70: Speaker wants to arrive on the 13th October (instead of 15th). Can we book the flight on those dates? Extra nights on the 13th and 14th are on his own expenses | CG70: A return train ticket for the same day is fine. If the speaker disagrees/protests then we can offer him accommodation for one night.
A71: 45945 | B71: 15:30 - 16:30 | C71: 45945 | D71: 45946 | E71: 2479 | F71: RESIST: collaboration & scaling innovative climate adaptation solutions for resilient territories | G71: Cities building tomorrow | H71: Workshop | J71: No | K71: ACCENT SUD - Association for the cultural cooperation and the cross-regional digital economy with Southern Europe | L71: France | N71: Silvia Cibien ; Gaia Marotta | O71: silvia.cibien@accent; gaia.marotta@errin.eu | P71: sud.eu | Q71: ACCENT SUD - Association for the cultural cooperation and the cross regional digital economy with Southern Europe - President | R71: Catarina Azevedo - INOVA+ - Project Manager - -
A72: 45945 | B72: 11:30 - 12:30 | C72: 45943 | D72: 45945 | E72: 2499 | F72: Inclusive Regions, Safer Spaces: Local and Regional Approaches to Gender Equality, Wellbeing, and Digital Safety in Education | G72: The Right to Stay: unlocking the potential of every territory | H72: Workshop | J72: No | K72: FORMA.Azione | L72: Italy | N72: Sylvia Liuti ; Martina Morbidini | O72: liuti@azione.com ; morbidini@azione.com | P72: FORMA.Azione | Q72: Director | R72: Albert Peiró Mateu - - - - ; Sylvia Liuti - FORMA.Azione - Director - - | S72: yes | T72: YES | U72: Yes | V72: 3 | W72: Sylvia | X72: Liuti | Y72: liuti@azione.com | Z72: Yiannis | AA72: Karoumpalos | AB72: yiannisk@kekdafni.gr | AC72: Lorena | AD72: Ripoll Ferri | AE72: lripoll@correu.escoladeltreball.org | AF72: Yes | AG72: 3 | AH72: Sylvia | AI72: Liuti | AJ72: liuti@azione.com | AK72: Yiannis | AL72: Karoumpalos | AM72: yiannisk@kekdafni.gr | AN72: Lorena | AO72: Ripoll Ferri | AP72: lripoll@correu.escoladeltreball.org | AQ72: The list of speakers will be confirmed as soon as possible. | AT72: Sylvia | AU72: Liuti | AV72: liuti@azione.com | AW72: +39 3358480855 | AX72: 15/10/2025 11.30-12.30 | AY72: Yes | AZ72: I prefer to travel by plane | BA72: Perugia | BB72: 45943 | BC72: 12:00 | BD72: Perugia | BE72: 45945 | BF72: 18:00 | BG72: Yes | BH72: I usually fly from Rome FCO | BI72: YES | BJ72: YES | BK72: YES | BL72: YES | BM72: Perugia | BN72: Flight | BO72: 45943 | BP72: 0.65625 | BQ72: SN4152 | BR72: Perugia | BS72: 45945 | BT72: 0.75347222 | BU72: SN3183 | BV72: 485.67 | BW72: 1 | BX72: 1 | BZ72: 45943 | CA72: 45945 | CC72: =BW72+BX72+BY72 -> 2
AT73: Ioannis | AU73: Karoumpalos | AV73: yiannisk@kekdafni.gr | AW73: 306948125141 | AX73: 15/10/2025 11.30-12.30 | AY73: Yes | AZ73: I prefer to travel by plane | BA73: ATHENS,GREECE | BB73: 45943 | BC73: In the morning | BD73: ATHENS,GREECE | BE73: 45945 | BF73: The session ends at 12.30, so I would prefer to fly to Athens during afternoon (maybe around 17.00-18.00) | BG73: Yes | BH73: Due to the announcement of a national strike, I would prefer to travel on October 13 for greater safety in terms of transportation. | BI73: YES | BJ73: YES | BK73: YES | BL73: YES | BM73: ATHENS,GREECE | BN73: Flight | BO73: 45943 | BP73: 0.44791667 | BQ73: GQ800 | BR73: ATHENS,GREECE | BS73: 45945 | BT73: 0.83333333 | BU73: A3623 | BV73: 528.45 | BW73: 1 | BX73: 1 | BZ73: 45943 | CA73: 45945 | CC73: =BW73+BX73+BY73 -> 2
AT74: Lorena | AU74: Ripoll Ferri | AV74: lripoll@correu.escoladeltreball.org | AW74: 34662244419 | AX74: 15/10/2025 11.30-12.30 | AY74: Yes | AZ74: I prefer to travel by plane | BA74: Barcelona | BB74: 45943 | BC74: 9 | BD74: Barcelona | BE74: 45945 | BF74: 19 | BG74: Yes | BI74: YES | BJ74: YES | BK74: YES | BL74: YES | BM74: Barcelona | BN74: Flight | BO74: 45943 | BP74: 0.50694444 | BQ74: VY8986 | BR74: Barcelona | BS74: 45945 | BT74: 0.75347222 | BU74: VY8983 | BV74: 324.1 | BW74: 1 | BX74: 1 | BZ74: 45943 | CA74: 45945 | CC74: =BW74+BX74+BY74 -> 2
A75: 45944 | B75: 09:30 - 10:30 | C75: 45943 | D75: 45945 | E75: 2502 | F75: Small Towns, Big Energy: Citizens Shaping a Sustainable Future | G75: Cities building tomorrow | H75: Workshop | I75: 25022524 | J75: Yes | K75: AISFOR SRL | L75: Italy | N75: Charalampos Chatzimallis ; Marina Varvesi | O75: chatzimallis@gmail.com ; varvesi@aisfor.it | P75: CITIZEN CROSSROADS | Q75: Representative | R75: João Pedro Gouveia - NOVA University of Lisbon - Professor - - ; Luigi Acquaviva - Association of Cities and Regions for sustainable Resource management - Project Manager - - ; Giulia Viero - Institute for European Energy and Climate Policy - Policy Expert - - | S75: yes | T75: YES | U75: Yes | V75: 3 | W75: João Pedro | X75: Gouveia | Y75: jplg@fct.unl.pt | Z75: Luigi | AA75: Acquaviva | AB75: l.acquaviva@gmail.com | AC75: Alice | AD75: Borsari | AE75: alice.borsari@eurac.edu | AF75: Yes | AG75: 3 | AH75: João Pedro | AI75: Gouveia | AJ75: jplg@fct.unl.pt | AK75: Luigi | AL75: Acquaviva | AM75: l.acquaviva@gmail.com | AN75: Alice | AO75: Borsari | AP75: alice.borsari@eurac.edu | AT75: João Pedro | AU75: Gouveia | AV75: jplg@fct.unl.pt | AW75: +351917428448 | AX75: 14th October 9h30 | AY75: Yes | AZ75: I prefer to travel by plane | BA75: Lisbon | BB75: 45943 | BC75: Early Afternoon | BD75: Brussels | BE75: 45945 | BF75: Late Morning | BG75: Yes | BI75: YES | BJ75: YES | BK75: YES | BL75: YES | BM75: Lisbon | BN75: Flight | BO75: 45943 | BP75: 0.68055556 | BQ75: TP644 | BR75: Lisbon | BS75: 45945 | BT75: 0.49305556 | BU75: TP641 | BV75: 304.32 | BW75: 1 | BX75: 1 | BZ75: 45943 | CA75: 45945 | CC75: =BW75+BX75+BY75 -> 2
AT76: Luigi | AU76: Acquaviva | AV76: l.acquaviva@gmail.com | AW76: 393665049991 | AX76: 14th October - 9:30-10:30 | AY76: Yes | AZ76: I have no preference regarding the mode of transport – please make a suggestion | BA76: Naples - Italy | BB76: 45943 | BC76: Any | BD76: Naples - Italy | BE76: 45947 | BF76: Any | BG76: Yes | BI76: YES | BJ76: YES | BK76: YES | BL76: YES | BM76: Naples - Italy | BN76: Flight | BO76: 45943 | BP76: 0.53819444 | BQ76: sn3170 | BR76: Naples - Italy | BS76: 45945 | BT76: 0.40625 | BU76: sn3169 | BV76: 356.92 | BW76: 1 | BX76: 1 | BZ76: 45943 | CA76: 45945 | CC76: =BW76+BX76+BY76 -> 2 | CF76: Speaker wants to leave on the 17th October. Can we book the flight on those dates? Extra nights on the 15th and 16th is on his own expenses | CG76: Yes, as long as the ticket is the same price or lower than the original proposed
AT77: Alice | AU77: Borsari | AV77: alice.borsari@eurac.edu | AW77: 00 39 3318958593 | AX77: 14.10.2025 time 09:30-10.30 | AY77: Yes | AZ77: I have no preference regarding the mode of transport – please make a suggestion | BA77: Bolzano | BB77: 45943 | BC77: 10 | BD77: Bolzano | BE77: 45946 | BF77: 10 | BG77: Yes | BI77: YES | BM77: Bolzano | BN77: Flight | BR77: Bolzano | CF77: Speaker wants to leave on the 16th October. Can we book the flight on those dates? Extra nights on the 15th is on her own expenses | CG77: Yes, as long as the ticket is the same price or lower than the original proposed
A78: 45944 | B78: 11:30 - 12:30 | C78: 45943 | D78: 45945 | E78: 2519 | F78: Reducing regulatory burden for investment and growth in regions and cities | G78: Cohesion and Growth for the Future | H78: Workshop | J78: No | K78: OECD | L78: France | N78: Alexandra Rusu ; Jorge Duran Laguna | O78: alexandra.rusu@oecd.org ; alexander.lembcke@oecd.org | P78: Organisation for Economic Co | Q78: operation and Development - Representative | R78: Jorge DURAN LAGUNA - European Commission - DG REGIO - Head of Sector - - ; Alexandra Rusu - OECD - Policy Expert - - ; Gunilla Thorstensson - Swedish Agency for Economic and Regional Growth - Policy Expert - - | S78: yes | T78: YES - 1 speaker TBC | U78: Yes | V78: 3 | W78: Alexandra | X78: Rusu | Y78: alexandra.rusu@oecd.org | Z78: Alexander | AA78: Lembcke | AB78: alexander.lembcke@oecd.org | AC78: Gunilla | AD78: Thorstensson (TBC) | AE78: Gunilla.Thorstensson@tillvaxtverket.se | AF78: Yes | AG78: 3 | AH78: Alexandra | AI78: Rusu | AJ78: alexandra.rusu@oecd.org | AK78: Alexander | AL78: Lembcke | AM78: alexander.lembcke@oecd.org | AN78: Gunilla | AO78: Thorstensson (TBC) | AP78: Gunilla.Thorstensson@tillvaxtverket.se | AQ78: no comment | AR78: positive | AS78: Deadline to complete the form: 31 July REMINDER SENT 08-08 | AT78: Alexandra Victoria | AU78: Rusu | AV78: alexandra.rusu@oecd.org | AW78: 33788916350 | AX78: 45944.479 | AY78: Yes | AZ78: I prefer to travel by train | BA78: Paris | BB78: 45943 | BC78: 0.66666667 | BD78: Brussels | BE78: 45945 | BF78: 1700 | BG78: Yes | BI78: YES | BJ78: YES | BK78: YES | BL78: YES | BM78: Paris | BN78: Train | BO78: 45943 | BP78: 0.68125 | BR78: Paris | BS78: 45945 | BT78: 0.71944444 | BV78: 318 | BW78: 1 | BX78: 1 | BZ78: 45943 | CA78: 45945 | CC78: =BW78+BX78+BY78 -> 2
AT79: Alexander | AU79: Lembcke | AV79: alexander.lembcke@oecd.org | AW79: +33651819491 | AX79: Tue 14/10/2025, 11:30 - 12:30 CET and Tue 14/10/2025, 17:00 - 18:00 CET | AY79: Yes | AZ79: I prefer to travel by train | BA79: Paris | BB79: 45943 | BC79: 16:00 | BD79: Paris | BE79: 45945 | BF79: 20:00 | BG79: Yes | BI79: YES | BJ79: YES | BK79: YES | BL79: YES | BM79: Paris | BN79: Train | BO79: 45943 | BP79: 0.66319444 | BQ79: EUR9359 | BR79: Paris | BS79: 45945 | BT79: 0.61319444 | BU79: EUR9350 | BW79: 1 | BX79: 1 | BZ79: 45943 | CA79: 45945 | CC79: =BW79+BX79+BY79 -> 2
AT80: Gunilla | AU80: Thorstensson (TBC) | AV80: Gunilla.Thorstensson@tillvaxtverket.se | AY80: Yes | BG80: Yes
A81: 45944 | B81: 17:00 - 18:00 | C81: 45943 | D81: 45945 | E81: 2522 | F81: Boosting regional competitiveness through entrepreneurship, innovation and circularity | G81: The Right to Stay: unlocking the potential of every territory | H81: Workshop | I81: 229523092522 | J81: Yes | K81: Climate KIC International Foundation | L81: Netherlands | N81: Alberto Minguela ; Katarzyna Balucka-debska | O81: alberto.minguela@climate-kic.org; katarzyna.balucka-debska@climate-kic.org | P81: EIT Climate - KIC | Q81: Representative | R81: Milan Petit - Systems Transformation Hub - Programme Manager - - ; Stientje Van Veldhoven - - President - - ; Eva Gladek - - - - | S81: yes | T81: YES | U81: Yes | V81: 3 | W81: Federico | X81: Esu | Y81: federico.esu@climate-kic.org | Z81: Rosanna | AA81: Haider | AB81: rosanna.haider@chiemgau.bayern | AC81: Stientje | AD81: Van Veldhoven | AE81: Stientje.vanVeldhoven@wri.org | AF81: Yes | AG81: 3 | AH81: Federico | AI81: Esu | AJ81: federico.esu@climate-kic.org | AK81: Rosanna | AL81: Haider | AM81: rosanna.haider@chiemgau.bayern | AN81: Stientje | AO81: Van Veldhoven | AP81: Stientje.vanVeldhoven@wri.org | AQ81: no comment | AS81: village close to Salzburg which is called Kuchl - by train | AT81: Federico | AU81: Esu | AV81: federico.esu@climate-kic.org | AW81: 393770875513 | AX81: 14 October, 17:00 hours | AY81: Yes | AZ81: I prefer to travel by plane | BA81: Cagliari | BB81: 45943 | BC81: morning | BD81: Cagliari | BE81: 45945 | BF81: late morning | BG81: Yes | BH81: Given the strike foreseen for 14 October and the timing of my session, it is fair to arrive on 13 October and to leave on 15 October (as flying back on 14 October evening is going to be unlikely given flights options Brussels-Cagliari) | BI81: YES | BJ81: YES | BK81: YES | BL81: YES | BM81: Cagliari | BN81: Flight | BO81: 45943 | BP81: 0.44097222 | BQ81: VY6467/VYVY8982 | BR81: Cagliari | BS81: 45945 | BT81: 0.75347222 | BU81: VY8983 | BV81: 545.27 | BW81: 1 | BX81: 1 | BZ81: 45943 | CA81: 45945 | CC81: =BW81+BX81+BY81 -> 2
AT82: Rosanna | AU82: Haider | AV82: rosanna.haider@chiemgau.bayern | AW82: 4915221565714 | AX82: 14.10.2025 at 5 pm | AY82: No | BB82: 45943 | BC82: morning | BD82: Cagliari | BE82: 45945 | BG82: Yes | BW82: 1 | BX82: 1 | BZ82: 45943 | CA82: 45945 | CC82: =BW82+BX82+BY82 -> 2
AT83: Stientje | AU83: Van Veldhoven | AV83: Stientje.vanVeldhoven@wri.org; marloes.toonen@wri.org | AW83: 31621703863 | AX83: Tue 14/10/2025, 17:00 - 18:00 CET | AY83: Yes | AZ83: I prefer to travel by train | BA83: Rotterdam | BB83: 45943 | BC83: 0.375 | BD83: Brussels | BE83: 45945 | BF83: TBD - depends on speaking slot most likely around noon | BG83: Yes | BI83: YES | BM83: Rotterdam | BN83: Train | BR83: Rotterdam
A84: 45944 | B84: 16:00 - 17:30 | C84: 45943 | D84: 45945 | E84: 2526 | F84: How can EU-funded programmes, projects, and policy-makers foster gender equality? Examples and lessons learnt from URBACT | G84: Cohesion and Growth for the Future | H84: Interactive session | J84: No | K84: URBACT Secretariat | L84: France | N84: Evgenia Koutsomarkou; Aleksandra Kluczka | O84: j.koutsomarkou@urbact.eu; a.kluczka@urbact.eu | P84: URBACT Secretariat | Q84: Head of Unit | R84: Clementine Gravier - URBACT Secretariat - Representative - -
A85: 45944 | B85: 09:30 - 11:00 | C85: 45943 | D85: 45945 | E85: 2535 | F85: From strategy to action: practical training on Land Suitability Analysis for sustainable development in Functional Urban Areas | G85: Cities building tomorrow | H85: Interactive session | J85: No | K85: European Urban Initiative | L85: France | N85: European Urban Initiative Permanent Secretariat ; Eilish O'Loughlin | O85: communication@urban-initiative.eu ; eilish@urban-initiative.eu | P85: European Urban Initiative | Q85: Representative | S85: yes | T85: yes | U85: Yes | V85: 1 | W85: Adina Dorina | X85: Vintan | Y85: avintan@worldbank.org | Z85: N/A | AA85: N/A | AB85: N/A | AC85: N/A | AD85: N/A | AE85: N/A | AF85: Yes | AG85: 3 | AH85: Marcel | AI85: Ionescu-Heroiu | AJ85: mionescuheroiu@worldbank.org | AK85: Grzegorz Aleksander | AL85: Wolszczak | AM85: gwolszczak@worldbank.org | AN85: Adina Dorina | AO85: Vintan | AP85: avintan@worldbank.org | AQ85: We will need for one speaker T&A coverage and for two speakers only accommodation coverage . | AR85: positive | AS85: Based in Petrosani, Romania, will take the plane from Cluj-Napoca, Romania. | AT85: Adina Dorina | AU85: Vintan | AV85: avintan@worldbank.org | AW85: 0040722697550 | AX85: 14th of October, 9.30 am | AY85: NO | BB85: 45943 | BE85: 45945 | BG85: Yes | BH85: I have already booked my flight and am getting in Brussels on the 13th of Oct. It is fine for me to cover the flight. Kindly let me know if the 2nd night could also be covered, so, the period 13-15th of Oct, or if I shall book myself the night of 14th. Thank you! | BI85: YES | BJ85: YES | BK85: YES | BL85: YES | BW85: 1 | BX85: 1 | BZ85: 45943 | CA85: 45945 | CG85: We can cover accommodation fro 13 to 15 October, before confirming the booking with the speakers please share with us the recap table so that we can make sure we have enough rooms left
AS86: Vienna, Austria | AT86: Marcel | AU86: Ionescu-Heroiu | AV86: mionescuheroiu@worldbank.org | AW86: 0040-741-610187 | AX86: October 14, 2025 | AY86: NO | BB86: 45943 | BE86: 45945 | BG86: Yes | BH86: Please confirm accomodation arrangements as fast as possible, to be able to secure affordable travel arrangements. | BI86: YES | BJ86: YES | BK86: YES | BL86: YES | BW86: 1 | BX86: 1 | BZ86: 45943 | CA86: 45945 | CG86: We can cover accommodation fro 13 to 15 October, before confirming the booking with the speakers please share with us the recap table so that we can make sure we have enough rooms left
AS87: Vienna, Austria | AT87: Grzegorz Aleksander | AU87: Wolszczak | AV87: gwolszczak@worldbank.org | AW87: +12022438970 | AX87: 14 October 2025; 9:30-11:00 | AY87: NO | BB87: 45943 | BE87: 45945 | BG87: Yes | BH87: I'll also participate in other sessions as a speaker. Accommodation for the whole EWRC would be very useful. | BI87: YES | BJ87: YES | BK87: YES | BL87: YES | BW87: 1 | BX87: 1 | BZ87: 45943 | CA87: 45945 | CF87: I'll also participate in other sessions as a speaker. Accommodation for the whole EWRC would be very useful. - Could we offer him more than 2 nights? He is covering his own travel and just need accommodation | CG87: We can cover accommodation fro 13 to 15 AOctober, before confirming the booking with the speakers please share with us the recap table so that we can make sure we have enough rooms left
A88: 45945 | B88: 14:00 - 15:30 | C88: 45945 | D88: 45946 | E88: 2543 | F88: Bridging borders: Interreg IPA, the Power Tool for Enlargement | G88: Cohesion and Growth for the Future | H88: Interactive session | J88: No | K88: Interact Office Vienna | L88: Austria | N88: Ivana Lazic ; Klaus Boele | O88: ivana.lazic@interact.eu ; Klaus.Boele@cor.europa.eu | P88: Interact Office Vienna | Q88: Head of Unit | R88: Moray Gilland - European Commission - DG REGIO - Head of Unit - -
A89: 45944 | B89: 16:00 - 17:30 | C89: 45943 | D89: 45945 | E89: 2559 | F89: Rural Proofing: Making Policies Work for Rural Areas through data/Earth observations | G89: The Right to Stay: unlocking the potential of every territory | H89: Interactive session | I89: 24372559 | J89: Yes | K89: P10 | L89: Netherlands | N89: Jasper Assen ; Martje Looijenga-Bekius | O89: jasper.assen@opsterland.nl ; europa@weststellingwerf.nl | P89: Municipality of Opsterland | Q89: Representative | R89: Alexia ROUBY - European Commission - Administrator - - ; Betty-Ann Bryce - OECD - Policy Expert - - ; Arjen van Gijssel - Berkelland - Deputy Mayor - - | S89: yes | T89: yes | U89: Yes | V89: 2 | W89: Betty-Ann | X89: Bryce | Y89: betty-ann.bryce@oecd.org | Z89: Christos | AA89: Moutsios | AB89: moutsios.c@pste.gov.gr | AF89: Yes | AG89: 2 | AH89: Betty-Ann | AI89: Bryce | AJ89: betty-ann.bryce@oecd.org | AK89: Christos | AL89: Moutsios | AM89: moutsios.c@pste.gov.gr | AQ89: no comment | AS89: city requested 20-08 | AT89: Betty-Ann | AU89: Bryce | AV89: betty-ann.bryce@oecd.org | AW89: +33 (0)6 27 20 49 71 | AX89: 14.10,2025 - 17:30 | AY89: Yes | AZ89: I prefer to travel by train | BA89: Paris | BB89: 45943 | BC89: 12 noon | BD89: Paris | BE89: 45945 | BF89: 10am | BG89: Yes | BI89: YES | BJ89: YES | BK89: YES | BL89: YES | BM89: Paris, France | BN89: Train | BO89: 45943 | BP89: 0.5125 | BQ89: EUR9339 | BR89: Paris, France | BS89: 45945 | BT89: 0.42569444 | BU89: EUR9322 | BV89: 318 | BW89: 1 | BX89: 1 | BZ89: 45943 | CA89: 45945 | CC89: =BW89+BX89+BY89 -> 2
AT90: Christos | AU90: Moutsios | AV90: moutsios.c@pste.gov.gr | AW90: 326973274022 | AX90: 14/10/2025 - 16:00 - 17:30 | AY90: No | BB90: 45943 | BE90: 45945 | BG90: Yes
A91: 45944 | B91: 17:00 - 18:00 | C91: 45943 | D91: 45945 | E91: 2560 | F91: Right to stay and live in small municipalities: evidence and experiences on the role of built environment, social environment and public services | G91: The Right to Stay: unlocking the potential of every territory | H91: Workshop | I91: 25602654 | J91: Yes | K91: ARCO (Action Research for CO-development) | L91: Italy | N91: Andrea Ferrannini; Serafin Pazos-Vidal | O91: andrea.ferrannini@pin.unifi.it; spv@aeidl.eu | P91: ARCO (Action Research for CO development) | Q91: Researcher | R91: Marianna Stori - Municipality of Gagliano Aterno - Representative - - ; Thibaut Guignard - Association Leader France - Representative - - ; Aistė Rutkauskienė - Society and Enterprise Development institute - Representative - - | S91: yes | T91: yes | U91: Yes | V91: 3 | W91: Marianna | X91: Stori | Y91: marianna.stori@gmail.com | Z91: Aistė | AA91: Rutkauskienė | AB91: aiste@vvpi.lt | AC91: Andrea | AD91: Ferrannini | AE91: andrea.ferrannini@pin.unifi.it | AF91: Yes | AG91: 3 | AH91: Marianna | AI91: Stori | AJ91: marianna.stori@gmail.com | AK91: Aistė | AL91: Rutkauskienė | AM91: aiste@vvpi.lt | AN91: Andrea | AO91: Ferrannini | AP91: andrea.ferrannini@pin.unifi.it | AQ91: no comment | AR91: positive | AS91: they would like t&a from the 13th to the 15th | AT91: Marianna | AU91: Stori | AV91: marianna.stori@gmail.com | AW91: +393331371568 | AX91: Tue 14/10/2025 (16:00 - 17:30 CET) | AY91: Yes | AZ91: I prefer to travel by plane | BA91: Rome | BB91: 45943 | BC91: Around 7pm | BD91: Rome | BE91: 45945 | BF91: Around 4 Pm | BG91: Yes | BI91: YES | BM91: Rome | BN91: Flight | BR91: Rome | CC91: =BW91+BX91+BY91 -> 0
AT92: Aistė | AU92: Rutkauskienė | AV92: aiste@vvpi.lt | AW92: 37062043662 | AX92: Tue 14/10/2025, 17:00 - 18:00 CET | AY92: Yes | AZ92: I prefer to travel by plane | BA92: Kaunas or Vilnius | BB92: 45943 | BC92: afternoon | BD92: Kaunas or Vilnius | BE92: 45945 | BF92: doesnt matter | BG92: Yes | BH92: Would like to live alone | BI92: YES | BN92: Flight | CC92: =BW92+BX92+BY92 -> 0
AT93: Andrea | AU93: Ferrannini | AV93: andrea.ferrannini@pin.unifi.it | AW93: +393385808722 | AX93: Tue 14/10/2025, 17:00 - 18:00 CET | AY93: Yes | AZ93: I prefer to travel by plane | BA93: Florence | BB93: 45943 | BC93: 11:30am | BD93: Pisa | BE93: 45945 | BF93: 11:20am | BG93: Yes | BH93: "I may need accommodation for two nights - i.e. arrival on the 13th and departure on the 15th. Indeed, our session is planned for the 14th at 5pm, making it difficult to plan a travel back to Italy on the same day. At the same time, due to these possible travel disruptions, it seems quite risky reaching Brussels on the 14th itself and I would like to avoid any potential issue being the coordinator/moderator of the session. Thanks in advance for your kind understanding. " | BI93: YES | BJ93: YES | BK93: YES | BL93: YES | BM93: Florence | BN93: Flight | BO93: 45943 | BP93: 0.47916667 | BQ93: sn3140 | BR93: Pisa | BS93: 45945 | BT93: 0.47222222 | BU93: fr5255 | BV93: 517.1 | BW93: 1 | BX93: 1 | BZ93: 45943 | CA93: 45945 | CC93: =BW93+BX93+BY93 -> 2
A94: 45944 | B94: 09:30 - 10:30 | C94: 45943 | D94: 45945 | E94: 2582 | F94: Navigating access to innovative financial instruments for green cities and regions | G94: Cities building tomorrow | H94: Workshop | J94: No | K94: EUROPEAN BANK FOR RECONSTRUCTION AND DEVELOPMENT (EBRD) - EU REPRESENTATIVE OFFICE | L94: Belgium | N94: Pippa Koszerek ; Esben Pejstrup | O94: KoszereP@ebrd.com ; esben.pejstrup@iclei.org | P94: EUROPEAN BANK FOR RECONSTRUCTION AND DEVELOPMENT (EBRD) | Q94: EU REPRESENTATIVE OFFICE - Officer | R94: Alessandra SGOBBI - European Commission - DG CLIMA - Head of Unit - - ; Jennifer McIntosh - ICLEI Europe - Head of Sector - - ; Anna-Maria Spyriouni - Climate Bonds Initiative Europe (ASBL) - Head of Sector - - | S94: yes | T94: YES | U94: Yes | V94: 2 | W94: Felicity | X94: Spors | Y94: sporsf@ebrd.com | Z94: Matthew | AA94: Bach | AB94: matthew.bach@iclei.org | AC94: N/A | AD94: N/A | AE94: N/A | AF94: Yes | AG94: 2 | AH94: Felicity | AI94: Spors | AJ94: sporsf@ebrd.com | AK94: Matthew | AL94: Bach | AM94: matthew.bach@iclei.org | AN94: N/A | AO94: N/A | AP94: N/A | AQ94: no comment | AR94: positive | AS94: They will need t&a for their speaker | AT94: Felicity | AU94: Spors | AV94: sporsf@ebrd.com | AW94: +44 7522985575 | AX94: 14-10-2025, 09:30-10:30 | AY94: Yes | AZ94: I prefer to travel by train | BA94: London | BB94: 45942 | BC94: 0.62777778 | BD94: London | BE94: 45945 | BF94: 0.36944444 | BG94: Yes | BI94: YES | BJ94: YES | BK94: YES | BL94: YES | BM94: London | BN94: Train | BR94: London | BW94: 1 | BX94: 1 | BZ94: 45943 | CA94: 45945 | CC94: =BW94+BX94+BY94 -> 2 | CF94: Please confirm if the speaker can arrive 1 day before (on the 12th) | CG94: We can cover the ticket as long as the price is the same or lower than the one originally offered. We do not cover for the extra nights
AT95: Matthew | AU95: Bach | AV95: matthew.bach@iclei.org | AW95: 491791358734 | AX95: 14-10-2025, 09:30-10:30 | AY95: Yes | AZ95: I prefer to travel by train | BA95: Freiburg im Breisgau, Germany | BB95: 45943 | BC95: After 12:00 | BD95: Freiburg im Breisgau, Germany | BE95: 45948 | BF95: Early morning | BG95: Yes | BH95: Return date is later so I am happy to proceed with price comparison. | BI95: YES | BJ95: YES | BK95: YES | BL95: YES | BM95: Freiburg im Breisgau, Germany | BN95: Train | BO95: 45943 | BP95: 0.58055556 | BR95: N/A | BS95: N/A | BT95: N/A | BU95: N/A | BV95: 377 | BW95: 1 | BX95: 1 | BZ95: 45943 | CA95: 45945 | CC95: 2 | CF95: Please confirm if the speaker can return 2 day later (on the 18th) | CG95: We can cover the ticket as long as the price is the same or lower than the one originally offered. We do not cover for the extra nights
A96: 45944 | B96: 16:00 - 17:30 | C96: 45943 | D96: 45945 | E96: 2585 | F96: Inclusive Future Sport Lab with NEB – Co-designing Rural Sports Services by New Olympiads | G96: The Right to Stay: unlocking the potential of every territory | H96: Interactive session | J96: No | K96: EuLabTEC | L96: Italy | N96: Francesco Marchionni ; Teresa Levi | O96: fmarchionni.euproject@gmail.com ; teresalevi95@gmail.com | P96: National Youth Council of Italy | Q96: Vice-President | R96: Daniele Taurino - Knowledge of Society - CEO - - ; Betty Geraga - Municipality of Levadia - - - | S96: yes | T96: YES | U96: Yes | V96: 3 | W96: Luigi | X96: Dell'Aquila | Y96: luigixdellaquila1@gmail.com | Z96: Andreas | AA96: Stamatakis | AB96: andreasstamatak2023@gmail.com | AC96: Francesco | AD96: Marchionni | AE96: francesco.marchionni@eulabtec.com | AF96: Yes | AG96: 3 | AH96: Luigi | AI96: Dell'Aquila | AJ96: luigixdellaquila1@gmail.com | AK96: Andreas | AL96: Stamatakis | AM96: andreasstamatak2023@gmail.com | AN96: Francesco | AO96: Marchionni | AP96: francesco.marchionni@eulabtec.com | AQ96: no comment | AT96: Luigi | AU96: Dell'Aquila | AV96: luigixdellaquila1@gmail.com | AW96: +393386064306 | AX96: Tue 14/10/2025 (16:00 - 17:30 CET) | AY96: Yes | AZ96: I prefer to travel by plane | BA96: Crotone | BB96: 45942 | BC96: 0.3125 | BD96: Crotone | BE96: 45946 | BF96: 0 | BG96: Yes | BH96: I request permission to participate in the other scheduled sessions and the entire event and, therefore, I request permission to extend my stay as indicated above. | BI96: YES | BJ96: YES | BK96: YES | BL96: YES | BM96: Crotone | BN96: Flight | BO96: 45943 | BP96: 0.63888889 | BQ96: az1178-7638 | BR96: Crotone | BS96: 45945 | BT96: 0.78819444 | BU96: az165-1173 | BV96: 455.9 | BW96: 1 | BX96: 1 | BZ96: 45943 | CA96: 45945 | CC96: =BW96+BX96+BY96 -> 2 | CF96: Speaker wants to arrive on the 12th of October. Can we book the flight on those dates? Extra nights on the 12th and 15th are on his own expenses | CG96: We can cover the ticket as long as the price is the same or lower than the one originally offered. We do not cover for the extra nights
AT97: Andreas | AU97: Stamatakis | AV97: andreasstamatak2023@gmail.com | AW97: 306939453432 | AX97: Tue 14/10/2025, time: 16:00 - 17:30 | AY97: Yes | AZ97: I prefer to travel by plane | BA97: Athens | BB97: 45943 | BC97: 0.33333333 | BD97: Athens | BE97: 45945 | BF97: 0.46875 | BG97: Yes | BH97: I request permission to participate in the other scheduled sessions and the entire event, and therefore to extend my stay beyond the scheduled date of our session. In any case, since this intervention is scheduled for October 14th and taking into account that a national strike is planned in Belgium on the same date, I ask that an additional night be covered in the hotel so that I can arrive a day earlier, on October 13th, and leave October 15th. | BI97: YES | BJ97: YES | BK97: YES | BL97: YES | BM97: Athens | BN97: Flight | BO97: 45943 | BP97: 0.33333333 | BQ97: a3 620 | BR97: Athens | BS97: 45945 | BT97: 0.62152778 | BU97: a3 621 | BV97: 480.95 | BW97: 1 | BX97: 1 | BZ97: 45943 | CA97: 45945 | CC97: =BW97+BX97+BY97 -> 2
AT98: Francesco | AU98: Marchionni | AV98: francesco.marchionni@eulabtec.com | AW98: 393403340077 | AX98: 14/10/2025 h 16:00 - 17:30 | AY98: Yes | AZ98: I prefer to travel by plane | BA98: Rome FCO | BB98: 45943 | BC98: Morning | BD98: Rome FCO | BE98: 45945 | BF98: Afternoon | BG98: Yes | BH98: If I can have the accomodation for 13 night and 14 night to strake reason. If it's not possible, please reserve it and I'll pay the extra night. | BI98: YES | BJ98: YES | BK98: YES | BL98: YES | BM98: Rome FCO | BN98: Flight | BO98: 45943 | BP98: 0.42361111 | BQ98: SN3176 | BR98: Rome FCO | BS98: 45945 | BT98: 0.62152778 | BU98: SN3181 | BV98: 487.67 | BW98: 1 | BX98: 1 | BZ98: 45943 | CA98: 45945 | CC98: =BW98+BX98+BY98 -> 2
A99: 45944 | B99: 15:30 - 16:30 | C99: 45943 | D99: 45945 | E99: 2593 | F99: Stimulating regional interventions to address developmental bottlenecks through hands-on capacity building and experimentation - Catching-up Regions | G99: The Right to Stay: unlocking the potential of every territory | H99: Workshop | I99: 25932614 | J99: Yes | K99: World Bank Group | L99: Belgium | N99: Grzegorz Wolszczak ; Sandra Spule | O99: gwolszczak@worldbank.org ; sandra.spule@gmail.com | P99: The World Bank | Q99: Programme Manager | R99: Peter Breyl - Regional Innovation Center of the Košice region - Director-General - - ; Linda SPROGE - European Commission - DG REGIO - Deputy Head of Unit - - ; Jolanta Blazaite - World Bank - Policy Expert - -
A100: 45944 | B100: 11:30 - 12:30 | C100: 45943 | D100: 45945 | E100: 2602 | F100: Integrated Clean Energy Transition Strategies – A Replacement for or Advancement Beyond SECAP? The Innovative Approach of the PLENTY-Life Project | G100: Cities building tomorrow | H100: Workshop | J100: No | K100: AIT Austrian Institute of Technology GmbH | L100: Austria | N100: Ali Hainoun ; Georg Neugebauer | O100: Ali.Hainoun@ait.ac.at ; georg.neugebauer@boku.ac.at | P100: AIT Austrian Institute of Technology GmbH | Q100: Researcher | R100: Georg NEUGEBAUER - BOKU University - Researcher - - ; Iudit BERE - SEMEREDI - Timiș County - Councillor - - ; Alice Borsari - Eurac Research - Researcher - - | S100: yes | T100: YES - 1 TBC (Alice Borsari included in another session) | U100: Yes | V100: 2 | W100: Iudit | X100: Bere-Semeredi | Y100: iudit.bere@cjtimis.ro | Z100: Ali | AA100: Hainoun | AB100: Ali.Hainoun@ait.ac.at | AF100: Yes | AG100: 2 | AH100: Iudit | AI100: Bere-Semeredi | AJ100: iudit.bere@cjtimis.ro | AK100: Ali | AL100: Hainoun | AM100: Ali.Hainoun@ait.ac.at | AQ100: no comment | AT100: Ali | AU100: Hainoun | AV100: Ali.Hainoun@ait.ac.at | AW100: 4366488256132 | AX100: 14-10-2025, 11:30-15:00 | AY100: Yes | AZ100: I prefer to travel by plane | BA100: Vienna | BB100: 45943 | BC100: 0.625 | BD100: Brussels | BE100: 45945 | BF100: 0.70833333 | BG100: Yes | BH100: In addition to the WS I am coordinating on 14-10-25, I also will be moderating another workshop, 14WS252602, on 15-10-2025. Thus, I need to be in Brussels on the 14th and 15th of October. Please consider that in booking the accommodation. | CF100: Please confirm whether we can cover the extra night on the 15th - ON HOLD | CG100: Please reach out to him to ask to let you know by Monday 18 August CoB if he confirms himself or replace himself by the speaker missing. No extra speaker covered. You can still accept a reply on Tuesday 19 August if need be.
...

Sheet Stands
A1: STANDHOLDERS INFORMATION | AL1: STANDHOLDER PREFERENCES | BA1: FOLLOW-UP | BE1: Travel information - confirmed | BZ1: APPROVALS
A2: Date | B2: Estimated arrival date | C2: Estimated departure date | D2: Index unique | E2: Title | F2: Thematic clusters | G2: Format | H2: Merged sessions | I2: Merged lead? | J2: Lead partner organisation name | K2: Lead partner organisation country of origin | L2: Associated partners | M2: Coordinator | N2: Email address | O2: Company name | P2: Job title | Q2: Answered | R2: Form/reminder sent | S2: Do any of your project members require travel coverage? | T2: Number of speakers for travel | U2: Travel - Speaker 1 - Name | V2: Travel - Speaker 1 - Name + last name | W2: Travel - Speaker 1 - Email address | X2: Travel - Speaker 2 - Name | Y2: Travel - Speaker 2 - Name + last name | Z2: Travel - Speaker 2 - Email address | AA2: Do any of your project members require accommodation coverage? | AB2: Number of speakers for accommodation | AC2: Accomodation - Speaker 1 - Name | AD2: Accomodation - Speaker 1 - Last name | AE2: Accomodation - Speaker 1 - Email address | AF2: Accomodation - Speaker 2 - Name | AG2: Accomodation - Speaker 2 - Last name | AH2: Accomodation - Speaker 2 - Email address | AI2: Additional comments | AJ2: Email follow up - Responses | AK2: Comments VO | AL2: First Name | AM2: Last name | AN2: Email address | AO2: Phone number | AP2: Date and time of your speaking slot | AQ2: Travel needed | AR2: Preferred mode of transport | AS2: City of departure | AT2: Date of departure | AU2: Time of departure | AV2: Return city | AW2: Preferred date of return | AX2: Preferred time of return | AY2: Accommoation needed | AZ2: Additional comments | BA2: Agency sent proposal | BB2: Guest confirmed proposal | BC2: Travel booked | BD2: Travel tickets sent to guest | BE2: Origin City (to Brussels) | BF2: Flight/Train | BG2: Date of departure | BH2: Flight/Train time | BI2: Flight number/Train | BJ2: Return City (from Brussels) | BK2: Date of return | BL2: Flight/Train time | BM2: Flight number/Train | BN2: Flight/Train cost | BO2: Hotel rate 13/10, €, excl. VAT | BP2: Hotel rate 14/10, €, excl. VAT | BQ2: Hotel rate 15/10, €, excl. VAT | BR2: 45943 | BS2: 45944 | BT2: 45945 | BU2: Check-in date | BV2: Check out date | BW2: Hotel nights | BX2: Hotel cost, €, excl. VAT | BY2: Total cost, € | BZ2: Client's approval needed | CA2: Client's approval received | CB2: Approval reason
A3: 14/10 - 15/10 | B3: 45943 | C3: 45946 | D3: 1960 | E3: Transnational cooperation: building solidarity, driving synergies & delivering change | F3: Cohesion and Growth for the Future | G3: Stand | I3: No | J3: Interreg North-West Europe | K3: France | M3: Rania Balia ; Martin Heibel | N3: rania@nweurope.eu ; mheibel@regione.sardegna.it | O3: Interreg North - West Europe | P3: Representative | Q3: yes | R3: reminder sent - However, the two stand holders, who are project representatives, have not yet been fully confirmed. There's also a possibility that their travel and accommodation is already covered through a different session during the week. Currently, we cannot specify exactly who these two representatives will be. If we do not meet your travel and accommodation deadlines, please feel free to withdraw our request for coverage. | S3: Yes | T3: 2 | U3: TBC | V3: TBC | W3: TBC | X3: TBC | Y3: TBC | Z3: TBC | AA3: Yes | AB3: 2 | AC3: TBC | AD3: TBC | AE3: TBC | AF3: TBC | AG3: TBC | AH3: TBC | AI3: no comment | AL3: TBC | AM3: TBC | AN3: TBC | AQ3: YES | AY3: YES | BW3: =BR3+BS3+BT3 -> 0
AL4: TBC | AM4: TBC | AN4: TBC | AQ4: YES | AY4: YES | BW4: =BR4+BS4+BT4 -> 0
A5: 14/10 - 15/10 | B5: 45943 | C5: 45946 | D5: 2005 | E5: Cohesion and Growth for the Future-the role of the civil society | F5: Cohesion and Growth for the Future | G5: Stand | I5: No | J5: European Economic and Social Committee | K5: Belgium | M5: Graziella Dilkinska ; Georgios Meleas | N5: Graziella.Dilkinska@eesc.europa.eu ; Georgios.Meleas@eesc.europa.eu | O5: European Economic and Social Committee | P5: Assistant | BW5: =BR5+BS5+BT5 -> 0
A6: 14/10 - 15/10 | B6: 45943 | C6: 45946 | D6: 2024 | E6: Interreg Europe – How cooperation unlocks regional potential | F6: The Right to Stay: unlocking the potential of every territory | G6: Stand | I6: No | J6: Interreg Europe | K6: France | M6: Marie Soucasse; Vladimir Sestovic | N6: m.soucasse@interregeurope.eu; v.sestovic@policylearning.eu | O6: Interreg Europe Policy Learning Platform | P6: Representative | Q6: yes | R6: YES - especial case, not travel,2 accomodation | S6: No, my speakers do not need coverage | T6: 0 | AA6: Yes | AB6: 2 | AC6: Marie | AD6: Soucasse | AE6: m.soucasse@interregeurope.eu | AF6: Irma | AG6: ASTRAUSKAITE | AH6: i.astrauskaite@interregeurope.eu | AI6: no comment | AK6: LILLE, FRANCE | AL6: Marie | AM6: Soucasse | AN6: m.soucasse@interregeurope.eu | AO6: +33647675364 | AP6: N/A | AQ6: NO | AT6: 45943 | AW6: 45946 | AY6: YES | BA6: YES | BB6: YES | BC6: YES | BD6: YES | BE6: Lille | BF6: TRAIN | BG6: TRAIN | BH6: TRAIN | BI6: TRAIN | BJ6: Lille | BK6: TRAIN | BL6: TRAIN | BM6: TRAIN | BN6: TRAIN | BR6: 1 | BS6: 1 | BT6: 1 | BU6: 13/010/2025 | BV6: 45946 | BW6: =BR6+BS6+BT6 -> 3 | BZ6: Marie and Irma, both standholders who only need accommodation (and not travel), have confirmed that they will come by train from Lille. Could you please confirm whether we can therefore cover both nights, 13 and 14 October, since they are not coming by car? (we discussed this stand the other day) Marie and Irma, both standholders who only need accommodation, have been informed that we will cover only the nights of 13 and 14 October and have told us the following: “The last train to Lille is at 18:16 on the evening of 15 October, and it is our understanding that we need to be at the stand until 18:00, which makes it difficult for us to catch our train on time.” Could you please confirm if, in this case, we can also book the night of 15 October for both of them? Please note that when making the estimates at the beginning of the process, these rooms for the 15th were planned for them and are still available. | CA6: confirmed | CB6: 20/08 Caroline : last departing train incompatible with stand schedule
AL7: Irma | AM7: Astrauskaite-Denis | AN7: i.Astrauskaite@interregeurope.eu | AO7: +33623408961 | AP7: N/A | AQ7: NO | AT7: 45943 | AW7: 45946 | AY7: YES | BA7: YES | BB7: YES | BC7: YES | BD7: YES | BE7: Lille | BF7: TRAIN | BG7: TRAIN | BH7: TRAIN | BI7: TRAIN | BJ7: Lille | BK7: TRAIN | BL7: TRAIN | BM7: TRAIN | BN7: TRAIN | BR7: 1 | BS7: 1 | BT7: 1 | BU7: 13/010/2025 | BV7: 45946 | BW7: =BR7+BS7+BT7 -> 3 | BZ7: Marie and Irma, both standholders who only need accommodation (and not travel), have confirmed that they will come by train from Lille. Could you please confirm whether we can therefore cover both nights, 13 and 14 October, since they are not coming by car? (we discussed this stand the other day) Marie and Irma, both standholders who only need accommodation, have been informed that we will cover only the nights of 13 and 14 October and have told us the following: “The last train to Lille is at 18:16 on the evening of 15 October, and it is our understanding that we need to be at the stand until 18:00, which makes it difficult for us to catch our train on time.” Could you please confirm if, in this case, we can also book the night of 15 October for both of them? Please note that when making the estimates at the beginning of the process, these rooms for the 15th were planned for them and are still available. | CA7: confirmed | CB7: 20/08 Caroline : last departing train incompatible with stand schedule
A8: 14/10 - 15/10 | B8: 45943 | C8: 45946 | D8: 2066 | E8: Have Your Say Portal | F8: Cohesion and Growth for the Future | G8: Stand | I8: No | J8: European Commission - Secretariat General | K8: Belgium | M8: Corina - Luciana Pirleci ; Carlos Perez-Padilla | N8: Corina-Luciana.PIRLECI@ec.europa.eu ; carlos.perez-padilla@ec.europa.eu | O8: European Commission | P8: Secretariat General - Representative | BW8: =BR8+BS8+BT8 -> 0
A9: 14/10 - 15/10 | B9: 45943 | C9: 45946 | D9: 2067 | E9: Unlock and Attract skills and talent through Regional Innovation Capacity insights | F9: The Right to Stay: unlocking the potential of every territory | G9: Stand | I9: No | J9: Region Vasterbotten | K9: Sweden | M9: Jenny Ferry ; Antti Kotinaa | N9: jenny.ferry@regionvasterbotten.se ; antti.kotimaa@savonia.fi | O9: Region Vasterbotten | P9: Project Manager | Q9: Yes | R9: YES | S9: Yes | T9: 2 | U9: Antti | V9: Kotimaa | W9: antti.kotimaa@savonia.fi | X9: Jenny | Y9: Ferry | Z9: jenny.ferry@regionvasterbotten.se | AA9: Yes | AB9: 2 | AC9: Antti | AD9: Kotimaa | AE9: antti.kotimaa@savonia.fi | AF9: Jenny | AG9: Ferry | AH9: jenny.ferry@regionvasterbotten.se | AI9: "Astric has a stand" | AL9: Antti | AM9: Kotimaa | AN9: antti.kotimaa@savonia.fi | AO9: +358 447856449 | AP9: N/A | AQ9: YES | AR9: I prefer to travel by plane | AS9: Kuopio | AT9: 45943 | AU9: Any time | AV9: Kuopio | AW9: 45945 | AX9: Any time | AY9: YES | BA9: YES | BB9: YES | BC9: YES | BD9: YES | BE9: Kuopio | BF9: Flight | BG9: 45943 | BH9: 0.58333333 | BI9: AY366/AY1545 | BJ9: Kuopio | BK9: 45946 | BL9: 0.48611111 | BM9: AY1542 | BN9: € 582,56 | BR9: 1 | BS9: 1 | BT9: 1 | BU9: 13/010/2025 | BV9: 45946 | BW9: =BR9+BS9+BT9 -> 3 | BZ9: Over budget: 585.56€ | CA9: Shadi: ok | CB9: Approval received via email on 8 August
AL10: Jenny | AM10: Ferry | AN10: jenny.ferry@regionvasterbotten.se | AO10: +46 70 2830498 | AP10: N/A | AQ10: YES | AR10: I prefer to travel by plane | AS10: Umeå, Sweden | AT10: 45943 | AU10: Ca 8:00-10:00 (morning time) | AV10: Brussels | AW10: 45946 | AX10: morning | AY10: YES | AZ10: Like to return to Umeå Sweden at night October 16th | BA10: YES | BB10: YES | BC10: YES | BD10: YES | BE10: Umeå, Sweden | BF10: Flight | BG10: 45943 | BH10: 0.40625 | BI10: D84006/SN2292 | BJ10: Umeå, Sweden | BK10: 45946 | BL10: 0.40972222 | BM10: SN2291 | BN10: 542.78 | BR10: 1 | BS10: 1 | BT10: 1 | BU10: 13/010/2025 | BV10: 45946 | BW10: =BR10+BS10+BT10 -> 3
A11: 14/10 - 15/10 | B11: 45943 | C11: 45946 | D11: 2073 | E11: Make your local government climate and future-proof from within! | F11: Cities building tomorrow | G11: Stand | I11: No | J11: Province of Antwerp | K11: Belgium | M11: Tirza Pulleman ; Maxime Rekkers | N11: tirza.pulleman@provincieantwerpen.be ; maxime@adaptatieatelier.net | O11: Province of Antwerp | P11: Project Manager | BW11: =BR11+BS11+BT11 -> 0
A12: 14/10 - 15/10 | B12: 45943 | C12: 45946 | D12: 2092 | E12: RIVCircular project: Regional Innovation Valleys | F12: The Right to Stay: unlocking the potential of every territory | G12: Stand | I12: No | J12: Fundación para el Conocimiento madri+d | K12: Spain | M12: Juana Sanz ; Natalia Memberto | N12: juana.sanz@madrimasd.org ; natalia.mamberto@madrimasd.org | O12: Fundación para el Conocimiento madri+d | P12: Project Manager | Q12: Yes | R12: special case: she did not include herself in the survey - checking intrnally | S12: Yes | T12: 2 | U12: Natalia | V12: Mamberto Debernardi | W12: natalia.mamberto@madrimasd.org | X12: Juana | Y12: Sanz | Z12: juana.sanz@madrimasd.org | AA12: Yes | AB12: 2 | AC12: Natalia | AD12: Mamberto Debernardi | AE12: natalia.mamberto@madrimasd.org | AF12: Juana | AG12: Sanz | AH12: juana.sanz@madrimasd.org | AI12: No comment | AL12: Natalia | AM12: Mamberto Debernardi | AN12: natalia.mamberto@madrimasd.org | AO12: 34690059344 | AP12: N/A | AQ12: YES | AR12: I prefer to travel by plane | AS12: Madrid | AT12: 45943 | AU12: Afternoon | AV12: Madrid | AW12: 45946 | AX12: Morning | AY12: YES | BA12: YES | BB12: YES | BC12: YES | BD12: YES | BE12: Madrid | BF12: Flight | BG12: 45943 | BH12: 0.63541667 | BI12: UX1173 | BJ12: Madrid | BK12: 45946 | BL12: 0.44791667 | BM12: UX1172 | BN12: 321.02 | BR12: 1 | BS12: 1 | BT12: 1 | BU12: 13/010/2025 | BV12: 45946 | BW12: =BR12+BS12+BT12 -> 3
AL13: Juana Maria | AM13: Sanz García | AN13: juana.sanz@madrimasd.org | AO13: 34620421759 | AP13: Tue 14/10/2025 at 09:30 to Wed 15/10/2025 at 18:00 CET | AQ13: YES | AR13: I prefer to travel by plane | AS13: Madrid | AT13: 45943 | AU13: afternoon | AV13: Madrid | AW13: 45946 | AX13: Morning | AY13: YES | BA13: YES | BB13: YES | BC13: YES | BD13: YES | BE13: Madrid | BF13: Flight | BG13: 45943 | BH13: 0.63541667 | BI13: UX1173 | BJ13: Madrid | BK13: 45946 | BL13: 0.44791667 | BM13: UX1172 | BN13: 321.02 | BR13: 1 | BS13: 1 | BT13: 1 | BU13: 13/010/2025 | BV13: 45946 | BW13: =BR13+BS13+BT13 -> 3
A14: 14/10 - 15/10 | B14: 45943 | C14: 45946 | D14: 2099 | E14: Budva and Kotor 2030: Smart, Sustainable, and Inclusive Coastal Growth | F14: Cities building tomorrow | G14: Stand | I14: No | J14: Budva Municipality | K14: Montenegro | M14: Luka Mihailovic ; Nadja Vukasovic | N14: luka.mihailovic@budva.me ; nadja.vukasovic@kotor.me | O14: Budva Municipality | P14: Representative | Q14: yes | R14: YES | S14: Yes | T14: 2 | U14: Luka | V14: Mihailovic | W14: luka.mihailovic@budva.me | X14: Nađa | Y14: Vukasovic | Z14: nadja.vukasovic@kotor.me | AA14: Yes | AB14: 2 | AC14: Luka | AD14: Mihailovic | AE14: luka.mihailovic@budva.me | AF14: Nađa | AG14: Vukasovic | AH14: nadja.vukasovic@kotor.me | AK14: We would like to inform you that both the Mayor of Budva and the Mayor of Kotor will be attending the EU Week of Regions and Cities this year. Their presence is intended to actively support our joint stand: “Budva and Kotor 2030: Smart, Sustainable and Inclusive Coastal Growth.” In light of this, we have decided to arrange travel and accommodation independently. | AL14: Luka | AM14: Mihailovic | AN14: luka.mihailovic@budva.me | AQ14: NO | AY14: NO | BW14: =BR14+BS14+BT14 -> 0
AL15: Nađa | AM15: Vukasovic | AN15: nadja.vukasovic@kotor.me | AQ15: NO | AY15: NO | BW15: =BR15+BS15+BT15 -> 0
A16: 14/10 - 15/10 | B16: 45943 | C16: 45946 | D16: 2104 | E16: Living without Leaving - a nomadic art exhibition | F16: The Right to Stay: unlocking the potential of every territory | G16: Stand | I16: No | J16: European Commission - DG REGIO | K16: Belgium | M16: Gaby Hagmuller ; Maria Galewska | N16: Gaby.HAGMULLER@ec.europa.eu ; maria.galewska@ec.europa.eu | O16: European Commission - DG REGIO | P16: Programme Manager | Q16: yes | R16: yes - undeliverable emails | S16: Yes | T16: 2 | U16: Eva | V16: Omahen | W16: eva.omahen@gov.si | X16: Freia | Y16: Verbinc | Z16: Freia.Verbinc.student@gov.si | AA16: Yes | AB16: 2 | AC16: Eva | AD16: Omahen | AE16: eva.omahen@gov.si | AF16: Freia | AG16: Verbinc | AH16: Freia.Verbinc.student@gov.si | AL16: Eva | AM16: Omahen | AN16: eva.omahen@gov.si | AO16: 38631393038 | AP16: N/A | AQ16: YES | AR16: I prefer to travel by plane | AS16: Ljubljana | AT16: 45943 | AU16: in the morning, before 10 am | AV16: Ljubljana | AW16: 45946 | AX16: in the afternoon, after 14 | AY16: YES | AZ16: I would like to attend the opening of the European Week of Regions and Cities, so if possible, please find a flight in the morning, as the session starts at 14.00. It can also be from neighbouring airports, such as Zagreb, regarding that I am flexible. | BA16: YES | BB16: YES | BC16: YES | BD16: YES | BE16: Ljubljana | BF16: Flight | BG16: 45943 | BH16: 0.28472222 | BI16: OU456 | BJ16: Ljubljana | BK16: 45946 | BL16: 0.85416667 | BM16: OU4457 | BN16: 425.84 | BR16: 1 | BS16: 1 | BT16: 1 | BU16: 13/010/2025 | BV16: 45946 | BW16: =BR16+BS16+BT16 -> 3
AL17: Freia | AM17: Verbinc | AN17: Freia.Verbinc.student@gov.si | AO17: 38631279026 | AP17: N/A | AQ17: YES | AR17: I prefer to travel by plane | AS17: Ljubljana | AT17: 45943 | AU17: / | AV17: Ljubljana | AW17: 45946 | AX17: / | AY17: YES | BA17: YES | BB17: YES | BC17: YES | BD17: YES | BE17: Ljubljana | BF17: Flight | BG17: 45943 | BH17: 0.45138889 | BI17: LX2273/LX780 | BJ17: Ljubljana | BK17: 45946 | BL17: 0.67013889 | BM17: SN3343 | BN17: 541.02 | BR17: 1 | BS17: 1 | BT17: 1 | BU17: 13/010/2025 | BV17: 45946 | BW17: =BR17+BS17+BT17 -> 3
A18: 14/10 - 15/10 | B18: 45943 | C18: 45946 | D18: 2139 | E18: Empowering Regions: Education as the Catalyst for Cohesion and Growth | F18: Cohesion and Growth for the Future | G18: Stand | I18: No | J18: European Association of Regional and Local Authorities for Lifelong Learning | K18: Belgium | M18: Alicia Gaban ; Noelia Cantero Gonzalvez | N18: alicia.gaban@earlall.eu ; noelia.cantero@earlall.eu | O18: European Association of Regional and Local Authorities for Lifelong Learning | P18: Project Manager | Q18: Yes | R18: yes | S18: Yes | T18: 2 | U18: Camilla | V18: Winter | W18: camilla@camillawinter.se | X18: Alejandra | Y18: Martinez | Z18: zuzendaria@fpsanturtzilh.eus | AA18: Yes | AB18: 2 | AC18: Camilla | AD18: Winter | AE18: camilla@camillawinter.se | AF18: Alejandra | AG18: Martinez | AH18: zuzendaria@fpsanturtzilh.eus | AI18: No comment | AL18: Camilla | AM18: Winter | AN18: camilla@camillawinter.se | AO18: 46705446606 | AP18: N/A | AQ18: YES | AR18: I prefer to travel by plane | AS18: Göteborg | AT18: 45942 | AU18: 18.2 | AV18: Göteborg | AW18: 45945 | AX18: 21 | AY18: YES | AZ18: I would like to travel 12 Oct 18.20 from Göteborg Landvetter Airport Sweden and back from Brussels15 Oct 21.00. Thank you! | BA18: YES | BB18: YES | BC18: YES | BD18: YES | BE18: Göteborg | BF18: Flight | BG18: 45943 | BH18: 0.29166667 | BI18: SN2324 | BJ18: Göteborg | BK18: 45945 | BL18: 0.875 | BM18: SN2319 | BN18: € 548,73 | BR18: 1 | BS18: 1 | BT18: 0 | BU18: 13/010/2025 | BV18: 45945 | BW18: =BR18+BS18+BT18 -> 2 | BZ18: Please confirm if she can leave on the 12th | CA18: She can arrive on the 12th granted that the ticket is the same price or lower of the original ticket proposed. Accommodation for the extra night is not covered.
AL19: Alejandra | AM19: Martinez Santos | AN19: zuzendaria@fpsanturtzilh.eus | AO19: 34604551586 | AP19: N/A | AQ19: YES | AR19: I prefer to travel by plane | AS19: Bilbao | AT19: 45943 | AU19: 0.33333333 | AV19: Bilbao | AW19: 45945 | AX19: 0.83333333 | AY19: YES | AZ19: I prefer to travel on these days, bit if it is not possible it will be ok on 13th to 16th | BA19: YES | BB19: YES | BC19: YES | BD19: YES | BE19: Bilbao | BF19: Flight | BG19: 45943 | BH19: 0.37152778 | BI19: VY1421/VY8986 | BJ19: Bilbao | BK19: 45946 | BL19: 0.58680556 | BM19: SN3711 | BN19: € 498,97 | BR19: 1 | BS19: 1 | BT19: 1 | BU19: 13/010/2025 | BV19: 45946 | BW19: =BR19+BS19+BT19 -> 3 | BZ19: Please confirm if she can return 1 day before (on the 15th) | CA19: This speaker and the one above can both leave 15 August at8pm or later, however if no tickets available one could stay until 16 August with accommodation covered and the other can leave on 15 August earlier.
A20: 14/10 - 15/10 | B20: 45943 | C20: 45946 | D20: 2140 | E20: #MakeEUBlue - cities in action! | F20: Cities building tomorrow | G20: Stand | I20: No | J20: ACTeon | K20: France | M20: Pierre Strosser ; Ginevra Alda | N20: p.strosser@acteon-environment.eu ; ginevra@aldaintranet.org | O20: ACTeon | P20: Director General | Q20: Yes | R20: yes | S20: Yes | T20: 2 | U20: Molly | V20: Wingate | W20: m.wingate@acteon-environment.eu | X20: Olga | Y20: Mashkina | Z20: o.mashkina@acteon-environment.eu | AA20: Yes | AB20: 2 | AC20: Molly | AD20: Wingate | AE20: m.wingate@acteon-environment.eu | AF20: Olga | AG20: Mashkina | AH20: o.mashkina@acteon-environment.eu | AI20: No comment | AL20: Molly | AM20: Wingate | AN20: m.wingate@acteon-environment.eu | AO20: 33767602651 | AP20: NA | AQ20: YES | AR20: I prefer to travel by train | AS20: Colmar, via Strasbourg | AT20: 45943 | AU20: 0.35833333 | AV20: Colmar, via Strasbourg | AW20: 45946 | AX20: 0.55347222 | AY20: YES | AZ20: Thank you :) | BA20: YES | BB20: YES | BC20: YES | BD20: YES | BE20: Colmar, via Strasbourg | BF20: Train | BG20: 45943 | BH20: 0.3375 | BI20: ICe9568/UER9333 | BJ20: Colmar, via Strasbourg | BK20: 45946 | BL20: 0.55347222 | BM20: TGV9874 | BN20: € 387,00 | BR20: 1 | BS20: 1 | BT20: 1 | BU20: 13/010/2025 | BV20: 45946 | BW20: =BR20+BS20+BT20 -> 3
AL21: Olga | AM21: Mashkina | AN21: o.mashkina@acteon-environment.eu | AO21: 33788077851 | AP21: N/A | AQ21: YES | AR21: I prefer to travel by train | AS21: Strasbourg | AT21: 45943 | AU21: 0.43819444 | AV21: Strasbourg | AW21: 45946 | AX21: 0.55347222 | AY21: YES | BA21: YES | BB21: YES | BC21: YES | BD21: YES | BE21: Strasbourg | BF21: Train | BG21: 45943 | BH21: 0.36944444 | BI21: ICe9568/UER9333 | BJ21: Strasbourg | BK21: 45946 | BL21: 0.55347222 | BM21: TGV9874 | BN21: 343 | BR21: 1 | BS21: 1 | BT21: 1 | BU21: 13/010/2025 | BV21: 45946 | BW21: =BR21+BS21+BT21 -> 3
A22: 14/10 - 15/10 | B22: 45943 | C22: 45946 | D22: 2144 | E22: Youth4Cooperation | F22: Cohesion and Growth for the Future | G22: Stand | I22: No | J22: European Commission - DG REGIO | K22: Belgium | M22: Beniamino Brunati ; Milena Pallota | N22: Beniamino.BRUNATI@ec.europa.eu ; M.Pallotta@aebr.eu | O22: European Commission - DG REGIO | P22: Assistant | BW22: =BR22+BS22+BT22 -> 0
A23: 14/10 - 15/10 | B23: 45943 | C23: 45946 | D23: 2149 | E23: Empowering Climate Action: A New Era of Local Resilience in Porto’s Metropolitan Region | F23: Cohesion and Growth for the Future | G23: Stand | I23: No | J23: Porto Metropolitan Area | K23: Portugal | M23: Ana Paula Abreu ; Claudia Alves | N23: apabreu@amp.pt ; claudia.alves@magellancircle.eu | O23: Porto Metropolitan Area | P23: Director | Q23: yes | R23: yes | S23: Yes | T23: 2 | U23: Ana Paula | V23: Abreu | W23: apabreu@amp.pt | X23: Andrea | Y23: Azevedo | Z23: aazevedo@amp.pt | AA23: Yes | AB23: 2 | AC23: Ana Paula | AD23: Abreu | AE23: apabreu@amp.pt | AF23: Andrea | AG23: Azevedo | AH23: aazevedo@amp.pt | AI23: Porto- Brussels on 13th and returned to Porto on the 16th octobre | AL23: Ana Paula | AM23: Abreu | AN23: apabreu@amp.pt | AO23: 351961526866 | AP23: N/A | AQ23: YES | AR23: I prefer to travel by plane | AS23: Porto, Portugal | AT23: 45943 | AU23: 08.00AM | AV23: Porto, Portugal | AW23: 45946 | AX23: 01:00PM | AY23: YES | BA23: YES | BB23: YES | BC23: YES | BD23: YES | BE23: Porto, Portugal | BF23: Flight | BG23: 45943 | BH23: 0.34375 | BI23: FR2929 | BJ23: Porto, Portugal | BK23: 45946 | BL23: 0.5625 | BM23: FR2928 | BN23: 274.78 | BR23: 1 | BS23: 1 | BT23: 1 | BU23: 13/010/2025 | BV23: 45946 | BW23: =BR23+BS23+BT23 -> 3
AL24: Andrea | AM24: Azevedo | AN24: aazevedo@amp.pt | AO24: +351934835785 | AP24: N/A | AQ24: YES | AR24: I prefer to travel by plane | AS24: Porto, Portugal | AT24: 45943 | AU24: Morning, since 08H AM | AV24: Porto, Portugal | AW24: 45946 | AX24: Afternoon, since 01H PM | AY24: YES | BA24: YES | BB24: YES | BC24: YES | BD24: YES | BE24: Porto, Portugal | BF24: Flight | BG24: 45943 | BH24: 0.34375 | BI24: FR2929 | BJ24: Porto, Portugal | BK24: 45946 | BL24: 0.5625 | BM24: FR2928 | BN24: 274.78 | BR24: 1 | BS24: 1 | BT24: 1 | BU24: 13/010/2025 | BV24: 45946 | BW24: =BR24+BS24+BT24 -> 3
A25: 14/10 - 15/10 | B25: 45943 | C25: 45946 | D25: 2197 | E25: OECD tools for climate and development strategies | F25: Cohesion and Growth for the Future | G25: Stand | I25: No | J25: OECD | K25: France | M25: Eric Gonnard ; Josep Espesa Reig | N25: regionstat@oecd.org ; josep.espesareig@oecd.org | O25: OECD | P25: Representative | BW25: =BR25+BS25+BT25 -> 0
A26: 14/10 - 15/10 | B26: 45943 | C26: 45946 | D26: 2213 | E26: High-quality statistics and data on Europe | F26: Cohesion and Growth for the Future | G26: Stand | I26: No | J26: Eurostat | K26: Luxembourg | M26: Giorgia Macchia ; Maria Hajdu | N26: Giorgia.MACCHIA@ec.europa.eu ; Maria.HAJDU@ec.europa.eu | O26: European Commission | P26: Eurostat - Representative | BW26: =BR26+BS26+BT26 -> 0
A27: 14/10 - 15/10 | B27: 45943 | C27: 45946 | D27: 2222 | E27: EU Mission on Adaptation to Climate Change | F27: The Right to Stay: unlocking the potential of every territory | G27: Stand | I27: No | J27: Ricardo | K27: United Kingdom | M27: Maria Cao ; Manny Sidhu | N27: maria.cao@ricardo.com ; maninder.sidhu@ricardo.com | O27: Ricardo | P27: Representative | BW27: =BR27+BS27+BT27 -> 0
A28: 14/10 - 15/10 | B28: 45943 | C28: 45946 | D28: 2240 | E28: Culture for Resilience | F28: Cities building tomorrow | G28: Stand | I28: No | J28: Varde Municipality | K28: Denmark | M28: Marie Feddersen ; Tarja Hautamäki | N28: mafe@vardebib.dk ; Tarja.Hautamaki@obotnia.fi | O28: Varde Municipality | P28: Representative | Q28: yes | R28: yes | S28: Yes | T28: 2 | U28: Pia | V28: Blomström | W28: pia.blomstrom@obotnia.fi | X28: Marie | Y28: Feddersen | Z28: mafe@vardebib.dk | AA28: Yes | AB28: 2 | AC28: Pia | AD28: Blomström | AE28: pia.blomstrom@obotnia.fi | AF28: Marie | AG28: Feddersen | AH28: mafe@vardebib.dk | AL28: Margot Pia Johanna | AM28: Blomström | AN28: pia.blomstrom@obotnia.fi | AO28: +358443206668 OR +358458554600 | AP28: N/A | AQ28: YES | AR28: I prefer to travel by plane | AS28: Kokkola/Pietarsaari | AT28: 45943 | AU28: Morning/forenoon | AV28: Kokkola/Pietarsaari | AW28: 45946 | AX28: Midday/Afternoon | AY28: YES | AZ28: The small airport is joint one for two cities Kokkola and Pietarsaari and there are not so many flights from there, hope you will find suitable connections via Helsinki to Brussels. | BA28: YES | BB28: YES | BC28: YES | BD28: YES | BE28: Kokkola/Pietarsaari | BF28: Flight | BG28: 45943 | BH28: 0.22916667 | BI28: AY1541 | BJ28: Kokkola/Pietarsaari | BK28: 45946 | BL28: 0.48611111 | BM28: AY1542 | BN28: 544.56 | BR28: 1 | BS28: 1 | BT28: 1 | BU28: 13/010/2025 | BV28: 45946 | BW28: =BR28+BS28+BT28 -> 3
AL29: Marie | AM29: Feddersen | AN29: mafe@vardebib.dk | AO29: 4528261309 | AP29: N/A | AQ29: YES | AR29: I have no preference regarding the mode of transport – please make a suggestion | AS29: Bramming, Denmark or Billund Denmark | AT29: 45945 | AU29: Early morning | AV29: Bramming, Denmark or Billund Denmark | AW29: 45946 | AX29: Evening | AY29: YES | BW29: =BR29+BS29+BT29 -> 0 | BZ29: Please confirm if she can leave on the 15th and return on the 16th | CA29: Since the other colleague is present from 13, so will be at the stand on October 14, we can confirm arrival on 15 October and leave on 16 October granted that the ticket price is the same or lower than the one originally offered.
A30: 14/10 - 15/10 | B30: 45943 | C30: 45946 | D30: 2241 | E30: Twin Cities Wanted: Join JUST STREETS to (Re)design Streets that are Sustainable, Safe, and Inclusive for All Citizens! | F30: Cities building tomorrow | G30: Stand | I30: No | J30: Climate Alliance | K30: Belgium | M30: Friederike Lebus ; Marie Boutin | N30: f.lebus@climatealliance.org ; m.boutin@climatealliance.org | O30: Climate Alliance | P30: Project Manager | Q30: yes | R30: YES | S30: Yes | T30: 2 | U30: Friederike | V30: Lebus | W30: f.lebus@climatealliance.org | X30: Marie | Y30: Boutin | Z30: m.boutin@climatealliance.org | AA30: Yes | AB30: 2 | AC30: Friederike | AD30: Lebus | AE30: f.lebus@climatealliance.org | AF30: Marie | AG30: Boutin | AH30: m.boutin@climatealliance.org | AI30: no comment | AL30: Friederike | AM30: Lebus | AN30: f.lebus@climatealliance.org | AO30: 4917631646232 | AP30: N/A | AQ30: YES | AR30: I prefer to travel by train | AS30: Frankfurt am Main | AT30: 45943 | AU30: 0.51736111 | AV30: Frankfurt am Main | AW30: 45949 | AX30: 0.51736111 | AY30: YES | AZ30: For train booking with Deutsche Bahn: I own a Bahncard50 2nd class (bahncard number 7081 4112 2883 9904). I would like to extend my stay for private reasons and only return on Sunday 19 Oct. The train ticket shouldn't be more expensive than it would be on 16 Oct. | BA30: YES | BB30: YES | BC30: YES | BD30: YES | BE30: Frankfurt am Main | BF30: Flight | BG30: 45943 | BH30: 0.51736111 | BI30: NVS314 | BJ30: Frankfurt am Main | BK30: 45949 | BL30: 0.51736111 | BM30: NVS315 | BN30: € 251,98 | BR30: 1 | BS30: 1 | BT30: 1 | BU30: 13/010/2025 | BV30: 45946 | BW30: =BR30+BS30+BT30 -> 3 | BZ30: Please confirm if she can return on the 19. he would like to extend his stay for private reasons and only return on Sunday 19 Oct. | CA30: We can cover accommodation 13-16 October and the ticket (granted that the ticket is the same price or below the original proposed). Additional nights not coverred
AL31: Marie | AM31: Boutin | AN31: m.boutin@climatealliance.org | AO31: 4917676678810 | AP31: N/A | AQ31: YES | AR31: I prefer to travel by train | AS31: Berlin | AT31: 45943 | AU31: Leave Berlin not earlier than 8:30 | AV31: Berlin | AW31: 45946 | AX31: Leave Brussels not earlier than 15:00 | AY31: YES | AZ31: I will attend the Covenant of Mayors ceremony on the 16th of October. Therefore I would like to leave later in the day. If it is possible to apply reductions, I have a BahnCard 25 with Deutsche Bahn. I will be on holidays with no access to my emails from 10-17 August. | BA31: YES | BB31: YES | BC31: YES | BD31: YES | BE31: Berlin | BF31: Train | BG31: 45943 | BH31: 0.37291667 | BI31: ICE314 | BJ31: Berlin | BK31: 45946 | BL31: 0.68194444 | BM31: ICE317 | BN31: 367.98 | BR31: 1 | BS31: 1 | BT31: 1 | BU31: 13/010/2025 | BV31: 45946 | BW31: =BR31+BS31+BT31 -> 3
A32: 14/10 - 15/10 | B32: 45943 | C32: 45946 | D32: 2249 | E32: A Sea of Green: Shaping a resilient and sustainable tomorrow for Greater Athens | F32: Cities building tomorrow | G32: Stand | I32: No | J32: Managing Authority of the Programme Attiki | K32: Greece | M32: Angelos Spiliotis; Gianna Krokou | N32: spiliotis@mou.gr; ikrokou@mou.gr | O32: Managing Authority of the Programme Attiki | P32: Head of Unit | Q32: yes | R32: DO NOT NEED COVERAGE | T32: 0 | AB32: 0 | AI32: they will cover the travel and accommodation themself | BW32: =BR32+BS32+BT32 -> 0
A33: 14/10 - 15/10 | B33: 45943 | C33: 45946 | D33: 2280 | E33: Unlocking EU Research & Innovation: get tailored insight and support for your region | F33: Cohesion and Growth for the Future | G33: Stand | I33: No | J33: European Commission - DG RTD | K33: Belgium | M33: Roberta Pattono ; Jacopo Grazzini | N33: Roberta.PATTONO@ec.europa.eu ; Jacopo.Grazzini@ec.europa.eu | O33: European Commission | P33: DG RTD - Administrator | BW33: =BR33+BS33+BT33 -> 0
A34: 14/10 - 15/10 | B34: 45943 | C34: 45946 | D34: 2290 | E34: METACITY - Showcasing the small and medium size city of the future | F34: Cities building tomorrow | G34: Stand | I34: No | J34: Municipality of Fundão | K34: Portugal | M34: Eurico Neves ; Ricardo Goncalves | N34: eurico.neves@inova.business ; ricardogoncalves@cm-fundao.pt | Q34: yes | R34: yes | S34: Yes | T34: 1 | U34: Jennie | V34: Olofsson | W34: jennie.olofsson@harnosand.se | X34: Mylos | Y34: Prokysek | Z34: milos.prokysek@mupisek.cz | AA34: Yes | AB34: 1 | AC34: Jennie | AD34: Olofsson | AE34: jennie.olofsson@harnosand.se | AF34: Mylos | AG34: Prokysek | AH34: milos.prokysek@mupisek.cz | AL34: Jennie | AM34: Olofsson | AN34: jennie.olofsson@harnosand.se | AO34: 460703011831 | AP34: N/A | AQ34: YES | AR34: I prefer to travel by plane | AS34: Sundsvall, Sweden | AT34: 45943 | AU34: Morning | AV34: Sundsvall, Sweden | AW34: 45946 | AX34: Afternoon/evening | AY34: YES | AZ34: I’d prefer to take the train from Sundsvall to Arlanda Airport in Stockholm and then fly to Brussels. The same applies to the return trip. Everything to avoid domestic flights in Sweden, when possible. | BA34: YES | BB34: YES | BC34: YES | BD34: YES | BE34: Sundsvall, Sweden | BF34: Flight | BG34: 45942 | BH34: 0.72916667 | BI34: SN2294 | BJ34: Sundsvall, Sweden | BK34: 45946 | BL34: 0.60416667 | BM34: SN2293 | BN34: € 546,99 | BR34: 1 | BS34: 1 | BT34: 1 | BU34: 13/010/2025 | BV34: 45946 | BW34: =BR34+BS34+BT34 -> 3
AL35: Mylos | AM35: Prokysek | AN35: milos.prokysek@mupisek.cz | AO35: 420777695976 | AP35: Tue 14/10/2025 at 09:30 to Wed 15/10/2025 at 18:00 CET | AQ35: NO | AY35: NO | BW35: =BR35+BS35+BT35 -> 0
A36: 14/10 - 15/10 | B36: 45943 | C36: 45946 | D36: 2301 | E36: European Capitals of Inclusion and Diversity 2026 and European Diversity Month 2026 | F36: Cities building tomorrow | G36: Stand | I36: No | J36: European Commission - DG JUST | K36: Belgium | M36: Maria Langiewicz ; Anu Ritz | N36: Maria.LANGIEWICZ@ec.europa.eu ; Anu.RITZ@ec.europa.eu | O36: European Commission - DG JUST | P36: Representative | BW36: =BR36+BS36+BT36 -> 0
A37: 14/10 - 15/10 | B37: 45943 | C37: 45946 | D37: 2308 | E37: European Parliamentary Research Service | F37: Cohesion and Growth for the Future | G37: Stand | I37: No | J37: European Parliamentary Research Service | K37: Belgium | M37: Emmanuel Alvarez ; Vasileios Margaras | N37: EMMANUEL.ALVAREZ@EUROPARL.EUROPA.EU ; VASILEIOS.MARGARAS@EUROPARL.EUROPA.EU | O37: EP Research Service | P37: Administrator | BW37: =BR37+BS37+BT37 -> 0
A38: 14/10 - 15/10 | B38: 45943 | C38: 45946 | D38: 2317 | E38: b-solutions: Facilitating cross-border solutions for a better future for border regions | F38: Cohesion and Growth for the Future | G38: Stand | I38: No | J38: Association of European Border Regions (AEBR) | K38: Germany | M38: Cinzia Dellagiacoma ; Mariane Bloudeau | N38: c.dellagiacoma@aebr.eu ; M.Bloudeau@aebr.eu | O38: Association of European Border Regions | P38: Project Manager | BW38: =BR38+BS38+BT38 -> 0
A39: 14/10 - 15/10 | B39: 45943 | C39: 45946 | D39: 2349 | E39: Cross-border Energy Communities: Building Energy Cooperation across Borders | F39: The Right to Stay: unlocking the potential of every territory | G39: Stand | I39: No | J39: Transfrontier Operational Mission (MOT) | K39: France | M39: Anouck Moulin ; Jean Peyrony | N39: anouck.moulin@mot.asso.fr ; jean.peyrony@mot.asso.fr | O39: Transfrontier Operational Mission (MOT) | P39: Policy Officer | Q39: yes | R39: special case: 2 travel, no accommodation - yes | S39: Yes | T39: 2 | U39: Mariane | V39: Bloudeau | W39: M.Bloudeau@aebr.eu | X39: Anouck | Y39: Moulin | Z39: anouck.moulin@mot.asso.fr | AA39: No, my speakers do not need accommodation coverage. | AB39: 0 | AI39: no comment | AL39: Mariane | AM39: Bloudeau | AN39: M.Bloudeau@aebr.eu | AO39: 4917642090666 | AP39: N/A | AQ39: YES | AR39: I prefer to travel by plane | AS39: Berlin | AT39: 45943 | AU39: 0.48611111 | AV39: Berlin | AW39: 45945 | AX39: 0.86458333 | AY39: NO | AZ39: If possible, I would prefer to fly back to Berlin on 15 October evening. If not, the second option would be to fly back to Berlin on 16 October at 18:35 (departure time from Brussels with Brussels airlines). | BA39: YES | BB39: YES | BC39: YES | BD39: YES | BE39: Berlin | BF39: Flight | BG39: 45943 | BH39: 0.48611111 | BI39: SN2582 | BJ39: Berlin | BK39: 45945 | BL39: 0.86458333 | BM39: SN2591 | BN39: € 542,21 | BR39: 1 | BS39: 1 | BT39: 0 | BU39: 13/010/2025 | BV39: 45945 | BW39: =BR39+BS39+BT39 -> 2 | BZ39: Finally, there are two standholders for whom the session coordinators indicated that they would not need accommodation, only travel coverage. However, when filling in the form, both indicated that they need both travel & accommodation. Since we have available rooms, could we make an exception and cover their nights on 13 and 14 October? | CA39: Confirmed
AL40: Anouck | AM40: Moulin | AN40: anouck.moulin@mot.asso.fr | AO40: 33744316245 | AP40: N/A | AQ40: YES | AR40: I prefer to travel by train | AS40: Paris | AT40: 45943 | AU40: 7.30 | AV40: Paris | AW40: 45945 | AX40: 18.30 | AY40: NO | BA40: YES | BB40: YES | BC40: YES | BD40: YES | BE40: Paris | BF40: Flight | BG40: 45943 | BH40: 0.725 | BI40: EUR9369 | BJ40: Paris | BK40: 45945 | BL40: 0.77986111 | BM40: EUR9474 | BN40: € 318,00 | BR40: 1 | BS40: 1 | BT40: 0 | BU40: 13/010/2025 | BV40: 45945 | BW40: =BR40+BS40+BT40 -> 2 | BZ40: Finally, there are two standholders for whom the session coordinators indicated that they would not need accommodation, only travel coverage. However, when filling in the form, both indicated that they need both travel & accommodation. Since we have available rooms, could we make an exception and cover their nights on 13 and 14 October? | CA40: Confirmed
A41: 14/10 - 15/10 | B41: 45943 | C41: 45946 | D41: 2366 | E41: VAMVAKOU REVIVAL - ESTABLISHMENT AND OPERATION OF A BUSINESS INCUBATOR | F41: Cohesion and Growth for the Future | G41: Stand | I41: No | J41: Region of Peloponnese | K41: Greece | M41: Ioanna Lampropoulou; Antonios Psarakis | N41: ilampropoulou@mou.gr; apsarakis@mou.gr | O41: Region of Peloponnese | P41: Representative | Q41: yes | R41: reminder sent | S41: Yes | T41: 2 | U41: tbc | V41: tbc | W41: tbc | X41: tbc | Y41: tbc | Z41: tbc | AA41: Yes | AB41: 2 | AC41: tbc | AD41: tbc | AE41: tbc | AF41: tbc | AG41: tbc | AH41: tbc | AI41: no comment | AL41: tbc | AM41: tbc | AN41: tbc | AQ41: YES | AY41: YES | BW41: =BR41+BS41+BT41 -> 0
AL42: tbc | AM42: tbc | AN42: tbc | AQ42: YES | AY42: YES | BW42: =BR42+BS42+BT42 -> 0
A43: 14/10 - 15/10 | B43: 45943 | C43: 45946 | D43: 2384 | E43: Empowering Communities through EU Innovation | F43: Cohesion and Growth for the Future | G43: Stand | I43: No | J43: Publications Office of the European Union | K43: Luxembourg | M43: Cecilia Charlier ; Dominika Uhrikova | N43: Cecilia.CHARLIER@publications.europa.eu ; Dominika.UHRIKOVA@ec.europa.eu | O43: Publications Office of the European Union | P43: Assistant | BW43: =BR43+BS43+BT43 -> 0
A44: 14/10 - 15/10 | B44: 45943 | C44: 45946 | D44: 2401 | E44: Cohesion for Transitions: Supporting Regions for a Greener Future | F44: Cohesion and Growth for the Future | G44: Stand | I44: No | J44: European Commission - DG REGIO | K44: Belgium | M44: Bolanle Hammed ; Victoria Huisa | N44: bolanle.hammed@ecorys.com ; victoria.huisa@ecorys.com | O44: ECORYS | P44: Consultant | BW44: =BR44+BS44+BT44 -> 0
A45: 14/10 - 15/10 | B45: 45943 | C45: 45946 | D45: 2417 | E45: Supporting entrepreneurs and SMEs: working together | F45: Cohesion and Growth for the Future | G45: Stand | I45: No | J45: European Commission - DG GROW | K45: Belgium | M45: Marijana Juras ; Alberto Valenzano | N45: Marijana.JURAS@ec.europa.eu ; Alberto.VALENZANO@ec.europa.eu | O45: European Commission | P45: DG GROW - Representative | BW45: =BR45+BS45+BT45 -> 0
A46: 14/10 - 15/10 | B46: 45943 | C46: 45946 | D46: 2427 | E46: Not a "Typicalp" european project! | F46: The Right to Stay: unlocking the potential of every territory | G46: Stand | I46: No | J46: REGIONAL AGRICULTURAL INSTITUTE | K46: Italy | M46: Sabina Valentini ; Luca Vernetti-Prot | N46: s.valentini@iaraosta.it ; l.vernetti@iaraosta.it | O46: REGIONAL AGRICULTURAL INSTITUTE | P46: Representative | Q46: yes | R46: YES | S46: Yes | T46: 2 | U46: Giorgia | V46: Gambino | W46: g.gambino@iaraosta.it | X46: Mathieu | Y46: Merlet | Z46: m.merlet@iaraosta.it | AA46: Yes | AB46: 2 | AC46: Giorgia | AD46: Gambino | AE46: g.gambino@iaraosta.it | AF46: Mathieu | AG46: Merlet | AH46: m.merlet@iaraosta.it | AI46: Our proposal includes tastngs. Is it possible to have a fridge at the stand? | AL46: Giorgia | AM46: Gambino | AN46: m.merlet@iaraosta.it | AO46: +39 3313450501 | AP46: N/A | AQ46: YES | AR46: I prefer to travel by plane | AS46: Aosta (Aosta Valley) | AT46: 45942 | AU46: Morning | AV46: Brussels | AW46: 45945 | AX46: Morning | AY46: YES | AZ46: We would like to point out the need to arrive in Brussels early (Sunday, 12 October) in order to prepare and set up our stand in the best possible way in terms of layout and organisation of the planned activities. We would also need to delay our departure from Brussels by one day (Thursday, 16 October) due to the late hour of the Regiostars Awards ceremony for which our project has been selected. | BA46: YES | BB46: YES | BC46: YES | BD46: YES | BE46: Aosta (Aosta Valley) | BF46: Flight | BG46: 45942 | BH46: 0.47569444 | BI46: SN2714 | BJ46: Aosta (Aosta Valley) | BK46: 45946 | BL46: 0.625 | BM46: SN2721 | BN46: € 363,97 | BR46: 1 | BS46: 1 | BT46: 1 | BU46: 13/010/2025 | BV46: 45946 | BW46: =BR46+BS46+BT46 -> 3 | BZ46: Please confirm if she can arrival 1 day before (on the 12th) | CA46: She can arrive on the 12th granted that the ticket is the same price or lower of the original ticket proposed. Accommodation for the extra night is not covered. If possible offer return on 15 evening at 8pm onwards
AL47: Mathieu | AM47: Merlet | AN47: m.merlet@iaraosta.it | AO47: 393477352972 | AP47: N/A | AQ47: YES | AR47: I prefer to travel by plane | AS47: Aosta (Aosta Valley) | AT47: 45942 | AU47: Morning | AV47: Aosta (Aosta Valley) | AW47: 45946 | AX47: Morning | AY47: YES | AZ47: We would like to point out the need to arrive in Brussels early (Sunday, 12 October) in order to prepare and set up our stand in the best possible way in terms of layout and organisation of the planned activities. We would also need to delay our departure from Brussels by one day (Thursday, 16 October) due to the late hour of the Regiostars Awards ceremony for which our project has been selected. | BA47: YES | BB47: YES | BC47: YES | BD47: YES | BE47: Aosta (Aosta Valley) | BF47: Flight | BG47: 45942 | BH47: 0.47569444 | BI47: SN2714 | BJ47: Aosta (Aosta Valley) | BK47: 45946 | BL47: 0.625 | BM47: SN2721 | BN47: € 363,97 | BR47: 1 | BS47: 1 | BT47: 1 | BU47: 13/010/2025 | BV47: 45946 | BW47: =BR47+BS47+BT47 -> 3 | BZ47: Please confirm if he can arrive 1 day before (on the 12th) | CA47: She can arrive on the 12th granted that the ticket is the same price or lower of the original ticket proposed. Accommodation for the extra night is not covered. If possible offer return on 15 evening at 8pm onwards
A48: 14/10 - 15/10 | B48: 45943 | C48: 45946 | D48: 2440 | E48: Giving knowledge cities more visibility within Europe | F48: Cities building tomorrow | G48: Stand | I48: No | J48: EUniverCities Network | K48: United Kingdom | M48: Alison Ward ; Andrew Dean | N48: A.M.S.Ward@exeter.ac.uk ; A.Dean@exeter.ac.uk | O48: EUniverCities Network | P48: Administrator | Q48: yes | R48: - special case: travel 1 - accomodation 2 - yes | S48: Yes | T48: 1 | U48: Andrew | V48: Dean | W48: a.dean@exeter.ac.uk | AA48: Yes | AB48: 2 | AC48: Andrew | AD48: Dean | AE48: a.dean@exeter.ac.uk | AF48: Alison | AG48: Ward | AH48: A.M.S.Ward@exeter.ac.uk | AI48: no comment | AK48: ALMERE, (NEAR AMSTERDAM) | AL48: Alison | AM48: Ward | AN48: A.M.S.Ward@exeter.ac.uk | AO48: +44 (0) 7526519106 | AP48: N/A | AQ48: NO | AT48: 45943 | AW48: 45945 | AY48: YES | AZ48: If possible, please book in same hotel as my colleague Andrew Dean - on same stand | BR48: 1 | BS48: 1 | BT48: 0 | BU48: 13/010/2025 | BV48: 45945 | BW48: =BR48+BS48+BT48 -> 2 | CA48: Please ask where are they coming from/based.
AL49: Andrew | AM49: Dean | AN49: a.dean@exeter.ac.uk | AO49: +44 (0) 7900692593 | AP49: N/A | AQ49: YES | AR49: I prefer to travel by train | AS49: Exeter, UK via Paddington | AT49: 45943 | AU49: 07:52 (13:01 Eurostar) | AV49: Exeter, UK | AW49: 45945 | AX49: 17:56 Eurostar (20:03 to Exeter from Paddington) | AY49: YES | AZ49: If possible, please book in same hotel as my colleague Alison Ward - on same stand | BA49: YES | BB49: YES | BC49: YES | BD49: YES | BE49: Exeter, UK via Paddington | BF49: Train | BG49: 45943 | BH49: 0.54236111 | BI49: EUR9132 | BJ49: Exeter, UK via Paddington | BK49: 45945 | BL49: 0.74722222 | BM49: EUR9153 | BN49: € 519,80 | BR49: 1 | BS49: 1 | BT49: 0 | BU49: 13/010/2025 | BV49: 45945 | BW49: =BR49+BS49+BT49 -> 2 | BZ49: Please confirm if she can return 1 day before (on the 15th) | CA49: Ok to return earlier
A50: 14/10 - 15/10 | B50: 45943 | C50: 45946 | D50: 2460 | E50: Joint Research Centre: EU rgional statistics explained | F50: The Right to Stay: unlocking the potential of every territory | G50: Stand | I50: No | J50: Joint Research Centre | K50: Italy | M50: Lucia Salgado ; Astrid Nedee | N50: Lucia.SALGADO-BAENA@ec.europa.eu ; Astrid.NEDEE@ec.europa.eu | O50: BAENA@ec.europa.eu | P50: Joint Research Centre - Representative | BW50: =BR50+BS50+BT50 -> 0
A51: 14/10 - 15/10 | B51: 45943 | C51: 45946 | D51: 2470 | E51: Showcasing Interreg’s results across key policy areas | F51: Cohesion and Growth for the Future | G51: Stand | I51: No | J51: Interact office Valencia | K51: Spain | M51: Rosa Escamilla ; Valeria Cibrario | N51: rosa.escamilla@interact.eu ; valeria.cibrario@interact.eu | O51: Interact | Q51: yes | R51: yes | S51: Yes | T51: 2 | U51: Rosa | V51: Escamilla Torregrosa | W51: rosa.escamilla@interact.eu | X51: Valeria | Y51: Cibrario | Z51: valeria.cibrario@interact.eu | AA51: Yes | AB51: 2 | AC51: Rosa | AD51: Escamilla Torregrosa | AE51: rosa.escamilla@interact.eu | AF51: Valeria | AG51: Cibrario | AH51: valeria.cibrario@interact.eu | AI51: no comment | AL51: Rosa | AM51: Escamilla Torregrosa | AN51: rosa.escamilla@interact.eu | AO51: 34616192005 | AP51: N/A | AQ51: YES | AR51: I prefer to travel by plane | AS51: Valencia, Spain | AT51: 45942 | AU51: evening/night | AV51: Valencia, Spain | AW51: 45945 | AX51: evening/night | AY51: YES | AZ51: I'd prefer to travel on the evening of 12/10 to be able to prep the stand on 13/10. Due to other engagements, I need to travel back to Valencia on the evening of 15/10. Thanks! | BA51: YES | BB51: YES | BC51: YES | BD51: YES | BE51: Valencia, Spain | BF51: Flight | BG51: 45943 | BH51: 0.59027778 | BI51: SN3752 | BJ51: Valencia, Spain | BK51: 45945 | BL51: 0.83680556 | BM51: LX789 | BN51: € 539,88 | BR51: 1 | BS51: 1 | BT51: 0 | BU51: 13/010/2025 | BV51: 45945 | BW51: =BR51+BS51+BT51 -> 2 | BZ51: Please confirm if it is possible to book the flight on the 12 (instead of 13) and return flight on the 15th. We would inform him that he would need to pay the extra night on the 12th | CA51: She can arrive on the 12th granted that the ticket is the same price or lower of the original ticket proposed. Accommodation for the extra night is not covered. Ok to return on October 15 at any time since the colleague is covering (staying until October 16)
AL52: Valeria | AM52: Cibrario | AN52: valeria.cibrario@interact.eu | AO52: 34649324937 | AP52: N/A | AQ52: YES | AR52: I prefer to travel by plane | AS52: Valencia, Spain | AT52: 45943 | AU52: 0.59027778 | AV52: Valencia, Spain | AW52: 45946 | AX52: 0.6875 | AY52: YES | AZ52: Direct flight is preferred, if possible | BA52: YES | BB52: YES | BC52: YES | BD52: YES | BE52: Valencia, Spain | BF52: Flight | BG52: 45943 | BH52: 0.59027778 | BI52: SN3752 | BJ52: Valencia, Spain | BK52: 45946 | BL52: 0.6875 | BM52: SN3751 | BN52: 517.77 | BR52: 1 | BS52: 1 | BT52: 1 | BU52: 13/010/2025 | BV52: 45946 | BW52: =BR52+BS52+BT52 -> 3
A53: 14/10 - 15/10 | B53: 45943 | C53: 45946 | D53: 2527 | E53: Think Local, Act Together! | F53: Cohesion and Growth for the Future | G53: Stand | I53: No | J53: Zabala Innovation | K53: Spain | M53: Paula Iribarren Toni; Irene Biancani | N53: piribarren@zabala.es; irene.biancani@fedarene.org | O53: Zabala Innovation | P53: Representative | Q53: yes | R53: YES | S53: Yes | T53: 2 | U53: Anna | V53: Mansson | W53: anna.mansson@energikontorsyd.se | X53: Marina | Y53: Malossi | Z53: marina.malossi@aessenergy.it | AA53: Yes | AB53: 2 | AC53: Anna | AD53: Mansson | AE53: anna.mansson@energikontorsyd.se | AF53: Marina | AG53: Malossi | AH53: marina.malossi@aessenergy.it | AL53: Anna Sofia | AM53: Frideborg Månsson | AN53: anna.mansson@energikontorsyd.se | AO53: 467035088529 | AP53: N/A | AQ53: YES | AR53: I prefer to travel by train | AS53: 2025-10-10 Karlskrona /Hamburg 2025-10-13 Hamburg-Brussels | AT53: 2025-10-10 (Karlskrona-Hamburg) 2025-10-13 (Hamburg-Brussels) | AU53: 2025-10-10 After 13:00 2025-10-13 Before lunch | AV53: Brussels- Karlskrona | AW53: 45945 | AX53: Possible to find night tran connection? Otherwise early 2025-10-16. Preferably back in Karlskrona 2025-10-16 15:30 | AY53: YES | AZ53: I will of course arrange my own accommodation in Hamburg, so I need 13-15(16) in Brussels. | BW53: =BR53+BS53+BT53 -> 0 | BZ53: She will arrange her own accommodation in Hamburg - ASK TRAVEL AGENCY prices of the tickets on both fates | CA53: We can offer the train travel (10oct) with the longer stop in Hamburg. Of course, we will not cover the extra nights but only the ones already foreseen for her session (from 13 to 16)
AL54: Marina | AM54: Malossi | AN54: marina.malossi@aessenergy.it | AO54: 393382043845 | AP54: n/a | AQ54: YES | AR54: I prefer to travel by plane | AS54: Bologna | AT54: 45943 | AU54: afternoon | AV54: Bologna | AW54: 45945 | AX54: evening | AY54: YES | AZ54: I would linke to depart on 15th October in the evening, if it's not possible, it will be ok to travel on 16th morning | BA54: YES | BB54: YES | BC54: YES | BD54: YES | BE54: Bologna | BF54: Flight | BG54: 45943 | BH54: 0.77083333 | BI54: SN 3126 | BJ54: Bologna | BK54: 45945 | BL54: 0.8125 | BM54: LH 5589- LH5678 | BR54: 1 | BS54: 1 | BT54: 0 | BU54: 13/010/2025 | BV54: 45945 | BW54: =BR54+BS54+BT54 -> 2 | CA54: If possible, ok to travel 15 evening
A55: 14/10 - 15/10 | B55: 45943 | C55: 45946 | D55: 2530 | E55: The URBACT IV programme | F55: Cities building tomorrow | G55: Stand | I55: No | J55: URBACT Secretariat | K55: France | M55: Evgenia Koutsomarkou ; Camilla Chiappini | N55: j.koutsomarkou@urbact.eu ; c.chiappini@urbact.eu | O55: URBACT Secretariat | P55: Head of Unit | BW55: =BR55+BS55+BT55 -> 0
A56: 14/10 - 15/10 | B56: 45943 | C56: 45946 | D56: 2557 | E56: European Urban Initiative: Supporting cities of all sizes across Europe | F56: Cohesion and Growth for the Future | G56: Stand | I56: No | J56: European Urban Initiative | K56: France | M56: European Urban Initiative Permanent Secretariat ; Eleni Kefallinou | N56: communication@urban-initiative.eu; eleni@urban-initiative.eu | O56: initiative.eu | P56: European Urban Initiative - Representative | BW56: =BR56+BS56+BT56 -> 0
A57: 14/10 - 15/10 | B57: 45943 | C57: 45946 | D57: 2562 | E57: EEA and Norway Grants: Investing in People and Regions | F57: Cohesion and Growth for the Future | G57: Stand | I57: No | J57: EEA and Norway Grants | K57: Belgium | M57: Gunnar Gardarsson ; Raquel Torres | N57: gunnar.gardarsson@efta.int ; torresprolraquel@gmail.com | O57: EEA and Norway Grants | P57: Representative | BW57: =BR57+BS57+BT57 -> 0
A58: 14/10 - 15/10 | B58: 45943 | C58: 45946 | D58: 2577 | E58: ICLEI Europe - Local Governments for Sustainability | F58: Cities building tomorrow | G58: Stand | I58: No | J58: ICLEI Europe | K58: Germany | M58: Esben Pejstrup | N58: esben.pejstrup@iclei.org | O58: ICLEI Europe | P58: Representative | Q58: yes | R58: yes | S58: Yes | T58: 1 | U58: Marine | V58: Francois | W58: marine.francois@iclei.org | AA58: Yes | AB58: 1 | AC58: Marine | AD58: Francois | AE58: marine.francois@iclei.org | AI58: (Fields were mandatory to submit, so I had to put my name several times. Thank you!) | AL58: Marine | AM58: Francois | AN58: marine.francois@iclei.org | AO58: 33770311832 | AP58: N/A | AQ58: YES | AR58: I prefer to travel by train | AS58: Frankfurt-am-Main Flughafen | AT58: 45943 | AU58: 0.35416667 | AV58: Frankfurt-am-Main Flughafen | AW58: 45946 | AX58: 0.43402778 | AY58: YES | BA58: YES | BB58: YES | BC58: YES | BD58: YES | BE58: Frankfurt-am-Main Flughafen | BF58: Train | BG58: 45943 | BH58: 0.34375 | BI58: ICE316 | BJ58: Frankfurt-am-Main Flughafen | BK58: 45946 | BL58: 0.43402778 | BM58: ICE15 | BN58: 235.98 | BR58: 1 | BS58: 1 | BT58: 1 | BU58: 13/010/2025 | BV58: 45946 | BW58: =BR58+BS58+BT58 -> 3
A59: 14/10 - 15/10 | B59: 45943 | C59: 45946 | D59: 2580 | E59: Accelerating circular action in cities and regions: CCRI support services | F59: Cities building tomorrow | G59: Stand | I59: No | J59: Circular Flanders / Public Flemish Waste Agency | K59: Belgium | M59: Jolien De Graeve ; Simon Gresset | N59: jolien@vlaanderen-circulair.be ; simon.gresset@iclei.org | O59: Circular Flanders / Public Flemish Waste Agency | P59: Programme Manager | Q59: yes | R59: YES | S59: Yes | T59: 2 | U59: Solveig | V59: Stornes | W59: Solveig.Stornes@mrfylke.no | X59: Francisco | Y59: Carvalho | Z59: francisco.carvalho@labpaisagem.pt | AA59: Yes | AB59: 2 | AC59: Solveig | AD59: Stornes | AE59: Solveig.Stornes@mrfylke.no | AF59: Francisco | AG59: Carvalho | AH59: francisco.carvalho@labpaisagem.pt | AI59: Change of lead coordinator for this stand from Elmar Willems to Jolien De Graeve (requested via mail) | AL59: Solveig | AM59: Stornes | AN59: Solveig.Stornes@mrfylke.no | AO59: 0047 097143553 | AP59: N/A | AQ59: YES | AR59: I prefer to travel by plane | AS59: Molde; Norway | AT59: 45943 | AU59: 0.26041667 | AV59: Molde; Norway | AW59: 45947 | AX59: 0.43055556 | AY59: YES | AZ59: I would like to return one day later than the program (17 Oct). The tickets around that time slot are less expensive than the previous day. To Brussels I would like to have the flight that arrives 13.15 in Brussel (Norwegian), and on the return the flight that arrives in Molde 17.15 (SAS). | BA59: YES | BB59: YES | BC59: YES | BD59: YES | BE59: Molde; Norway | BF59: Flight | BG59: 45943 | BH59: 0.375 | BI59: WF1890 | BJ59: Molde; Norway | BK59: 45947 | BL59: 0.58333333 | BM59: WF1891 | BN59: € 388,83 | BR59: 1 | BS59: 1 | BT59: 1 | BU59: 13/010/2025 | BV59: 45946 | BW59: =BR59+BS59+BT59 -> 3 | BZ59: Please confirm if she can return 1 day later (on the 17th) | CA59: Yes, granted the ticket is the same price or below the original ticket offered. No additional night will be covered.
AL60: Francisco | AM60: Carvalho | AN60: francisco.carvalho@labpaisagem.pt | AO60: 351927713863 | AP60: 13-15 | AQ60: YES | AR60: I prefer to travel by plane | AS60: Porto | AT60: 13 | AU60: 9:00AM | AV60: Porto | AW60: 16 | AX60: 0.375 | AY60: YES | BW60: =BR60+BS60+BT60 -> 0 | BZ60: varvesi@aisfor.it
A61: 14/10 - 15/10 | B61: 45943 | C61: 45946 | D61: 2592 | E61: A STEP forward | F61: Cohesion and Growth for the Future | G61: Stand | I61: No | J61: Presidency of the Council of Ministers - Italy | K61: Italy | M61: Simona De Luca ; Gianmarco Guazzo | N61: sim.deluca@governo.it ; gianmarco.guazzo@opencoesione.team | O61: Presidency of the Council of Ministers - Italy | P61: Representative | Q61: yes | R61: yes | S61: Yes | T61: 2 | U61: Simona | V61: De Luca | W61: sim.deluca@governo.it | X61: Gianmarco | Y61: Guazzo | Z61: gianmarco.guazzo@opencoesione.team | AA61: Yes | AB61: 2 | AC61: Simona | AD61: De Luca | AE61: sim.deluca@governo.it | AF61: Gianmarco | AG61: Guazzo | AH61: gianmarco.guazzo@opencoesione.team | AK61: Travelling from ROME | AL61: Simona | AM61: De Luca | AN61: sim.deluca@governo.it | AO61: 393483418950 | AP61: N/A | AQ61: NO | AT61: 45943 | AW61: 45946 | AY61: YES | AZ61: My colleague Gianmarco Guazzo, who's reading us in copy, will be accomodate at the hotel Le Plaza Brussels from 13 to 15 october and, if it is possible, it'll be great for us to stay in the same place. | BW61: =BR61+BS61+BT61 -> 0 | BZ61: Simona de Luca – this standholder only needs accommodation. She has confirmed that she will be traveling from Rome by plane and therefore needs the nights of 13, 14, and 15 October. Could you please confirm if we can offer her all three nights, instead of just two (13 and 14) as we are doing for those coming by train from other cities near Brussels? | CA61: clarifications needed - cf mail
AL62: Gianmarco | AM62: Guazzo | AN62: gianmarco.guazzo@opencoesione.team | AO62: 393454053220 | AP62: N/A | AQ62: YES | AR62: I prefer to travel by plane | AS62: Rome FCO (Fiumicino Airport) | AT62: 45943 | AU62: 0.375 | AV62: Rome FCO (Fiumicino Airport) | AW62: 45946 | AX62: 0.33333333 | AY62: YES | AZ62: I kindly ask you to ensure that the arrival airport (Rome-Brussels) and the departure airport (Brussels-Rome) is the main one (Brussels Airport - Zaventem) and not Charleroi. I would also appreciate it if accommodation could be arranged in the same hotel, or in a nearby hotel, as my colleague Simona De Luca. Thank you. | BA62: YES | BB62: YES | BC62: YES | BD62: YES | BE62: Rome FCO (Fiumicino Airport) | BF62: Flight | BG62: 45943 | BH62: 0.42361111 | BI62: SN3176 | BJ62: Rome FCO (Fiumicino Airport) | BK62: 45946 | BL62: 0.48263889 | BM62: SN4125 | BN62: 410.67 | BR62: 1 | BS62: 1 | BT62: 1 | BU62: 13/010/2025 | BV62: 45946 | BW62: =BR62+BS62+BT62 -> 3
A63: 14/10 - 15/10 | B63: 45943 | C63: 45946 | D63: 2600 | E63: Stay by Choice, Not by Chance: Unlocking smart and green solutions for thriving Mediterranean Communities and Territories | F63: The Right to Stay: unlocking the potential of every territory | G63: Stand | I63: No | J63: The UNEP/MAP regional Activity Center for SCP - MedWaves | K63: Spain | M63: Matias Ibañez ; Jesus Maestro | N63: matiasibanez@gencat.cat ; jesus.maestro@gencat.cat | O63: The UNEP/MAP regional Activity Center for SCP | P63: MedWaves - Head of Unit | BW63: =BR63+BS63+BT63 -> 0 | BZ63: The session coordinator of this stand did not complete the form requesting T&A for any person, and they are now telling us that they would like coverage. I explained to them that in mid-June they received a form that had to be completed and that the deadline for submitting such requests was 30 June, so unfortunately we cannot cover it anymore. They replied with the following: “Thank you for your kind reply. It is very important for us that the T&A is covered. Could you kindly confirm that we submitted the T&A request by June 30?I checked my email exchange, and saw that we sent an email on June 30 to register, but we couldn’t find the form you mentioned in your email, nor were we able to locate it on the platform. As a matter of fact, I have a long email exchange in which I inquired about the T&A, and I even tried calling the EU. On the contrary, I would greatly appreciate it if you could provide guidance on how to resolve this situation. Thank you very much for your help.” I am not aware of any email exchange requesting T&A, as no one has been in contact with us until now, and after checking again, no form was received from them. Could you please advise how we should proceed?
A64: 14/10 - 15/10 | B64: 45943 | C64: 45946 | D64: 2604 | E64: One Borderless Vision: Celebrating 20 Years of EU’s Eastern Cooperation | F64: Cohesion and Growth for the Future | G64: Stand | I64: No | J64: Romania - Ukraine Regional Office for Cross Border Cooperation | K64: Romania | M64: Larisa Dumitrescu ; Cezar Adrian Grozavu | N64: larisa.dumitrescu3@yahoo.com ; cezar.grozavu@brctsuceava.ro | O64: Romania - Ukraine Regional Office for Cross Border Cooperation | P64: Representative | Q64: yes | R64: yes | S64: Yes | T64: 2 | U64: Larisa | V64: Dumitrescu | W64: larisa.dumitrescu@brctsuceava.ro | X64: Alina | Y64: Dobos | Z64: alina.dobos@brctsuceava.ro | AA64: Yes | AB64: 2 | AC64: Larisa | AD64: Dumitrescu | AE64: larisa.dumitrescu@brctsuceava.ro | AF64: Alina | AG64: Dobos | AH64: alina.dobos@brctsuceava.ro | AI64: no comment | AL64: Larisa | AM64: Dumitrescu | AN64: larisa.dumitrescu@brctsuceava.ro | AO64: 40757421909 | AP64: N/A | AQ64: YES | AR64: I prefer to travel by plane | AS64: Suceava | AT64: 45943 | AU64: 0.33333333 | AV64: Brussels | AW64: 45946 | AX64: 0.58333333 | AY64: YES | BA64: YES | BB64: YES | BC64: YES | BD64: YES | BE64: Suceava | BF64: Flight | BG64: 45943 | BH64: 0.26388889 | BI64: W43661 | BJ64: Suceava | BK64: 45946 | BL64: 0.36111111 | BM64: W43662 | BN64: 546.4 | BR64: 1 | BS64: 1 | BT64: 1 | BU64: 13/010/2025 | BV64: 45946 | BW64: =BR64+BS64+BT64 -> 3
AL65: Alina | AM65: VASILICA DOBOȘ | AN65: alina.dobos@brctsuceava.ro | AO65: 40753450170 | AP65: N/A | AQ65: YES | AR65: I prefer to travel by plane | AS65: Suceava | AT65: 45943 | AU65: 0.33333333 | AV65: Brussels | AW65: 45946 | AX65: 0.58333333 | AY65: YES | BA65: YES | BB65: YES | BC65: YES | BD65: YES | BE65: Suceava | BF65: Flight | BG65: 45943 | BH65: 0.26388889 | BI65: W43661 | BJ65: Suceava | BK65: 45946 | BL65: 0.36111111 | BM65: W43662 | BN65: 546.4 | BR65: 1 | BS65: 1 | BT65: 1 | BU65: 13/010/2025 | BV65: 45946 | BW65: =BR65+BS65+BT65 -> 3
A66: 14/10 - 15/10 | B66: 45943 | C66: 45946 | D66: 2620 | E66: Here to Stay: Strengthening Belonging, Equality, and Participation in Europe's Marginalised Territories | F66: The Right to Stay: unlocking the potential of every territory | G66: Stand | I66: No | J66: European Executive Agency for Culture and Education (EACEA) | K66: Belgium | M66: Maria Inmaculada Perez Rocha ; Michela Beati | N66: Maria-Inmaculada.PEREZ-ROCHA@ec.europa.eu ; michela.beati@ec.europa.eu | O66: European Commission - DG JUST | P66: Project Manager | BW66: =BR66+BS66+BT66 -> 0
A67: 14/10 - 15/10 | B67: 45943 | C67: 45946 | D67: 2621 | E67: European Youth Capitals | F67: The Right to Stay: unlocking the potential of every territory | G67: Stand | I67: No | J67: European Youth Forum | K67: Belgium | M67: Vittoria Torrisi ; Francesco Zollo | N67: vittoria.torrisi@youthforum.org ; francesco.zollo@youthforum.org | O67: European Youth Forum | P67: Project Manager | Q67: yes | R67: YES | S67: Yes | T67: 2 | U67: Agnieszka | V67: Parol-Gorna | W67: aparol@lublin.eu | X67: Gabriele | Y67: Stonkiene | Z67: gabriele.stonkiene@klaipeda.lt | AA67: Yes | AB67: 2 | AC67: Agnieszka | AD67: Parol-Gorna | AE67: aparol@lublin.eu | AF67: Gabriele | AG67: Stonkiene | AH67: gabriele.stonkiene@klaipeda.lt | AI67: no comment | AJ67: replaced by Francesco Zoolo Email: francesco.zollo@youthforum.org | AK67: Deadline to complete the form: 5 August - REMINDER SENT 08-08 + 14-08 | AL67: Agnieszka | AM67: Parol-Gorna | AN67: aparol@lublin.eu | AO67: +48515261121 | AP67: EYC session | AQ67: YES | AR67: I prefer to travel by plane | AS67: Warsaw (Chopin) | AT67: 45943 | AU67: 6:50 p.m. | AV67: Warsaw (Chopin) | AW67: 45945 | AX67: 07:35 p.m | AY67: YES | BA67: YES | BB67: YES | BC67: YES | BD67: YES | BE67: Warsaw (Chopin) | BF67: Flight | BG67: 45943 | BH67: 0.43402778 | BI67: LO237 | BJ67: Warsaw (Chopin) | BK67: 45945 | BL67: 0.89930556 | BM67: LO234 | BN67: € 457,70 | BR67: 1 | BS67: 1 | BT67: 0 | BU67: 13/010/2025 | BV67: 45945 | BW67: =BR67+BS67+BT67 -> 2 | BZ67: Please confirm if she can return 1 day before (on the 15th) | CA67: Yes for the 7.30PM one, since we do not know when the other standholder is arriving/leaving
AL68: Gabriele | AM68: Stonkiene | AN68: gabriele.stonkiene@klaipeda.lt | AO68: 37061006946 | AP68: 2621 | AQ68: YES | AR68: I prefer to travel by plane | AS68: Palanga | AT68: 13 th October | AU68: Early morning | AV68: Palanga | AW68: 16 th October | AX68: Evening | AY68: YES | BA68: YES | BB68: YES | BC68: YES | BD68: YES | BE68: Palanga | BF68: Flight | BG68: 45943 | BH68: 0.29166667 | BI68: SK2749/SK549 | BJ68: Palanga | BK68: 45945 | BL68: 0.85416667 | BM68: SK2590 | BN68: € 397,44 | BR68: 1 | BS68: 1 | BT68: 0 | BU68: 13/010/2025 | BV68: 45945 | BW68: =BR68+BS68+BT68 -> 2
A69: 14/10 - 15/10 | B69: 45943 | C69: 45946 | D69: 2634 | E69: ENTRACK: Empowering local and regional authorities to design clean ENergy TRAnsition plans through Capacity and Knowledge building actions | F69: Cities building tomorrow | G69: Stand | I69: No | J69: AISFOR SRL | K69: Italy | M69: Charalampos Chatzimallis ; Marina Varvesi | N69: chatzimallis@gmail.com ; varvesi@aisfor.it | O69: CITIZEN CROSSROADS | P69: Representative | Q69: yes | R69: YES | S69: Yes | T69: 2 | U69: Giulia | V69: Viero | W69: giulia.viero@ieecp.org | X69: Marina | Y69: Varvesi | Z69: varvesi@aisfor.it | AA69: Yes | AB69: 2 | AC69: Giulia | AD69: Viero | AE69: giulia.viero@ieecp.org | AF69: Marina | AG69: Varvesi | AH69: varvesi@aisfor.it | AI69: no comment | AJ69: positive | AK69: from the 13 to the 15 | AL69: Giulia | AM69: Viero | AN69: giulia.viero@ieecp.org | AO69: +39 348 5128247 | AP69: WORKSHOP ENTRACK/PLENTY-life. Date: 14 October 2025 Time: 09:30–10:30 Room: 313–315 + stand in Grand Hall 2, Square Brussels Building | AQ69: YES | AR69: I prefer to travel by plane | AS69: Athens (ATH) | AT69: 45943 | AU69: 8:00 CET (AEGEAN: ATH - BRU) | AV69: Venice (or nearby airport) | AW69: 45946 | AX69: 21:20 (BRU - VCE) | AY69: YES | AZ69: On Thu, 16 Oct, I will arrive in Venice airport at 23:00 with no car/public transport. Since I may need to spend a night at the hotel nearby the airport, would it be possible to leave on Fri, 17 Oct at 10:55 am (BRU - VCE)? If not - I will find a solution. Thank you! | BA69: YES | BB69: YES | BC69: YES | BD69: YES | BE69: Athens (ATH) | BF69: Flight | BG69: 45943 | BH69: 0.33333333 | BI69: A3620 | BJ69: Venice (or nearby airport) | BK69: 45946 | BL69: 0.88888889 | BM69: AZ7659 | BN69: 365.95 | BR69: 1 | BS69: 1 | BT69: 1 | BU69: 13/010/2025 | BV69: 45946 | BW69: =BR69+BS69+BT69 -> 3
AL70: Marina | AM70: Varvesi | AN70: vvarvesi@aisfor.it | AO70: 3356469570 | AP70: Tuesday, 14 October 2025, from 09:30 to 10:30 CET. | AQ70: YES | AR70: I prefer to travel by plane | AS70: rome Italy | AT70: 45943 | AU70: 0.42361111 | AV70: Rome | AW70: 45947 | AX70: 0.78819444 | AY70: YES | AZ70: I will have to stay in Brussels until Friday, the cost of the extra nights will be covered by myself. I have made the booking of a room at the Citybox Brussels where I will be staying for the extra nights - if possible please confirm the room booked at my name | BA70: YES | BB70: YES | BC70: YES | BD70: YES | BE70: Rome | BF70: Flight | BG70: 45943 | BH70: 0.42361111 | BI70: SN3176 | BJ70: Rome | BK70: 45947 | BL70: 0.78819444 | BM70: SN4127 | BN70: € 445,67 | BR70: 1 | BS70: 1 | BT70: 1 | BU70: 13/010/2025 | BV70: 45946 | BW70: =BR70+BS70+BT70 -> 3 | BZ70: Please confirm if we can book the return flight on the 17th. Exta nights will be covered by himself (confirmed by him) | CA70: Ok if the ticket is the same price or below the original ticket offered
A71: 14/10 - 15/10 | B71: 45943 | C71: 45946 | D71: 2640 | E71: Learning through Data, Playing through Stats | F71: Cohesion and Growth for the Future | G71: Stand | I71: No | J71: ISTAT-Italian National Institute of Statistics | K71: Italy | M71: Rina Camporese ; Simona Cafieri | N71: rinacampore00@gmail.com ; cafieri@istat.it | Q71: yes | R71: yes | S71: Yes | T71: 2 | U71: CAFIERI | V71: SIMONA | W71: cafieri@istat.it | X71: TBC | Y71: TBC | Z71: TBC | AA71: Yes | AB71: 2 | AC71: CAFIERI | AD71: SIMONA | AE71: cafieri@istat.it | AF71: TBC | AG71: TBC | AH71: TBC | AI71: the person who answered is "Cafieri Simona" adress email : cafieri@istat.it | AK71: ONLY TRAVEL - TBC | AL71: Simona | AM71: Cafieri | AN71: cafieri@istat.it | AO71: 393358218457 | AP71: stand holder N/A | AQ71: YES | AR71: I prefer to travel by plane | AS71: NAPLES | AT71: 45943 | AU71: 8 | AV71: NAPLES | AW71: 45946 | AX71: 18 | AY71: YES | AZ71: If the stands open on the morning of 13/10, i would like to book the outbound journey for 12/10, otherwise for 13/10. | BA71: YES | BB71: YES | BC71: YES | BD71: YES | BE71: NAPLES | BF71: Flight | BG71: 45943 | BH71: 0.27430556 | BI71: AZ156 | BJ71: NAPLES | BK71: 45946 | BL71: 0.78819444 | BM71: Az165 | BN71: 443.6 | BR71: 1 | BS71: 1 | BT71: 1 | BU71: 13/010/2025 | BV71: 45946 | BW71: =BR71+BS71+BT71 -> 3
AL72: Mariarosario | AM72: Russo | AN72: TBC | AQ72: YES | AY72: NO | BR72: 0 | BS72: 0 | BT72: 0 | BW72: =BR72+BS72+BT72 -> 0
A73: 14/10 - 15/10 | B73: 45943 | C73: 45946 | D73: 2641 | E73: Cities for Just Transition: the future is now | F73: Cities building tomorrow | G73: Stand | I73: No | J73: Managing Authority of the National Programme JTF 2021-2027 and Metro Plus 2021-2027 | K73: Italy | M73: Germana Di Falco ; Raffaele Parlangeli | N73: germana.difalco@gmail.com ; r.parlangeli@governo.it | Q73: yes | R73: YES | S73: Yes | T73: 2 | U73: Maria | V73: Stassi | W73: m.stassi@pcm.gov.it | X73: Valeria | Y73: Sciucchini | Z73: v.sciucchini@pcm.gov.it | AA73: Yes | AB73: 2 | AC73: Maria | AD73: Stassi | AE73: m.stassi@pcm.gov.it | AF73: Valeria | AG73: Sciucchini | AH73: v.sciucchini@pcm.gov.it | AI73: no comment | AL73: Maria | AM73: Stassi | AN73: m.stassi@pcm.gov.it | AO73: 393473444705 | AP73: N/A | AQ73: YES | AR73: I have no preference regarding the mode of transport – please make a suggestion | AS73: Rome | AT73: 45943 | AU73: morning | AV73: Rome | AW73: 45946 | AX73: early afternoon | AY73: YES | BA73: YES | BB73: YES | BC73: YES | BD73: YES | BE73: Rome | BF73: Flight | BG73: 45943 | BH73: 0.42361111 | BI73: SN3176 | BJ73: Rome | BK73: 45946 | BL73: 0.62152778 | BM73: SN3181 | BN73: 347.67 | BR73: 1 | BS73: 1 | BT73: 1 | BU73: 13/010/2025 | BV73: 45946 | BW73: =BR73+BS73+BT73 -> 3
AL74: Valeria | AM74: Sciucchini | AN74: v.sciucchini@pcm.gov.it | AO74: 393290073740 | AP74: NA | AQ74: YES | AR74: I prefer to travel by plane | AS74: ROMA | AT74: 45943 | AU74: from 9am | AV74: ROMA | AW74: 45945 | AX74: from 8pm | AY74: YES | AZ74: if the last plane of the evening for Rome is not available, preference goes to a plane on the morning of 16/10 | BA74: YES | BB74: YES | BC74: YES | BD74: YES | BE74: Rome | BF74: Flight | BG74: 45943 | BH74: 0.42361111 | BI74: SN3176 | BJ74: Rome | BK74: 45945 | BL74: 0.86805556 | BM74: U22983 | BN74: € 427,00 | BR74: 1 | BS74: 1 | BT74: 0 | BU74: 13/010/2025 | BV74: 45945 | BW74: =BR74+BS74+BT74 -> 2
A75: 14/10 - 15/10 | B75: 45943 | C75: 45946 | D75: 2666 | E75: Visualising Communities’ Stakes in the Just Transition: Policy, Plausible, and Preferred Futures | F75: Cohesion and Growth for the Future | G75: Stand | I75: No | J75: Delft University of Technology | K75: Netherlands | M75: Samir Amin; Neli Georgieva | N75: amin@isocarp-institute.org ; neli.georgieva@strath.ac.uk | O75: Institute for Urban Excellence | P75: Project Manager | BW75: =BR75+BS75+BT75 -> 0
A76: 14/10 - 15/10 | B76: 45943 | C76: 45946 | D76: 2670 | E76: Discover the EIB support for your city or region! | F76: Cohesion and Growth for the Future | G76: Stand | I76: No | J76: European Investment Bank Group | K76: Luxembourg | M76: Bianca Faragau Souza Tavares ; Massimo Marra | N76: b.faragau@eib.org ; m.marra@eib.org | O76: European Investment Bank | P76: Representative | BW76: =BR76+BS76+BT76 -> 0
A77: 14/10 - 15/10 | B77: 45943 | C77: 45946 | D77: 2675 | E77: The EU Tourism Platform: for a more competitive, sustainable travel sector | F77: The Right to Stay: unlocking the potential of every territory | G77: Stand | I77: No | J77: European Commission - DG MOVE | K77: Belgium | M77: Balint Rippert ; Elina Zempili | N77: balint.rippert@pwc.com ; balint.rippert@gmail.com ; elina.zempili@pwc.com | O77: European Commission - DG MOVE | P77: Representative | Q77: yes | R77: yes | S77: Yes | T77: 2 | U77: Balint | V77: Rippert | W77: balint.rippert@pwc.com | X77: Vasiliki | Y77: Vorropoulou | Z77: vasiliki.vorropoulou@pwc.com | AA77: Yes | AB77: 2 | AC77: Balint | AD77: Rippert | AE77: balint.rippert@pwc.com | AF77: Vasiliki | AG77: Vorropoulou | AH77: vasiliki.vorropoulou@pwc.com | AI77: no comment | AL77: Balint | AM77: Rippert | AN77: balint.rippert@pwc.com | AO77: 36308693910 | AP77: N/A | AQ77: YES | AR77: I prefer to travel by plane | AS77: Budapest | AT77: 45943 | AU77: 06:35 | AV77: Budapest | AW77: 45946 | AX77: 21:05 | AY77: YES | BA77: YES | BB77: YES | BC77: YES | BD77: YES | BE77: Budapest | BF77: Flight | BG77: 45943 | BH77: 0.27430556 | BI77: SN2830 | BJ77: Budapest | BK77: 45946 | BL77: 0.87847222 | BM77: SN2829 | BN77: 484.69 | BR77: 1 | BS77: 1 | BT77: 1 | BU77: 13/010/2025 | BV77: 45946 | BW77: =BR77+BS77+BT77 -> 3
AL78: Vasiliki | AM78: Vorropoulou | AN78: vasiliki.vorropoulou@pwc.com | AO78: 306943069126 | AP78: N/A | AQ78: YES | AR78: I prefer to travel by plane | AS78: Athens | AT78: 45943 | AU78: 08.00 | AV78: Athens | AW78: 45946 | AX78: 20.00 | AY78: YES | BA78: YES | BB78: YES | BC78: YES | BD78: YES | BE78: Athens | BF78: Flight | BG78: 45943 | BH78: 0.33333333 | BI78: a3 620 | BJ78: Athens | BK78: 45946 | BL78: 0.83333333 | BM78: a3 623 | BN78: 216.95 | BR78: 1 | BS78: 1 | BT78: 1 | BU78: 13/010/2025 | BV78: 45946 | BW78: =BR78+BS78+BT78 -> 3
A79: 14/10 - 15/10 | B79: 45943 | C79: 45946 | D79: 2728 | E79: European Committee of the Regions EURW Stand | F79: Cohesion and Growth for the Future | G79: Stand | I79: No | J79: European Committee of the Regions | K79: Belgium | M79: Violeta Tomas Gutierrez ; Caroline Parmentier | N79: Violeta.TomasGutierrez@cor.europa.eu; Caroline.PARMENTIER@ec.europa.eu | BW79: =BR79+BS79+BT79 -> 0
A80: 14/10 - 15/10 | B80: 45943 | C80: 45946 | D80: 2123 | E80: Bridging Urban and Rural: Hungary’s New Functional Urban Area Model | F80: The Right to Stay: unlocking the potential of every territory | G80: Stand | H80: 2123,2406 | I80: Yes | J80: MFOI - Hungarian Development Promotion Office | K80: Hungary | M80: Bence Cseke; Elina Heredi | N80: bence.cseke@mfoi.org ; elina.heredi@mfoi.org | O80: Hungarian Development Promotion Office | P80: Project Manager | Q80: Yes | R80: yes | S80: Yes | T80: 2 | U80: Bence | V80: Cseke | W80: bence.cseke@mfoi.org | X80: Mária Emese | Y80: Viszoczky (dr.) | Z80: viszoczky.emese@maltai.hu | AA80: Yes | AB80: 2 | AC80: Bence | AD80: Cseke | AE80: bence.cseke@mfoi.org | AF80: Mária Emese | AG80: Viszoczky (dr.) | AH80: viszoczky.emese@maltai.hu | AI80: No comment | AL80: Bence | AM80: Cseke | AN80: bence.cseke@mfoi.org | AO80: 36305816989 | AP80: N/A | AQ80: YES | AR80: I prefer to travel by plane | AS80: Zagreb | AT80: 45942 | AU80: 0.45833333 | AV80: Zagreb | AW80: 45946 | AX80: 0.66666667 | AY80: YES | BA80: YES | BB80: YES | BC80: YES | BD80: YES | BE80: Zagreb | BF80: Flight | BG80: 45943 | BH80: 0.28472222 | BI80: OU456 | BJ80: Zagreb | BK80: 45945 | BL80: 0.85416667 | BM80: OU4457 | BN80: € 325,84 | BR80: 1 | BS80: 1 | BT80: 0 | BU80: 13/010/2025 | BV80: 45945 | BW80: =BR80+BS80+BT80 -> 2 | BZ80: Please confirm if it is possible to book the flight on the 12 (instead of 13). We would inform him that he would need to pay the extra night on the 12th | CA80: Ok if the ticket is the same price or below the original ticket offered
AL81: Mária Emese | AM81: Viszoczky (dr.) | AN81: viszoczky.emese@maltai.hu | AO81: 0036706663608 | AP81: N/A | AQ81: YES | AR81: I prefer to travel by plane | AS81: Budapest | AT81: 45943 | AU81: Afternoon | AV81: Budapest | AW81: 45946 | AX81: Evening | AY81: YES | BA81: YES | BB81: YES | BC81: YES | BD81: YES | BE81: Budapest | BF81: Flight | BG81: 45943 | BH81: 0.75 | BI81: SN2826 | BJ81: Budapest | BK81: 45945 | BL81: 0.87847222 | BM81: Sn2829 | BR81: 1 | BS81: 1 | BT81: 0 | BU81: 13/010/2025 | BV81: 45945 | BW81: =BR81+BS81+BT81 -> 2
A82: 14/10 - 15/10 | B82: 45943 | C82: 45946 | D82: 2257 | E82: CINEA – Funding a greener future for Europe | F82: Cohesion and Growth for the Future | G82: Stand | H82: 22572267 | I82: Yes | J82: European Climate, Infrastructure and Environment Executive Agency | K82: Belgium | M82: Sara Gayarre Lete ; Oana Barbulete | N82: Sara.GAYARRE-LETE@ec.europa.eu; Oana.BARBULETE@ec.europa.eu | O82: European Climate, Infrastructure and Environment Executive Agency | P82: Representative | BW82: =BR82+BS82+BT82 -> 0
A83: 14/10 - 15/10 | B83: 45943 | C83: 45946 | D83: 2299 | E83: Building a future @ home: Interreg for the right to stay along the EU's external borders | F83: The Right to Stay: unlocking the potential of every territory | G83: Stand | H83: 22372299 | I83: Yes | J83: Particip GmbH - TESIM | K83: Germany | M83: Volha Prokharava ; Daniela Cavini | N83: volha.prokharava@tesim-cbc.eu; daniela.cavini@tesim-cbc.eu | O83: Particip GmbH - TESIM | P83: Expert | BW83: =BR83+BS83+BT83 -> 0
D84: Total | Q84: Total | T84: Total | AB84: Total | BN84: =SUM(BN3:BN83) -> 8072.86
D85: 54 | Q85: 28 | T85: =SUM(T3:T83) -> 50 | AB85: =SUM(AB3:AB83) -> 51 | BN85: Total rooms used | BR85: =SUM(BR3:BR83) -> 43 | BS85: =SUM(BS3:BS83) -> 43 | BT85: =SUM(BT3:BT83) -> 31
BN86: Rooms not used | BR86: 1 | BS86: 1 | BT86: 13
B88: TRAVEL | D88: ACCOMODATION
B89: Arrival | C89: Departure | D89: Arrival | E89: Departure | M89: Departure | BL89: =Sessions!BV117+Stands!BN84+Tastings!BL22+Journalists!AL65+'Jury members'!AG19 -> 55786.33
A90: 45943 | B90: 52 | C90: 0 | D90: 53 | E90: 0
A91: 45944 | B91: 0 | C91: 0 | D91: 0 | E91: 0
A92: 45945 | B92: 0 | C92: 0 | D92: 0 | E92: 0
A93: 45946 | B93: 0 | C93: 52 | D93: 0 | E93: 50 | M93: 53
B94: 52 | C94: 52 | D94: 53 | E94: 50 | M94: 53
B96: ACCOMODATION
B97: 45943 | C97: 45944 | D97: 45945
A98: Session coordinators form | B98: 53 | C98: 53 | D98: 53
A99: Number of stand holders confirmed by session coordinators before deadline 1 August | B99: 48 | C99: 48 | D99: 48
A100: Nights already confirmed by stand holders | B100: 41 | C100: 41 | D100: 32

Sheet Tastings
A1: TASTING INFORMATION | AJ1: TASTING PREFERENCES | AY1: FOLLOW-UP | BC1: Travel information - confirmed | BX1: APPROVALS
A2: Date | B2: Slot | C2: Estimated arrival date | D2: Estimated departure date | E2: Index unique | F2: Title | G2: Thematic clusters | H2: Lead partner organisation name | I2: Lead partner organisation country of origin | J2: Coordinator | K2: Email address | L2: Company name | M2: Job title | N2: Speakers | O2: Answered | P2: Do any of your project members require travel coverage? | Q2: Form sent | R2: Number of speakers needed for travel | S2: Travel - Speaker 1 - Name | T2: Travel - Speaker 1 - Name + last name | U2: Travel - Speaker 1 - Email address | V2: Travel - Speaker 2 - Name | W2: Travel - Speaker 2 - Name + last name | X2: Travel - Speaker 2 - Email address | Y2: Do any of your speakers require accommodation coverage? | Z2: Number of speaker needed for accommodation | AA2: Accomodation - Speaker 1 - Name | AB2: Accomodation - Speaker 1 - Last name | AC2: Accomodation - Speaker 1 - Email address | AD2: Accomodation - Speaker 2 - Name | AE2: Accomodation - Speaker 2 - Last name | AF2: Accomodation - Speaker 2 - Email address | AG2: Additional comments | AH2: Email follow up - Responses | AI2: Comments VO | AJ2: First Name | AK2: Last name | AL2: Email address | AM2: Phone number | AN2: Date and time of your speaking slot | AO2: Travel needed | AP2: Preferred mode of transport | AQ2: City of departure | AR2: Date of departure | AS2: Time of departure | AT2: Return city | AU2: Preferred date of return | AV2: Preferred time of return | AW2: Accommodation needed | AX2: Additional comments | AY2: Agency sent proposal | AZ2: Guest confirmed proposal | BA2: Travel booked | BB2: Travel tickets sent to guest | BC2: Origin City (to Brussels) | BD2: Flight/Train | BE2: Date of departure | BF2: Flight/Train time | BG2: Flight number/Train | BH2: Return City (from Brussels) | BI2: Date of return | BJ2: Flight/Train time | BK2: Flight number/Train | BL2: Flight/Train cost | BM2: Hotel rate 13/10, €, excl. VAT | BN2: Hotel rate 14/10, €, excl. VAT | BO2: Hotel rate 15/10, €, excl. VAT | BP2: 45943 | BQ2: 45944 | BR2: 45945 | BS2: Check-in date | BT2: Check out date | BU2: Hotel nights | BV2: Hotel cost, €, excl. VAT | BW2: Total cost, € | BX2: Client's approval needed | BY2: Client's approval received | BZ2: Approval reason
A3: 45944 | B3: 19:00 - 23:00 | C3: 45943 | D3: 45945 | E3: 2129 | F3: Prykarpattia — where Ukraine’s taste begins! | G3: The Right to Stay: unlocking the potential of every territory | H3: Regional Development Agency of Ivano-Frankivsk region | I3: Ukraine | J3: Tetiana Zbyrak ; Yulia Haiduk | K3: tetyana.zbyrak@gmail.com ; yulkagay@gmail.com | L3: Regional Development Agency of Ivano - Frankivsk region | M3: Deputy Director | N3: Tetiana Kozak - - - - | O3: Yes | P3: Yes | Q3: yes | R3: 2 | S3: Tetiana | T3: Zbyrak | U3: tetyana.zbyrak@gmail.com | V3: Yuliia | W3: Haiduk | X3: yulkagay@gmail.com | Y3: Yes | Z3: 2 | AA3: Tetiana | AB3: Zbyrak | AC3: tetyana.zbyrak@gmail.com | AD3: Yuliia | AE3: Haiduk | AF3: yulkagay@gmail.com | AG3: No comment | AH3: positive | AI3: they will need t&a from 13 to 15 | AJ3: Tetiana | AK3: Zbyrak | AL3: tetyana.zbyrak@gmail.com | AM3: 380993028958 | AN3: 14-Oct 19:00 - 23:00 | AO3: YES | AP3: I prefer to travel by plane | AQ3: Rzeszów (PL) | AR3: 45943 | AS3: 8:00-12:00 | AT3: Rzeszów (PL) | AU3: 45946 | AV3: 16:00-19:00 | AW3: YES | AY3: YES | AZ3: YES | BA3: YES | BB3: YES | BC3: Rzeszów (PL) | BD3: Flight | BE3: 45943 | BF3: 0.51388889 | BG3: sn2548 | BH3: Rzeszów (PL) | BI3: 45946 | BJ3: 0.81944444 | BK3: lh5583-1626 | BL3: 544.81 | BP3: 1 | BQ3: 1 | BS3: 45943 | BT3: 45945 | BU3: 2 | BX3: Please confirm whether we can book the return flight on the 16th, informing him that we will not cover the extra night (15) | BY3: Ok to cover return on 16 October if travel price is the same or lower than the one originally offered. No extra accommodation will be covered
AJ4: Yuliia | AK4: Haiduk | AL4: yulkagay@gmail.com | AM4: 380968184146 | AN4: 14-Oct 19:00 - 23:00 | AO4: YES | AP4: I prefer to travel by plane | AQ4: Rzeszów (PL) | AR4: 45943 | AS4: 8:00-12:00 | AT4: Rzeszów (PL) | AU4: 45946 | AV4: 16:00-19:00 | AW4: YES | AY4: YES | AZ4: YES | BA4: YES | BB4: YES | BC4: Rzeszów (PL) | BD4: Flight | BE4: 45943 | BF4: 0.51388889 | BG4: sn2548 | BH4: Rzeszów (PL) | BI4: 45946 | BJ4: 0.81944444 | BK4: lh5583-1626 | BL4: 544.81 | BP4: 1 | BQ4: 1 | BS4: 45943 | BT4: 45945 | BU4: 2 | BX4: Please confirm whether we can book the return flight on the 16th, informing him that we will not cover the extra night (15) | BY4: Ok to cover return on 16 October if travel price is the same or lower than the one originally offered. No extra accommodation will be covered
A5: 45944 | B5: 19:00 - 23:00 | C5: 45943 | D5: 45945 | E5: 2415 | F5: Taste Nicosia | G5: The Right to Stay: unlocking the potential of every territory | H5: Nicosia Tourism Board | I5: Cyprus | J5: Sotiris Christoforou ; Angeliki Vasileiadou | K5: s.christoforou@ccci.org.cy ; info@visitnicosia.com.cy | L5: Nicosia Tourism Board | M5: Representative | N5: theodoros Kringou - Nicosia Tourism Board - President - - | O5: Yes | P5: Yes | Q5: yes | R5: 2 | S5: Sotiris | T5: Christoforou | U5: s.christoforou@ccci.org.cy | V5: Angeliki | W5: Vasileiadou | X5: info@visitnicosia.com.cy | Y5: Yes | Z5: 2 | AA5: Sotiris | AB5: Christoforou | AC5: s.christoforou@ccci.org.cy | AD5: Angeliki | AE5: Vasileiadou | AF5: info@visitnicosia.com.cy | AG5: Can we receive any logists costs coverage like transportation of foodies? | AH5: positive | AI5: Deadline to complete the form: 31 July - REMINDER SENT 08-08 + 14/08 | AJ5: Simon | AK5: Saracino | AL5: s.saracino@ccci.org.cy | AM5: +39 3513794535 | AN5: 14-Oct 19:00 - 23:00 | AO5: YES | AP5: I prefer to travel by plane | AQ5: Larnaca | AR5: 45942 | AS5: Morning hours | AT5: Larnaca | AU5: 45946 | AV5: After 2pm if possible | AW5: Yes (If Yes, we will book accommodation according to your speaking slot) | AX5: For the extra two days of accommodation of 12th and 16th we can the pay the difference of price please also inform us of the hotel name. | AY5: YES | BC5: Larnaca | BH5: Larnaca | BX5: Please confirm whether we can book the return flight on the 16th, informing him that we will not cover the extra night (15)
AJ6: Angeliki | AK6: Vasileiadou | AL6: info@visitnicosia.com.cy | AM6: 35795549700 | AN6: 14-Oct 19:00 - 23:00 | AO6: YES | AP6: I prefer to travel by plane | AQ6: Larnaca | AR6: 45942 | AS6: Morning hours | AT6: Larnaca | AU6: 45946 | AV6: After 2pm if possible | AW6: Yes (If Yes, we will book accommodation according to your speaking slot) | AX6: for the extra two days of accommodation 12 and 16 we can pay the change of price, please also inform us of the hotel name. | AY6: YES | AZ6: YES | BA6: YES | BB6: YES | BC6: Larnaca | BD6: Flight | BE6: 45942 | BF6: 0.59722222 | BG6: os838-355 | BH6: Larnaca | BI6: 45946 | BJ6: 0.40972222 | BK6: os352-831 | BL6: 531.6 | BP6: 1 | BQ6: 1 | BX6: Please confirm whether we can book the return flight on the 16th, informing him that we will not cover the extra night (15)
A7: 45944 | B7: 19:00 - 23:00 | C7: 45943 | D7: 45945 | E7: 2589 | F7: The Fish Knows Everything: An experience by the Hamburg pilot of Bauhaus of the Seas Sails | G7: The Right to Stay: unlocking the potential of every territory | H7: Magellan Circle | I7: Portugal | J7: Andrea Hrzic ; Nuno Jardim | K7: andrea.hrzic@magellancircle.eu ; nunojnunes@tecnico.ulisboa.pt | L7: Magellan Circle | M7: Representative | N7: Katinka Versendaal - The Eatelier - CEO - - | O7: yes | P7: Yes | Q7: yes + reminder 1 TBC | R7: 2 | S7: Katinka | T7: Versendaal | U7: katinka@the-eatelier.com | V7: TBC | W7: TBC | X7: TBC | Y7: Yes | Z7: 2 | AA7: Katinka | AB7: Versendaal | AC7: katinka@the-eatelier.com | AD7: TBC | AE7: TBC | AF7: TBC | AG7: no comment | AJ7: Katinka | AK7: Versendaal | AL7: katinka@the-eatelier.com | AM7: +31643750783 | AN7: 14-Oct 19:00 - 23:00 | AO7: NO | AR7: 45944 | AU7: 45945 | AW7: YES | AY7: YES | AZ7: YES | BA7: YES | BB7: YES | BC7: Eindhoven | BD7: CAR | BE7: CAR | BF7: CAR | BG7: CAR | BH7: Eindhoven | BI7: CAR | BJ7: CAR | BK7: CAR | BL7: CAR | BP7: 0 | BQ7: 1 | BS7: 45944 | BT7: 45945 | BU7: 1 | BX7: This tasting still had 1 of the 2 people who needed T&A as TBC. Last week, they confirmed their name and requested travel & accommodation coverage, and informed us that the other person (already confirmed and who initially needed both T&A) would finally only require accommodation, as she would come by car with the food. After consulting with Shadi, we told them that we would accept covering T&A for the confirmed person after the deadline as an exception, and that we would therefore cover the night of 14 October for the person coming by car. She appreciated our decision, and now, when confirming to the person who only needs accommodation that we would cover the night of 14 October, she is asking us to also cover the night of the 13th, claiming that: she still needs a full day of prepping on 14th October. Could you please confirm if we can also cover the night of the 13th, considering that we have available rooms according to the latest recap I prepared on Friday? Additionally, this person is asking if they can be reimbursed for traveling by car. Can you confirm if this is possible? | BY7: Since the tasting begins at 19:00 on 14 October and Eindhoven is only a two-hour drive from Brussels, arriving on 13 October does not appear to be justified. As mentioned during the Partners’ meeting, we do not cover the transportation of food/material for tastings (ref. presentation), we will therefore not reimburse the car travel in this case. If she prefers, we could buy her a train ticket for her to use instead.
AJ8: Frederico | AK8: Duarte | AL8: frederico.duarte@tecnico.ulisboa.pt | AM8: 3516313206 | AN8: 14-Oct 19:00 - 23:00 | AO8: YES | AP8: I prefer to travel by plane | AQ8: Lisbon | AR8: 45943 | AS8: Morning | AT8: Lisbon | AU8: 45945 | AV8: Evening | AW8: YES | AY8: YES | AZ8: YES | BA8: YES | BB8: YES | BC8: Lisbon | BD8: Flight | BE8: 45943 | BF8: 0.30208333 | BG8: tp640 | BH8: Lisbon | BI8: 45945 | BJ8: 0.87152778 | BK8: tp645 | BL8: 425.32 | BP8: 1 | BQ8: 1
A9: 45944 | B9: 19:00 - 23:00 | C9: 45943 | D9: 45945 | E9: 1990 | F9: Gastronomic Heritage of the Peloponnese | G9: Cohesion and Growth for the Future | H9: Region of Peloponnese | I9: Greece | J9: Ioanna Lampropoulou ; Antonios Psarakis | K9: ilampropoulou@mou.gr ; apsarakis@mou.gr | L9: Region of Peloponnese | M9: Representative | N9: ANTONIOS PSARAKIS - MANAGING AUTHORITY OF PROGRAMME PELOPONNESE - Director - - ; DIMITRIOS BOURIS - MANAGING AUTHORITY OF PROGRAMME PELOPONNESE - Representative - - | O9: yes | P9: Yes | Q9: yes | R9: 2 | S9: DIMITRIOS | T9: BOURIS | U9: dmpouris@yahoo.gr | V9: KONSTANTINOS | W9: MAKAROUNIS | X9: kmakarounis@ppel.gov.gr | Y9: Yes | Z9: 2 | AA9: DIMITRIOS | AB9: BOURIS | AC9: dmpouris@yahoo.gr | AD9: KONSTANTINOS | AE9: MAKAROUNIS | AF9: kmakarounis@ppel.gov.gr | AG9: no comment | AJ9: DIMITRIOS | AK9: BOURIS | AL9: dmpouris@yahoo.gr | AM9: +306945559565 | AN9: 14-Oct 19:00 - 23:00 | AO9: YES | AP9: I prefer to travel by plane | AQ9: ATHENS | AR9: 45943 | AS9: 0.33333333 | AT9: ATHENS | AU9: 45945 | AV9: 0.91666667 | AW9: YES | AY9: YES | AZ9: YES | BA9: YES | BB9: YES | BC9: ATHENS | BD9: Flight | BE9: 45943 | BF9: 0.33333333 | BG9: a3 620 | BH9: ATHENS | BI9: 45945 | BJ9: 0.83333333 | BK9: a3 623 | BL9: 448.95 | BP9: 1 | BQ9: 1 | BS9: 45943 | BT9: 45945 | BU9: 2
AJ10: KONSTANTINOS | AK10: MAKAROUNIS | AL10: kmakarounis@ppel.gov.gr | AM10: 306074842431 | AN10: 14-Oct 19:00 - 23:00 | AO10: YES | AP10: I prefer to travel by plane | AQ10: ATHENS | AR10: 45943 | AS10: 0.33333333 | AT10: ATHENS | AU10: 45945 | AV10: 0.91666667 | AW10: YES | AY10: YES | AZ10: YES | BA10: YES | BB10: YES | BC10: ATHENS | BD10: Flight | BE10: 45943 | BF10: 0.33333333 | BG10: a3 620 | BH10: ATHENS | BI10: 45945 | BJ10: 0.83333333 | BK10: a3 623 | BL10: 448.95 | BP10: 1 | BQ10: 1 | BS10: 45943 | BT10: 45945 | BU10: 2
A11: 45944 | B11: 19:00 - 23:00 | C11: 45943 | D11: 45945 | E11: 2531 | F11: Moldova without Borders: One Heart, One Path | G11: The Right to Stay: unlocking the potential of every territory | H11: Iasi County Council | I11: Romania | J11: Costel Alexe ; Iurie Levinschi | K11: costel.alexe@gmail.com ; presedinte@hincesti.md | L11: Iasi County Council | M11: President | N11: ANA-ROXANA SLEMCO - North-East Regional Development Agency - Director - - | O11: yes | P11: Yes | Q11: yes | R11: 2 | S11: Andrei | T11: Podeanu | U11: Contact@afumatorianoastra.ro | V11: Nicolae | W11: Sterbet | X11: consiliul@hincesti.md | Y11: Yes | Z11: 2 | AA11: Andrei | AB11: Podeanu | AC11: Contact@afumatorianoastra.ro | AD11: Nicolae | AE11: Sterbet | AF11: consiliul@hincesti.md | AG11: no comment | AH11: positive | AI11: they will need t&a | AJ11: Andrei | AK11: Podeanu | AL11: Contact@afumatorianoastra.ro | AM11: 40757242424 | AN11: 14-Oct 19:00 - 23:00 | AO11: YES | AP11: I prefer to travel by plane | AQ11: Iasi | AR11: 45943 | AS11: Anytime | AT11: Iasi | AU11: 45945 | AV11: Anytime | AW11: YES | AY11: YES | BC11: Iasi | BD11: Flight | BH11: Iasi
AJ12: Nicolai | AK12: Şterbeţ | AL12: consiliul@hincesti.md | AM12: 373 60601106 | AN12: 14-Oct 19:00 - 23:00 | AO12: YES | AP12: I prefer to travel by plane | AQ12: Chisinau, RMO | AR12: 45943 | AS12: 8.00 A.M | AT12: Chisinau | AU12: 45945 | AV12: 17.00 | AW12: YES | AY12: YES | BC12: Chisinau, RMO | BD12: Flight | BH12: Chisinau, RMO
